Workbook
Name _56F9DC9755BA473782653E2940F9FormId: "eLGl-_E6IESWa79RY-ax2iuoN7rWI-dLhfbHv3sOlYFUM0Y0RTFLQTE3WUtYV1pQOTgwNUEySkFJSiQlQCN0PWcu"
Name _56F9DC9755BA473782653E2940F9ResponseSheet: "Form1"
Name _56F9DC9755BA473782653E2940F9SourceDocId: "{f62d1b90-5b8b-47b9-9246-cc08b8118503}"

Sheet SEC.EXEC.
A1: ACOMPANHAMENTO EXECUÇÃO GESTÃO - 2024
A2: UNIDADE | B2: AÇÃO | C2: PO | D2: INICIATIVAS | E2: GRUPO DE DESPESAS | F2: DOTAÇÃO ATUALIZADA | G2: PROGRAMADO 2024 | H2: EMPENHADO 2024 | I2: LIQUIDADO 2024 | J2: PAGO 2024 | K2: OBSERVAÇÃO (PENDÊNCIAS)
A4: SECRETARIA EXECUTIVA | B4: 2000 | C4: 0000 | D4: Administração da unidade- Despesas diversas | E4: Despesas correntes | F4: 18899295 | G4: 18899295 | H4: 17466044 | I4: 10669894 | J4: 10420389 | K4: A pedido do CCAL, foi realizada uma troca de PO do 0000 para o 000B no valor de 400 mil As programações dos dois POS devem ser ajustadas para refletir a dotação existente (R$ 175.674,00 utilizados para Diaspora)
B5: 2000 | C5: 0000 | E5: Investimento | F5: 200000 | G5: 200000 | H5: 11925 | I5: 11925 | J5: 11925
B6: Subtotal PO 0000 | F6: =SUBTOTAL(109,F4:F5) -> 19099295 | G6: =SUBTOTAL(109,G4:G5) -> 19099295 | H6: =SUBTOTAL(109,H4:H5) -> 17477969 | I6: =SUBTOTAL(109,I4:I5) -> 10681819 | J6: =SUBTOTAL(109,J4:J5) -> 10432314
B7: 2000 | C7: 0007 | D7: Capacitação de Servidores Públicos Federais em Processo de Qualificação e Requalificação | E7: Despesas correntes | F7: 317309 | G7: 317309 | H7: 288403.67 | I7: 132525.97 | J7: 132525.97 | K7: Previsão de gastos até o fim de 2024, com cursos de idiomas, congressos, GECC, dentre outros. Fazer num pedido de recomposição de R$182.691 devido ao remanejamento realizado em julho
B8: Subtotal PO 0007 | F8: =SUBTOTAL(109,F7) -> 317309 | G8: =SUBTOTAL(109,G7) -> 317309 | H8: =SUBTOTAL(109,H7) -> 288403.67 | I8: =SUBTOTAL(109,I7) -> 132525.97 | J8: =SUBTOTAL(109,J7) -> 132525.97
B9: 2000 | C9: 000B | D9: Ajuda de custo (mobilização e desmobilização) | E9: Despesas correntes | F9: 642128 | G9: 642128 | H9: 318961.74 | I9: 279889.08 | J9: 279889.08 | K9: Ajuste do valor tendo em vistas novas nomeações/exonerações
B10: Subtotal PO 000B | F10: =SUBTOTAL(109,F9) -> 642128 | G10: =SUBTOTAL(109,G9) -> 642128 | H10: =SUBTOTAL(109,H9) -> 318961.74 | I10: =SUBTOTAL(109,I9) -> 279889.08 | J10: =SUBTOTAL(109,J9) -> 279889.08
B11: 2000 | C11: 000C | D11: Ajuda de custo para Estagiários | E11: Despesas correntes | F11: 275980 | G11: 275980 | H11: 220673 | I11: 176534.71 | J11: 149203.18 | K11: Valor para pagamento de bolsas de estágiarios até o final de 2024
B12: Subtotal PO 000C | F12: =SUBTOTAL(109,F11) -> 275980 | G12: =SUBTOTAL(109,G11) -> 275980 | H12: =SUBTOTAL(109,H11) -> 220673 | I12: =SUBTOTAL(109,I11) -> 176534.71 | J12: =SUBTOTAL(109,J11) -> 149203.18
B13: 2000 | C13: 000F | D13: Integração e Aquisição de Tecnologia da Informação | E13: Despesas correntes | F13: 1184630 | G13: 758630 | H13: 522239.82 | I13: 343712.07 | J13: 343712.07
B14: 2000 | C14: 000F | E14: Investimento | F14: 200000 | G14: 200000
B15: Subtotal PO 000F | F15: =SUBTOTAL(109,F13:F14) -> 1384630 | G15: =SUBTOTAL(109,G13:G14) -> 958630 | H15: =SUBTOTAL(109,H13:H14) -> 522239.82 | I15: =SUBTOTAL(109,I13:I14) -> 343712.07 | J15: =SUBTOTAL(109,J13:J14) -> 343712.07
B16: 2000 | C16: 0010 | D16: Conservação de Ativos da União | E16: Despesas correntes | F16: 0 | K16: Valor integral oferecido para cancelamento
B17: Subtotal PO 0010 | F17: =SUBTOTAL(109,F16) -> 0 | G17: =SUBTOTAL(109,G16) -> 0 | H17: =SUBTOTAL(109,H16) -> 0 | I17: =SUBTOTAL(109,I16) -> 0 | J17: =SUBTOTAL(109,J16) -> 0
B18: Subtotal Ação 2000 | F18: =SUBTOTAL(109,F4:F17) -> 21719342 | G18: =SUBTOTAL(109,G4:G17) -> 21293342 | H18: =SUBTOTAL(109,H4:H17) -> 18828247 | I18: =SUBTOTAL(109,I4:I17) -> 11614481 | J18: =SUBTOTAL(109,J4:J17) -> 11337644
B19: 216h | C19: 0000 | D19: Auxilio Moradia servidores publicos | E19: Despesas Correntes | F19: 1408000 | G19: 1408000 | H19: 1408000 | I19: 839440.91 | J19: 759653.77
B20: Subtotal Ação 216H | F20: =SUBTOTAL(109,F19) -> 1408000 | G20: =SUBTOTAL(109,G19) -> 1408000 | H20: =SUBTOTAL(109,H19) -> 1408000 | I20: =SUBTOTAL(109,I19) -> 839440.91 | J20: =SUBTOTAL(109,J19) -> 759653.77
B21: 4641 | C21: 0000 | D21: Publicidade de Utilidade Pública | E21: Despesas correntes | F21: 454769
B22: Subtotal Ação 4641 | F22: =SUBTOTAL(109,F21) -> 454769 | G22: =SUBTOTAL(109,G21) -> 0 | H22: =SUBTOTAL(109,H21) -> 0 | I22: =SUBTOTAL(109,I21) -> 0 | J22: =SUBTOTAL(109,J21) -> 0
B23: 162G | C23: 0000 | D23: Exercício da Presidência do G20 pelo Brasil | E23: Despesas correntes | F23: 919593 | G23: 919593 | H23: 919593 | I23: 919593 | J23: 919593
B24: Subtotal Ação 162G | F24: =SUBTOTAL(109,F23) -> 919593 | G24: =SUBTOTAL(109,G23) -> 919593 | H24: =SUBTOTAL(109,H23) -> 919593 | I24: =SUBTOTAL(109,I23) -> 919593 | J24: =SUBTOTAL(109,J23) -> 919593
B25: TOTAL | F25: =SUBTOTAL(109,F4:F24) -> 24501704 | G25: =SUBTOTAL(109,G4:G24) -> 23620935 | H25: =SUBTOTAL(109,H4:H24) -> 21155840 | I25: =SUBTOTAL(109,I4:I24) -> 13373515 | J25: =SUBTOTAL(109,J4:J24) -> 13016891
B26: (%) DE EXECUÇÃO | F26: =H25/F25 -> 0.86344362

Sheet LIMITE DE MOVIMENTAÇÃO EMPENHO
A1: LIMITE | B1: AGUARDANDO EMPENHO | C1: EMPENHADO | D1: LIMITE CONSUMIDO | E1: EMPENHADO/ LIMITE | G1: LIMITE A CONSUMIR
A2: =72484603+20809690+34248+15853095 -> 109181636 | B2: ='Consolidado 2026'!C4 -> 1516590.6 | C2: ='Consolidado 2026'!D4 -> 1.0042509e+08 | D2: =B2+C2 -> 1.0194168e+08 | E2: =C2/A2 -> 0.91979832 | G2: =A2-D2 -> 7239960

Sheet Consolidado 2026
A1: LIMITE DE MOVIMENTAÇÃO EMPENHO
A2: Decreto nº 12.990, de 29 de maio de 2026, e alterações | B2: ATÉ NOVEMBRO 2026
B3: LIMITE | C3: AGUARDANDO EMPENHO | D3: EMPENHADO | E3: LIMITE CONSUMIDO | F3: EMPENHADO/ LIMITE | H3: LIMITE A CONSUMIR
A4: MIR | B4: =72484603+20809690+34248+15853095 -> 109181636 | C4: =K10 -> 1516590.6 | D4: =L10 -> 1.0042509e+08 | E4: =C4+D4 -> 1.0194168e+08 | F4: =D4/B4 -> 0.91979832 | H4: =B4-E4 -> 7239960
A5: O LME refere-se ao montante autorizado por decreto para execução pelo MIR em determinado período do exercício. Dessa forma, as áreas devem observar, no planejamento de suas ações, a capacidade de execução orçamentária disponível para o Ministério no respectivo período.
L7: Atualização: 21/10/2026 (base SIAFI) | U7: Planilha | V7: Código | W7: PROGRAMADO 2025 | X7: EMPENHADO 2025 | Y7: LIQUIDADO 2025 | Z7: PAGO 2025
A8: PROGRAMAÇÃO | B8: GND | C8: PLOA | D8: LOA | E8: DOTAÇÃO ATUALIZADA 2026 | F8: BLOQUEIO DECRETO Nº 12.990 | G8: BLOQUEIO SOF/MPO | H8: DOTAÇÃO LIVRE PARA EMPENHO | I8: PROGRAMADO 2026 | J8: DESCENTRALIZADO (ocultar) | K8: DESCENTRALIZADO (ainda não empenhado) 2026 | L8: EMPENHADO 2026 | M8: LIQUIDADO 2026 | N8: PAGO 2026 | O8: SALDO A UTILIZAR 2026 | P8: (%) Programado | Q8: (%) Empenhado | R8: (%) Liquidado | S8: (%) Pago | W8: L3:L200 | X8: M3:M200 | Y8: N3:N200 | Z8: O3:O200
A10: TOTAL GERAL | C10: =SUBTOTAL(109,C12:C58) -> 170823603 | D10: =SUBTOTAL(109,D12:D58) -> 158737644 | E10: =SUBTOTAL(109,E12:E58) -> 158801726 | F10: =SUBTOTAL(109,F12:F58) -> 29876127 | G10: =SUBTOTAL(109,G12:G58) -> 0 | H10: =SUBTOTAL(109,H12:H58) -> 128925599 | I10: =SUBTOTAL(109,I12:I58) -> 1.3014019e+08 | J10: =SUBTOTAL(109,J12:J58) -> 1.0194168e+08 | ... O10: =SUBTOTAL(109,O12:O58) -> 26983923 | P10: =I10/H10 -> 1.0094208 | Q10: =L10/H10 -> 0.77893829 | R10: =M10/H10 -> 0.58845527 | S10: =N10/H10 -> 0.54894257
A12: SEPAR | C12: =SUBTOTAL(109,C13:C20) -> 42164656 | D12: =SUBTOTAL(109,D13:D20) -> 39175588 | E12: =SUBTOTAL(109,E13:E20) -> 39175588 | F12: =SUBTOTAL(109,F13:F20) -> 7660000 | G12: =SUBTOTAL(109,G13:G20) -> 0 | H12: =SUBTOTAL(109,H13:H20) -> 31515588 | I12: =SUBTOTAL(109,I13:I20) -> 31176620 | J12: =SUBTOTAL(109,J13:J19) -> 22587910 | K12: =SUBTOTAL(109,K13:K19) -> 137620.28 | L12: =SUBTOTAL(109,L13:L20) -> 23971440 | M12: =SUBTOTAL(109,M13:M20) -> 19285180 | N12: =SUBTOTAL(109,N13:N20) -> 18345219 | O12: =SUBTOTAL(109,O13:O20) -> 7406527.7 | P12: =I12/H12 -> 0.98924445 | Q12: =L12/H12 -> 0.7606217 | R12: =M12/H12 -> 0.61192513 | S12: =N12/H12 -> 0.58209984
A13: 21HN - Gestão de Políticas de Ações Afirmativas e de Combate e Superação do Racismo | C13: =SUBTOTAL(109,C14:C16) -> 26656612 | D13: =SUBTOTAL(109,D14:D16) -> 24703694 | E13: =SUBTOTAL(109,E14:E16) -> 28703694 | F13: =SUBTOTAL(109,F14:F16) -> 3572084 | G13: =SUBTOTAL(109,G14:G16) -> 0 | H13: =SUBTOTAL(109,H14:H16) -> 25131610 | I13: =SUBTOTAL(109,I14:I16) -> 24802643 | J13: =SUBTOTAL(109,J14:J16) -> 20837910 | ... O13: =SUBTOTAL(109,O14:O16) -> 4293699.7 | P13: =I13/H13 -> 0.98691023 | Q13: =L13/H13 -> 0.82367545 | R13: =M13/H13 -> 0.69689184 | S13: =N13/H13 -> 0.65949028
A14: 0000 - Gestão de Políticas de Ações Afirmativas e de Combate e Superação do Racismo - Despesas Diversas | B14: Despesas correntes | C14: 1500000 | D14: 1390108 | E14: 560000 | F14: 0 | H14: =E14-G14-F14 -> 560000 | I14: =SUMIFS(INDIRECT($U14 & W$8),INDIRECT($U14 & "B3:B200"),$V14,INDIRECT($U14 & "D3:D200"),$B14) -> 560000 | J14: 560000 | L14: =SUMIFS(INDIRECT($U14 & X$8),INDIRECT($U14 & "B3:B200"),$V14,INDIRECT($U14 & "D3:D200"),$B14) -> 560000 | M14: =SUMIFS(INDIRECT($U14 & Y$8),INDIRECT($U14 & "B3:B200"),$V14,INDIRECT($U14 & "D3:D200"),$B14) -> 304630.96 | N14: =SUMIFS(INDIRECT($U14 & Z$8),INDIRECT($U14 & "B3:B200"),$V14,INDIRECT($U14 & "D3:D200"),$B14) -> 304630.96 | O14: =H14-K14-L14 -> 0 | P14: =I14/H14 -> 1 | Q14: =L14/H14 -> 1 | R14: =M14/H14 -> 0.54398386 | S14: =N14/H14 -> 0.54398386 | U14: '21HN - SEPAR'! | V14: =IF(A14="",LEFT(A13,4),LEFT(A14,4)) -> 0000
A15: 0001 - Fortalecimento das Ações Afirmativas | B15: Despesas correntes | C15: 12578306 | D15: 11656793 | E15: 8522424 | F15: 2960000 | H15: =E15-G15-F15 -> 5562424 | I15: =SUMIFS(INDIRECT($U15 & W$8),INDIRECT($U15 & "B3:B200"),$V15,INDIRECT($U15 & "D3:D200"),$B15) -> 5562423.9 | J15: 1661216.4 | K15: =J15-L15 -> 51145.44 | L15: =SUMIFS(INDIRECT($U15 & X$8),INDIRECT($U15 & "B3:B200"),$V15,INDIRECT($U15 & "D3:D200"),$B15) -> 1610071 | M15: =SUMIFS(INDIRECT($U15 & Y$8),INDIRECT($U15 & "B3:B200"),$V15,INDIRECT($U15 & "D3:D200"),$B15) -> 651016.41 | N15: =SUMIFS(INDIRECT($U15 & Z$8),INDIRECT($U15 & "B3:B200"),$V15,INDIRECT($U15 & "D3:D200"),$B15) -> 456115.81 | O15: =H15-K15-L15 -> 3901207.6 | P15: =I15/H15 -> 0.99999998 | Q15: =L15/H15 -> 0.28945492 | R15: =M15/H15 -> 0.11703826 | S15: =N15/H15 -> 0.081999468 | U15: '21HN - SEPAR'! | V15: =IF(A15="",LEFT(A14,4),LEFT(A15,4)) -> 0001
A16: 0002 - Promoção e Implementação de Políticas para o Combate e a Superação de todas as Formas de Racismo | B16: Despesas correntes | C16: 12578306 | D16: 11656793 | E16: 19621270 | F16: 612084 | H16: =E16-G16-F16 -> 19009186 | I16: =SUMIFS(INDIRECT($U16 & W$8),INDIRECT($U16 & "B3:B200"),$V16,INDIRECT($U16 & "D3:D200"),$B16) -> 18680219 | J16: 18616694 | K16: =J16-L16 -> 86474.84 | L16: =SUMIFS(INDIRECT($U16 & X$8),INDIRECT($U16 & "B3:B200"),$V16,INDIRECT($U16 & "D3:D200"),$B16) -> 18530219 | M16: =SUMIFS(INDIRECT($U16 & Y$8),INDIRECT($U16 & "B3:B200"),$V16,INDIRECT($U16 & "D3:D200"),$B16) -> 16558366 | N16: =SUMIFS(INDIRECT($U16 & Z$8),INDIRECT($U16 & "B3:B200"),$V16,INDIRECT($U16 & "D3:D200"),$B16) -> 15813306 | O16: =H16-K16-L16 -> 392492.07 | P16: =I16/H16 -> 0.98269432 | Q16: =L16/H16 -> 0.9748034 | R16: =M16/H16 -> 0.87107183 | S16: =N16/H16 -> 0.83187706 | U16: '21HN - SEPAR'! | V16: =IF(A16="",LEFT(#REF!,4),LEFT(A16,4)) -> 0002
A17: 21FF - Fortalecimento de Políticas em prol da Vida e do Bem Viver da Juventude Negra | C17: =SUBTOTAL(109,C18:C20) -> 15508044 | D17: =SUBTOTAL(109,D18:D20) -> 14471894 | E17: =SUBTOTAL(109,E18:E20) -> 10471894 | F17: =SUBTOTAL(109,F18:F20) -> 4087916 | G17: =SUBTOTAL(109,G18:G20) -> 0 | H17: =SUBTOTAL(109,H18:H20) -> 6383978 | I17: =SUBTOTAL(109,I18:I20) -> 6373977.5 | J17: =SUBTOTAL(109,J18:J20) -> 3271150 | ... O17: =SUBTOTAL(109,O18:O20) -> 3112828 | P17: =I17/H17 -> 0.9984335 | Q17: =L17/H17 -> 0.51239995 | R17: =M17/H17 -> 0.27743928 | S17: =N17/H17 -> 0.27743928
A18: 0000 - Fortalecimento de Políticas em prol da Vida e do Bem Viver da Juventude Negra - Despesas Diversas | B18: Despesas correntes | C18: 1500000 | D18: 1403142 | E18: 480000 | F18: 0 | H18: =E18-G18-F18 -> 480000 | I18: =SUMIFS(INDIRECT($U18 & W$8),INDIRECT($U18 & "B3:B200"),$V18,INDIRECT($U18 & "D3:D200"),$B18) -> 480000 | J18: 480000 | K18: =J18-L18 -> 0 | L18: =SUMIFS(INDIRECT($U18 & X$8),INDIRECT($U18 & "B3:B200"),$V18,INDIRECT($U18 & "D3:D200"),$B18) -> 480000 | M18: =SUMIFS(INDIRECT($U18 & Y$8),INDIRECT($U18 & "B3:B200"),$V18,INDIRECT($U18 & "D3:D200"),$B18) -> 250016.27 | N18: =SUMIFS(INDIRECT($U18 & Z$8),INDIRECT($U18 & "B3:B200"),$V18,INDIRECT($U18 & "D3:D200"),$B18) -> 250016.27 | O18: =H18-K18-L18 -> 0 | P18: =I18/H18 -> 1 | Q18: =L18/H18 -> 1 | R18: =M18/H18 -> 0.52086723 | S18: =N18/H18 -> 0.52086723 | U18: '21FF - SEPAR'! | V18: =IF(A18="",LEFT(A17,4),LEFT(A18,4)) -> 0000
A19: 0001 - Ações de promoção, proteção e garantia dos direitos da juventude negra | B19: Despesas correntes | C19: 12382044 | D19: 11547747 | E19: 8470744 | F19: 4087916 | H19: =E19-G19-F19 -> 4382828 | I19: =SUMIFS(INDIRECT($U19 & W$8),INDIRECT($U19 & "B3:B200"),$V19,INDIRECT($U19 & "D3:D200"),$B19) -> 4372827.5 | J19: 1270000 | K19: =J19-L19 -> 0 | L19: =SUMIFS(INDIRECT($U19 & X$8),INDIRECT($U19 & "B3:B200"),$V19,INDIRECT($U19 & "D3:D200"),$B19) -> 1270000 | M19: =SUMIFS(INDIRECT($U19 & Y$8),INDIRECT($U19 & "B3:B200"),$V19,INDIRECT($U19 & "D3:D200"),$B19) -> 0 | N19: =SUMIFS(INDIRECT($U19 & Z$8),INDIRECT($U19 & "B3:B200"),$V19,INDIRECT($U19 & "D3:D200"),$B19) -> 0 | O19: =H19-K19-L19 -> 3112828 | P19: =I19/H19 -> 0.99771825 | Q19: =L19/H19 -> 0.28976725 | R19: =M19/H19 -> 0 | S19: =N19/H19 -> 0 | U19: '21FF - SEPAR'! | V19: =IF(A19="",LEFT(A18,4),LEFT(A19,4)) -> 0001
A20: 0002 - Promoção de Justiça Racial e Garantia de Direitos às Pessoas Privadas de Liberdade - ADPF 347 | B20: Despesas correntes | C20: 1626000 | D20: 1521005 | E20: 1521150 | F20: 0 | H20: =E20-G20-F20 -> 1521150 | I20: =SUMIFS(INDIRECT($U20 & W$8),INDIRECT($U20 & "B3:B200"),$V20,INDIRECT($U20 & "D3:D200"),$B20) -> 1521150 | J20: 1521150 | K20: =J20-L20 -> 0 | L20: =SUMIFS(INDIRECT($U20 & X$8),INDIRECT($U20 & "B3:B200"),$V20,INDIRECT($U20 & "D3:D200"),$B20) -> 1521150 | M20: =SUMIFS(INDIRECT($U20 & Y$8),INDIRECT($U20 & "B3:B200"),$V20,INDIRECT($U20 & "D3:D200"),$B20) -> 1521150 | N20: =SUMIFS(INDIRECT($U20 & Z$8),INDIRECT($U20 & "B3:B200"),$V20,INDIRECT($U20 & "D3:D200"),$B20) -> 1521150 | O20: =H20-K20-L20 -> 0 | P20: =I20/H20 -> 1 | Q20: =L20/H20 -> 1 | R20: =M20/H20 -> 1 | S20: =N20/H20 -> 1 | U20: '21FF - SEPAR'! | V20: =IF(A20="",LEFT(A19,4),LEFT(A20,4)) -> 0002
A21: OUVIDORIA | C21: =SUBTOTAL(109,C22:C24) -> 1000000 | D21: =SUBTOTAL(109,D22:D24) -> 926737 | E21: =SUBTOTAL(109,E22:E24) -> 926737 | F21: =SUBTOTAL(109,F22:F24) -> 643937 | G21: =SUBTOTAL(109,G22:G24) -> 0 | H21: =SUBTOTAL(109,H22:H24) -> 282800 | I21: =SUBTOTAL(109,I22:I24) -> 0 | J21: =SUBTOTAL(109,J22:J24) -> 0 | ... O21: =SUBTOTAL(109,O22:O24) -> 282800 | P21: =I21/H21 -> 0 | Q21: =L21/H21 -> 0 | R21: =M21/H21 -> 0 | S21: =N21/H21 -> 0
A22: 21HN - Gestão de Políticas de Ações Afirmativas e de Combate e Superação do Racismo | C22: =SUBTOTAL(109,C24) -> 1000000 | D22: =SUBTOTAL(109,D24) -> 926737 | E22: =SUBTOTAL(109,E24) -> 926737 | F22: =SUBTOTAL(109,F24) -> 643937 | G22: =SUBTOTAL(109,G24) -> 0 | H22: =SUBTOTAL(109,H24) -> 282800 | I22: =SUBTOTAL(109,I24) -> 0 | J22: =SUBTOTAL(109,J24) -> 0 | ... O22: =SUBTOTAL(109,O24) -> 282800 | P22: =I22/H22 -> 0 | Q22: =L22/H22 -> 0 | R22: =M22/H22 -> 0 | S22: =N22/H22 -> 0
A24: 0003 - Ferramentas Nacionais de Recebimento e Encaminhamento de Denúncias de Racismo | B24: Despesas correntes | C24: 1000000 | D24: 926737 | E24: 926737 | F24: 643937 | H24: =E24-G24-F24 -> 282800 | I24: =SUMIFS(INDIRECT($U24 & W$8),INDIRECT($U24 & "B3:B200"),$V24,INDIRECT($U24 & "D3:D200"),$B24) -> 0 | K24: =J24-L24 -> 0 | L24: =SUMIFS(INDIRECT($U24 & X$8),INDIRECT($U24 & "B3:B200"),$V24,INDIRECT($U24 & "D3:D200"),$B24) -> 0 | M24: =SUMIFS(INDIRECT($U24 & Y$8),INDIRECT($U24 & "B3:B200"),$V24,INDIRECT($U24 & "D3:D200"),$B24) -> 0 | N24: =SUMIFS(INDIRECT($U24 & Z$8),INDIRECT($U24 & "B3:B200"),$V24,INDIRECT($U24 & "D3:D200"),$B24) -> 0 | O24: =H24-K24-L24 -> 282800 | P24: =I24/H24 -> 0 | Q24: =L24/H24 -> 0 | R24: =M24/H24 -> 0 | S24: =N24/H24 -> 0 | U24: '21HN - OUV'! | V24: =IF(A24="",LEFT(A22,4),LEFT(A24,4)) -> 0003 | AA24: =H24-I24 -> 282800
A25: SENAPIR | C25: =SUBTOTAL(109,C26:C30) -> 32058194 | D25: =SUBTOTAL(109,D26:D31) -> 39135894 | E25: =SUBTOTAL(109,E26:E31) -> 38735894 | F25: =SUBTOTAL(109,F26:F31) -> 12501549 | G25: =SUBTOTAL(109,G26:G31) -> 0 | H25: =SUBTOTAL(109,H26:H31) -> 26234345 | I25: =SUBTOTAL(109,I26:I31) -> 26285894 | J25: =SUBTOTAL(109,J26:J31) -> 17934709 | K25: =SUBTOTAL(109,K26:K31) -> 291002.06 | ... O25: =SUBTOTAL(109,O26:O31) -> 8299636.2 | P25: =I25/H25 -> 1.0019649 | Q25: =L25/H25 -> 0.6725423 | R25: =M25/H25 -> 0.51904197 | S25: =N25/H25 -> 0.46014567
A26: 21FC - Monitoramento, aperfeiçoamento, articulação e estruturação de políticas de promoção da igualdade racial no âmbito do SINAPIR | C26: =SUBTOTAL(109,C27:C30) -> 32058194 | D26: =SUBTOTAL(109,D27:D31) -> 39135894 | E26: =SUBTOTAL(109,E27:E31) -> 38735894 | F26: =SUBTOTAL(109,F27:F31) -> 12501549 | G26: =SUBTOTAL(109,G27:G31) -> 0 | H26: =SUBTOTAL(109,H27:H31) -> 26234345 | I26: =SUBTOTAL(109,I27:I31) -> 26285894 | J26: =SUBTOTAL(109,J27:J31) -> 17934709 | K26: =SUBTOTAL(109,K27:K31) -> 291002.06 | ... O26: =SUBTOTAL(109,O27:O31) -> 8299636.2 | P26: =I26/H26 -> 1.0019649 | Q26: =L26/H26 -> 0.6725423 | R26: =M26/H26 -> 0.51904197 | S26: =N26/H26 -> 0.46014567
A27: 0000 - Monitoramento, aperfeiçoamento, articulação e estruturação de políticas de promoção da igualdade racial no âmbito do SINAPIR - Despesas Diversas | B27: Despesas correntes | C27: 2663706 | D27: 2473982 | E27: 2473982 | F27: 51549 | H27: =E27-G27-F27 -> 2422433 | I27: =SUMIFS(INDIRECT($U27 & W$8),INDIRECT($U27 & "B3:B200"),$V27,INDIRECT($U27 & "D3:D200"),$B27) -> 2473982 | J27: 2188889.6 | K27: =J27-L27 -> 6273.85 | L27: =SUMIFS(INDIRECT($U27 & X$8),INDIRECT($U27 & "B3:B200"),$V27,INDIRECT($U27 & "D3:D200"),$B27) -> 2182615.8 | M27: =SUMIFS(INDIRECT($U27 & Y$8),INDIRECT($U27 & "B3:B200"),$V27,INDIRECT($U27 & "D3:D200"),$B27) -> 1397287.1 | N27: =SUMIFS(INDIRECT($U27 & Z$8),INDIRECT($U27 & "B3:B200"),$V27,INDIRECT($U27 & "D3:D200"),$B27) -> 1397287.1 | O27: =H27-K27-L27 -> 233543.35 | P27: =I27/H27 -> 1.0212798 | Q27: =L27/H27 -> 0.90100151 | R27: =M27/H27 -> 0.57681143 | S27: =N27/H27 -> 0.57681143 | U27: '21FC - SENAPIR'! | V27: =IF(A27="",LEFT(A26,4),LEFT(A27,4)) -> 0000
B28: Investimento | D28: 50000 | E28: 50000 | F28: 50000 | H28: =E28-G28-F28 -> 0 | I28: =SUMIFS(INDIRECT($U28 & W$8),INDIRECT($U28 & "B3:B200"),$V28,INDIRECT($U28 & "D3:D200"),$B28) -> 0 | K28: =J28-L28 -> 0 | L28: =SUMIFS(INDIRECT($U28 & X$8),INDIRECT($U28 & "B3:B200"),$V28,INDIRECT($U28 & "D3:D200"),$B28) -> 0 | M28: =SUMIFS(INDIRECT($U28 & Y$8),INDIRECT($U28 & "B3:B200"),$V28,INDIRECT($U28 & "D3:D200"),$B28) -> 0 | N28: =SUMIFS(INDIRECT($U28 & Z$8),INDIRECT($U28 & "B3:B200"),$V28,INDIRECT($U28 & "D3:D200"),$B28) -> 0 | O28: =H28-K28-L28 -> 0 | P28: =I28/H28 -> #DIV/0! | Q28: =L28/H28 -> #DIV/0! | R28: =M28/H28 -> #DIV/0! | S28: =N28/H28 -> #DIV/0! | U28: '21FC - SENAPIR'! | V28: =IF(A28="",LEFT(A27,4),LEFT(A28,4)) -> 0000
A29: 0001 - Monitoramento, Avaliação e Gestão da informação de Políticas de Promoção da Igualdade Racial | B29: Despesas correntes | C29: 13757644 | D29: 12777740 | E29: 7721555 | F29: 3473651 | H29: =E29-G29-F29 -> 4247904 | I29: =SUMIFS(INDIRECT($U29 & W$8),INDIRECT($U29 & "B3:B200"),$V29,INDIRECT($U29 & "D3:D200"),$B29) -> 4247904 | J29: 3878238.5 | K29: =J29-L29 -> 284728.21 | L29: =SUMIFS(INDIRECT($U29 & X$8),INDIRECT($U29 & "B3:B200"),$V29,INDIRECT($U29 & "D3:D200"),$B29) -> 3593510.3 | M29: =SUMIFS(INDIRECT($U29 & Y$8),INDIRECT($U29 & "B3:B200"),$V29,INDIRECT($U29 & "D3:D200"),$B29) -> 2023833.2 | N29: =SUMIFS(INDIRECT($U29 & Z$8),INDIRECT($U29 & "B3:B200"),$V29,INDIRECT($U29 & "D3:D200"),$B29) -> 2020333.2 | O29: =H29-K29-L29 -> 369665.47 | P29: =I29/H29 -> 1 | Q29: =L29/H29 -> 0.84594904 | R29: =M29/H29 -> 0.476431 | S29: =N29/H29 -> 0.47560707 | U29: '21FC - SENAPIR'! | V29: =IF(A29="",LEFT(A28,4),LEFT(A29,4)) -> 0001
A30: 0002 - Aperfeiçoamento, estruturação e promoção do SINAPIR - Sistema Nacional de Promoção da Igualdade Racial | B30: Despesas correntes | C30: 15636844 | D30: 14507823 | E30: 19564008 | H30: =E30-G30-F30 -> 19564008 | I30: =SUMIFS(INDIRECT($U30 & W$8),INDIRECT($U30 & "B3:B200"),$V30,INDIRECT($U30 & "D3:D200"),$B30) -> 19564008 | J30: 11867581 | K30: =J30-L30 -> 0 | L30: =SUMIFS(INDIRECT($U30 & X$8),INDIRECT($U30 & "B3:B200"),$V30,INDIRECT($U30 & "D3:D200"),$B30) -> 11867581 | M30: =SUMIFS(INDIRECT($U30 & Y$8),INDIRECT($U30 & "B3:B200"),$V30,INDIRECT($U30 & "D3:D200"),$B30) -> 10195606 | N30: =SUMIFS(INDIRECT($U30 & Z$8),INDIRECT($U30 & "B3:B200"),$V30,INDIRECT($U30 & "D3:D200"),$B30) -> 8654000 | O30: =H30-K30-L30 -> 7696427.3 | P30: =I30/H30 -> 1 | Q30: =L30/H30 -> 0.60660273 | R30: =M30/H30 -> 0.52114096 | S30: =N30/H30 -> 0.4423429 | U30: '21FC - SENAPIR'! | V30: =IF(A30="",LEFT(A29,4),LEFT(A30,4)) -> 0002
B31: Investimento | C31: 10000000 | D31: 9326349 | E31: 8926349 | F31: 8926349 | H31: =E31-G31-F31 -> 0 | I31: =SUMIFS(INDIRECT($U31 & W$8),INDIRECT($U31 & "B3:B200"),$V31,INDIRECT($U31 & "D3:D200"),$B31) -> 0 | L31: =SUMIFS(INDIRECT($U31 & X$8),INDIRECT($U31 & "B3:B200"),$V31,INDIRECT($U31 & "D3:D200"),$B31) -> 0 | M31: =SUMIFS(INDIRECT($U31 & Y$8),INDIRECT($U31 & "B3:B200"),$V31,INDIRECT($U31 & "D3:D200"),$B31) -> 0 | N31: =SUMIFS(INDIRECT($U31 & Z$8),INDIRECT($U31 & "B3:B200"),$V31,INDIRECT($U31 & "D3:D200"),$B31) -> 0 | O31: =H31-K31-L31 -> 0 | P31: =I31/H31 -> #DIV/0! | Q31: =L31/H31 -> #DIV/0! | R31: =M31/H31 -> #DIV/0! | S31: =N31/H31 -> #DIV/0! | U31: '21FC - SENAPIR'! | V31: =IF(A31="",LEFT(A30,4),LEFT(A31,4)) -> 0002
A32: SQPT | C32: =SUBTOTAL(109,C33:C40) -> 42135688 | D32: =SUBTOTAL(109,D33:D40) -> 39148741 | E32: =SUBTOTAL(109,E33:E40) -> 39212823 | F32: =SUBTOTAL(109,F33:F40) -> 8084934 | G32: =SUBTOTAL(109,G33:G40) -> 0 | H32: =SUBTOTAL(109,H33:H40) -> 31127889 | I32: =SUBTOTAL(109,I33:I40) -> 30832395 | J32: =SUBTOTAL(109,J33:J40) -> 22682540 | ... O32: =SUBTOTAL(109,O33:O40) -> 8445349 | P32: =I32/H32 -> 0.9905071 | Q32: =L32/H32 -> 0.72587447 | R32: =M32/H32 -> 0.63172393 | S32: =N32/H32 -> 0.56101113
A33: 21FE - Apoio à Implementação de Políticas para Quilombolas, Comunidades Tradicionais de Matriz Africana, Povos de Terreiro e Ciganos | C33: =SUBTOTAL(109,C34:C40) -> 42135688 | D33: =SUBTOTAL(109,D34:D40) -> 39148741 | E33: =SUBTOTAL(109,E34:E40) -> 39212823 | F33: =SUBTOTAL(109,F34:F40) -> 8084934 | G33: =SUBTOTAL(109,G34:G40) -> 0 | H33: =SUBTOTAL(109,H34:H40) -> 31127889 | I33: =SUBTOTAL(109,I34:I40) -> 30832395 | J33: =SUBTOTAL(109,J34:J40) -> 22682540 | ... O33: =SUBTOTAL(109,O34:O40) -> 8445349 | P33: =I33/H33 -> 0.9905071 | Q33: =L33/H33 -> 0.72587447 | R33: =M33/H33 -> 0.63172393 | S33: =N33/H33 -> 0.56101113
A34: 0000 - Apoio à Implementação de Políticas para Quilombolas, Comunidades Tradicionais de Matriz Africana, Povos de Terreiro e Ciganos - Despesas Diversas | B34: Despesas correntes | C34: 2000000 | D34: 1859799 | E34: 2499130 | F34: 0 | H34: =E34-G34-F34 -> 2499130 | I34: =SUMIFS(INDIRECT($U34 & W$8),INDIRECT($U34 & "B3:B200"),$V34,INDIRECT($U34 & "D3:D200"),$B34) -> 2499130 | J34: 1805034.4 | K34: =J34-L34 -> 0 | L34: =SUMIFS(INDIRECT($U34 & X$8),INDIRECT($U34 & "B3:B200"),$V34,INDIRECT($U34 & "D3:D200"),$B34) -> 1805034.4 | M34: =SUMIFS(INDIRECT($U34 & Y$8),INDIRECT($U34 & "B3:B200"),$V34,INDIRECT($U34 & "D3:D200"),$B34) -> 1327574.9 | N34: =SUMIFS(INDIRECT($U34 & Z$8),INDIRECT($U34 & "B3:B200"),$V34,INDIRECT($U34 & "D3:D200"),$B34) -> 1327574.9 | O34: =H34-K34-L34 -> 694095.65 | P34: =I34/H34 -> 1 | Q34: =L34/H34 -> 0.72226509 | R34: =M34/H34 -> 0.53121484 | S34: =N34/H34 -> 0.53121484 | U34: '21FE - SQPT'! | V34: 0000
A35: 0001 - Promoção, proteção e garantia dos direitos dos povos Ciganos | B35: Despesas correntes | C35: 7463631 | D35: 6934100 | E35: 7171507 | F35: 182065 | H35: =E35-G35-F35 -> 6989442 | I35: =SUMIFS(INDIRECT($U35 & W$8),INDIRECT($U35 & "B3:B200"),$V35,INDIRECT($U35 & "D3:D200"),$B35) -> 6986541.2 | J35: 6903894 | K35: =J35-L35 -> 12600 | L35: =SUMIFS(INDIRECT($U35 & X$8),INDIRECT($U35 & "B3:B200"),$V35,INDIRECT($U35 & "D3:D200"),$B35) -> 6891294 | M35: =SUMIFS(INDIRECT($U35 & Y$8),INDIRECT($U35 & "B3:B200"),$V35,INDIRECT($U35 & "D3:D200"),$B35) -> 6264858 | N35: =SUMIFS(INDIRECT($U35 & Z$8),INDIRECT($U35 & "B3:B200"),$V35,INDIRECT($U35 & "D3:D200"),$B35) -> 5454858 | O35: =H35-K35-L35 -> 85547.99 | P35: =I35/H35 -> 0.99958497 | Q35: =L35/H35 -> 0.98595768 | R35: =M35/H35 -> 0.89633164 | S35: =N35/H35 -> 0.78044256 | U35: '21FE - SQPT'! | V35: 0001
B36: Investimento | C36: 1000000 | D36: 926738 | E36: 500000 | F36: 500000 | H36: =E36-G36-F36 -> 0 | I36: =SUMIFS(INDIRECT($U36 & W$8),INDIRECT($U36 & "B3:B200"),$V36,INDIRECT($U36 & "D3:D200"),$B36) -> 0 | K36: =J36-L36 -> 0 | L36: =SUMIFS(INDIRECT($U36 & X$8),INDIRECT($U36 & "B3:B200"),$V36,INDIRECT($U36 & "D3:D200"),$B36) -> 0 | M36: =SUMIFS(INDIRECT($U36 & Y$8),INDIRECT($U36 & "B3:B200"),$V36,INDIRECT($U36 & "D3:D200"),$B36) -> 0 | N36: =SUMIFS(INDIRECT($U36 & Z$8),INDIRECT($U36 & "B3:B200"),$V36,INDIRECT($U36 & "D3:D200"),$B36) -> 0 | O36: =H36-K36-L36 -> 0 | P36: =I36/H36 -> #DIV/0! | Q36: =L36/H36 -> #DIV/0! | R36: =M36/H36 -> #DIV/0! | S36: =N36/H36 -> #DIV/0! | U36: '21FE - SQPT'! | V36: 0001
A37: 0002 - Promoção, proteção e garantia dos direitos das Comunidades Tradicionais de Matriz Africana e Povos de Terreiro | B37: Despesas correntes | C37: 9649828 | D37: 8973364 | E37: 9103035 | F37: 2521718 | H37: =E37-G37-F37 -> 6581317 | I37: =SUMIFS(INDIRECT($U37 & W$8),INDIRECT($U37 & "B3:B200"),$V37,INDIRECT($U37 & "D3:D200"),$B37) -> 6581308.2 | J37: 5559022 | K37: =J37-L37 -> 0 | L37: =SUMIFS(INDIRECT($U37 & X$8),INDIRECT($U37 & "B3:B200"),$V37,INDIRECT($U37 & "D3:D200"),$B37) -> 5559022 | M37: =SUMIFS(INDIRECT($U37 & Y$8),INDIRECT($U37 & "B3:B200"),$V37,INDIRECT($U37 & "D3:D200"),$B37) -> 4096567.2 | N37: =SUMIFS(INDIRECT($U37 & Z$8),INDIRECT($U37 & "B3:B200"),$V37,INDIRECT($U37 & "D3:D200"),$B37) -> 4092927.1 | O37: =H37-K37-L37 -> 1022295 | P37: =I37/H37 -> 0.99999866 | Q37: =L37/H37 -> 0.84466711 | R37: =M37/H37 -> 0.62245402 | S37: =N37/H37 -> 0.62190092 | U37: '21FE - SQPT'! | V37: 0002
B38: Investimento | C38: 2500000 | D38: 2316845 | E38: 1937174 | F38: 1158587 | H38: =E38-G38-F38 -> 778587 | I38: =SUMIFS(INDIRECT($U38 & W$8),INDIRECT($U38 & "B3:B200"),$V38,INDIRECT($U38 & "D3:D200"),$B38) -> 778587 | K38: =J38-L38 -> 0 | L38: =SUMIFS(INDIRECT($U38 & X$8),INDIRECT($U38 & "B3:B200"),$V38,INDIRECT($U38 & "D3:D200"),$B38) -> 0 | M38: =SUMIFS(INDIRECT($U38 & Y$8),INDIRECT($U38 & "B3:B200"),$V38,INDIRECT($U38 & "D3:D200"),$B38) -> 0 | N38: =SUMIFS(INDIRECT($U38 & Z$8),INDIRECT($U38 & "B3:B200"),$V38,INDIRECT($U38 & "D3:D200"),$B38) -> 0 | O38: =H38-K38-L38 -> 778587 | P38: =I38/H38 -> 1 | Q38: =L38/H38 -> 0 | R38: =M38/H38 -> 0 | S38: =N38/H38 -> 0 | U38: '21FE - SQPT'! | V38: 0002
A39: 0003 - Promoção, proteção e garantia dos direitos das populações e comunidades Quilombolas | B39: Despesas correntes | C39: 16522229 | D39: 15357681 | E39: 15221763 | F39: 942350 | H39: =E39-G39-F39 -> 14279413 | I39: =SUMIFS(INDIRECT($U39 & W$8),INDIRECT($U39 & "B3:B200"),$V39,INDIRECT($U39 & "D3:D200"),$B39) -> 13986829 | J39: 8414589.7 | K39: =J39-L39 -> 75000.13 | L39: =SUMIFS(INDIRECT($U39 & X$8),INDIRECT($U39 & "B3:B200"),$V39,INDIRECT($U39 & "D3:D200"),$B39) -> 8339589.5 | M39: =SUMIFS(INDIRECT($U39 & Y$8),INDIRECT($U39 & "B3:B200"),$V39,INDIRECT($U39 & "D3:D200"),$B39) -> 7975232.2 | N39: =SUMIFS(INDIRECT($U39 & Z$8),INDIRECT($U39 & "B3:B200"),$V39,INDIRECT($U39 & "D3:D200"),$B39) -> 6587732.2 | O39: =H39-K39-L39 -> 5864823.3 | P39: =I39/H39 -> 0.97951006 | Q39: =L39/H39 -> 0.58402888 | R39: =M39/H39 -> 0.55851261 | S39: =N39/H39 -> 0.46134475 | U39: '21FE - SQPT'! | V39: 0003
B40: Investimento | C40: 3000000 | D40: 2780214 | E40: 2780214 | F40: 2780214 | H40: =E40-G40-F40 -> 0 | I40: =SUMIFS(INDIRECT($U40 & W$8),INDIRECT($U40 & "B3:B200"),$V40,INDIRECT($U40 & "D3:D200"),$B40) -> 0 | K40: =J40-L40 -> 0 | L40: =SUMIFS(INDIRECT($U40 & X$8),INDIRECT($U40 & "B3:B200"),$V40,INDIRECT($U40 & "D3:D200"),$B40) -> 0 | M40: =SUMIFS(INDIRECT($U40 & Y$8),INDIRECT($U40 & "B3:B200"),$V40,INDIRECT($U40 & "D3:D200"),$B40) -> 0 | N40: =SUMIFS(INDIRECT($U40 & Z$8),INDIRECT($U40 & "B3:B200"),$V40,INDIRECT($U40 & "D3:D200"),$B40) -> 0 | O40: =H40-K40-L40 -> 0 | P40: =I40/H40 -> #DIV/0! | Q40: =L40/H40 -> #DIV/0! | R40: =M40/H40 -> #DIV/0! | S40: =N40/H40 -> #DIV/0! | U40: '21FE - SQPT'! | V40: 0003
A41: CNPIR | C41: =SUBTOTAL(109,C42:C43) -> 2000000 | D41: =SUBTOTAL(109,D42:D43) -> 1853476 | E41: =SUBTOTAL(109,E42:E43) -> 2253476 | F41: =SUBTOTAL(109,F42:F43) -> 0 | G41: =SUBTOTAL(109,G42:G43) -> 0 | H41: =SUBTOTAL(109,H42:H43) -> 2253476 | I41: =SUBTOTAL(109,I42:I43) -> 1853476 | J41: =SUBTOTAL(109,J42:J43) -> 1479048.9 | ... O41: =SUBTOTAL(109,O42:O43) -> 774427.12 | P41: =I41/H41 -> 0.82249645 | Q41: =L41/H41 -> 0.61640278 | R41: =M41/H41 -> 0.52058798 | S41: =N41/H41 -> 0.52058798
A42: 21FG - Apoio no Funcionamento do Conselho Nacional de Promoção da Igualdade Racial - CNPIR | C42: =SUBTOTAL(109,C43:C43) -> 2000000 | D42: =SUBTOTAL(109,D43:D43) -> 1853476 | E42: =SUBTOTAL(109,E43:E43) -> 2253476 | F42: =SUBTOTAL(109,F43:F43) -> 0 | G42: =SUBTOTAL(109,G43:G43) -> 0 | H42: =SUBTOTAL(109,H43:H43) -> 2253476 | I42: =SUBTOTAL(109,I43:I43) -> 1853476 | J42: =SUBTOTAL(109,J43:J43) -> 1479048.9 | ... O42: =SUBTOTAL(109,O43:O43) -> 774427.12 | P42: =I42/H42 -> 0.82249645 | Q42: =L42/H42 -> 0.61640278 | R42: =M42/H42 -> 0.52058798 | S42: =N42/H42 -> 0.52058798
A43: 0000 - Apoio no Funcionamento do Conselho Nacional de Promoção da Igualdade Racial - Despesas Diversas | B43: Despesas correntes | C43: 2000000 | D43: 1853476 | E43: 2253476 | H43: =E43-G43-F43 -> 2253476 | I43: =SUMIFS(INDIRECT($U43 & W$8),INDIRECT($U43 & "B3:B200"),$V43,INDIRECT($U43 & "D3:D200"),$B43) -> 1853476 | J43: 1479048.9 | K43: =J43-L43 -> 90000 | L43: =SUMIFS(INDIRECT($U43 & X$8),INDIRECT($U43 & "B3:B200"),$V43,INDIRECT($U43 & "D3:D200"),$B43) -> 1389048.9 | M43: =SUMIFS(INDIRECT($U43 & Y$8),INDIRECT($U43 & "B3:B200"),$V43,INDIRECT($U43 & "D3:D200"),$B43) -> 1173132.5 | N43: =SUMIFS(INDIRECT($U43 & Z$8),INDIRECT($U43 & "B3:B200"),$V43,INDIRECT($U43 & "D3:D200"),$B43) -> 1173132.5 | O43: =H43-K43-L43 -> 774427.12 | P43: =I43/H43 -> 0.82249645 | Q43: =L43/H43 -> 0.61640278 | R43: =M43/H43 -> 0.52058798 | S43: =N43/H43 -> 0.52058798 | U43: '21FG - CNPIR'! | V43: 0000
A44: SECRETARIA EXECUTIVA | C44: =SUBTOTAL(109,C45:C58) -> 41465065 | D44: =SUBTOTAL(109,D45:D58) -> 38497208 | E44: =SUBTOTAL(109,E45:E58) -> 38497208 | F44: =SUBTOTAL(109,F45:F58) -> 985707 | G44: =SUBTOTAL(109,G45:G58) -> 0 | H44: =SUBTOTAL(109,H45:H58) -> 37511501 | I44: =SUBTOTAL(109,I45:I58) -> 39991802 | J44: =SUBTOTAL(109,J45:J58) -> 35736318 | ... O44: =SUBTOTAL(109,O45:O58) -> 1775183.1 | P44: =I44/H44 -> 1.0661211 | Q44: =L44/H44 -> 0.92840726 | R44: =M44/H44 -> 0.58989047 | S44: =N44/H44 -> 0.57901404
A45: 2000 - Administração da Unidade | C45: =SUBTOTAL(109,C46:C54) -> 38965065 | D45: =SUBTOTAL(109,D46:D54) -> 36121393 | E45: =SUBTOTAL(109,E46:E54) -> 36121393 | F45: =SUBTOTAL(109,F46:F54) -> 0 | G45: =SUBTOTAL(109,G46:G53) -> 0 | H45: =SUBTOTAL(109,H46:H54) -> 36121393 | I45: =SUBTOTAL(109,I46:I54) -> 38491802 | J45: =SUBTOTAL(109,J46:J54) -> 34536318 | K45: =SUBTOTAL(109,K46:K54) -> 1100476.1 | L45: =SUBTOTAL(109,L46:L54) -> 33435842 | M45: =SUBTOTAL(109,M46:M54) -> 21252767 | N45: =SUBTOTAL(109,N46:N54) -> 20844776 | O45: =SUBTOTAL(109,O46:O54) -> 1585075.1 | P45: =I45/H45 -> 1.0656234 | Q45: =L45/H45 -> 0.92565206 | R45: =M45/H45 -> 0.58837064 | S45: =N45/H45 -> 0.57707564
A46: 0000 - Administração da Unidade - Despesas Diversas | B46: Despesas correntes | C46: 30065065 | D46: 27862440 | E46: 31849254 | H46: =E46-G46-F46 -> 31849254 | I46: =SUMIFS(INDIRECT($U46 & W$8),INDIRECT($U46 & "B3:B200"),$V46,INDIRECT($U46 & "D3:D200"),$B46) -> 30065065 | J46: 30853631 | K46: =J46-L46 -> 157864.4 | L46: =SUMIFS(INDIRECT($U46 & X$8),INDIRECT($U46 & "B3:B200"),$V46,INDIRECT($U46 & "D3:D200"),$B46) -> 30695767 | M46: =SUMIFS(INDIRECT($U46 & Y$8),INDIRECT($U46 & "B3:B200"),$V46,INDIRECT($U46 & "D3:D200"),$B46) -> 19889117 | N46: =SUMIFS(INDIRECT($U46 & Z$8),INDIRECT($U46 & "B3:B200"),$V46,INDIRECT($U46 & "D3:D200"),$B46) -> 19481126 | O46: =H46-K46-L46 -> 995622.94 | P46: =I46/H46 -> 0.94398019 | Q46: =L46/H46 -> 0.96378291 | R46: =M46/H46 -> 0.6244767 | S46: =N46/H46 -> 0.61166663 | U46: '2000 - SE'! | V46: =IF(A46="",LEFT(A45,4),LEFT(A46,4)) -> 0000
B47: Investimento | C47: 1000000 | D47: 926738 | E47: 168645 | H47: =E47-G47-F47 -> 168645 | I47: =SUMIFS(INDIRECT($U47 & W$8),INDIRECT($U47 & "B3:B200"),$V47,INDIRECT($U47 & "D3:D200"),$B47) -> 1000000 | J47: 168239 | K47: =J47-L47 -> 0 | L47: =SUMIFS(INDIRECT($U47 & X$8),INDIRECT($U47 & "B3:B200"),$V47,INDIRECT($U47 & "D3:D200"),$B47) -> 168239 | M47: =SUMIFS(INDIRECT($U47 & Y$8),INDIRECT($U47 & "B3:B200"),$V47,INDIRECT($U47 & "D3:D200"),$B47) -> 160319 | N47: =SUMIFS(INDIRECT($U47 & Z$8),INDIRECT($U47 & "B3:B200"),$V47,INDIRECT($U47 & "D3:D200"),$B47) -> 160319 | O47: =H47-K47-L47 -> 406 | P47: =I47/H47 -> 5.9296155 | Q47: =L47/H47 -> 0.99759258 | R47: =M47/H47 -> 0.95063002 | S47: =N47/H47 -> 0.95063002 | U47: '2000 - SE'! | V47: =IF(A47="",LEFT(A46,4),LEFT(A47,4)) -> 0000
A48: 0007 - Capacitação de Servidores Públicos Federais em Processo de Qualificação e Requalificação | B48: Despesas correntes | C48: 1000000 | D48: 926737 | E48: 588071 | H48: =E48-G48-F48 -> 588071 | I48: =SUMIFS(INDIRECT($U48 & W$8),INDIRECT($U48 & "B3:B200"),$V48,INDIRECT($U48 & "D3:D200"),$B48) -> 526737 | J48: 535062.44 | K48: =J48-L48 -> 68272.45 | L48: =SUMIFS(INDIRECT($U48 & X$8),INDIRECT($U48 & "B3:B200"),$V48,INDIRECT($U48 & "D3:D200"),$B48) -> 466789.99 | M48: =SUMIFS(INDIRECT($U48 & Y$8),INDIRECT($U48 & "B3:B200"),$V48,INDIRECT($U48 & "D3:D200"),$B48) -> 338040.49 | N48: =SUMIFS(INDIRECT($U48 & Z$8),INDIRECT($U48 & "B3:B200"),$V48,INDIRECT($U48 & "D3:D200"),$B48) -> 338040.49 | O48: =H48-K48-L48 -> 53008.56 | P48: =I48/H48 -> 0.89570307 | Q48: =L48/H48 -> 0.79376468 | R48: =M48/H48 -> 0.57482938 | S48: =N48/H48 -> 0.57482938 | U48: '2000 - SE'! | V48: =IF(A48="",LEFT(A47,4),LEFT(A48,4)) -> 0007
A49: 000B - Ajuda de custo (mobilização e desmobilização) | B49: Despesas correntes | C49: 1500000 | D49: 1390106 | E49: 590106 | H49: =E49-G49-F49 -> 590106 | I49: =SUMIFS(INDIRECT($U49 & W$8),INDIRECT($U49 & "B3:B200"),$V49,INDIRECT($U49 & "D3:D200"),$B49) -> 1500000 | J49: 371386.4 | K49: =J49-L49 -> 0 | L49: =SUMIFS(INDIRECT($U49 & X$8),INDIRECT($U49 & "B3:B200"),$V49,INDIRECT($U49 & "D3:D200"),$B49) -> 371386.4 | M49: =SUMIFS(INDIRECT($U49 & Y$8),INDIRECT($U49 & "B3:B200"),$V49,INDIRECT($U49 & "D3:D200"),$B49) -> 349478.89 | N49: =SUMIFS(INDIRECT($U49 & Z$8),INDIRECT($U49 & "B3:B200"),$V49,INDIRECT($U49 & "D3:D200"),$B49) -> 349478.89 | O49: =H49-K49-L49 -> 218719.6 | P49: =I49/H49 -> 2.5419162 | Q49: =L49/H49 -> 0.6293554 | R49: =M49/H49 -> 0.5922307 | S49: =N49/H49 -> 0.5922307 | U49: '2000 - SE'! | V49: =IF(A49="",LEFT(A48,4),LEFT(A49,4)) -> 000B
A50: 000C - Ajuda de custo para Estagiários | B50: Despesas correntes | C50: 1000000 | D50: 926737 | E50: 626737 | H50: =E50-G50-F50 -> 626737 | I50: =SUMIFS(INDIRECT($U50 & W$8),INDIRECT($U50 & "B3:B200"),$V50,INDIRECT($U50 & "D3:D200"),$B50) -> 1000000 | J50: 456000 | K50: =J50-L50 -> 0 | L50: =SUMIFS(INDIRECT($U50 & X$8),INDIRECT($U50 & "B3:B200"),$V50,INDIRECT($U50 & "D3:D200"),$B50) -> 456000 | M50: =SUMIFS(INDIRECT($U50 & Y$8),INDIRECT($U50 & "B3:B200"),$V50,INDIRECT($U50 & "D3:D200"),$B50) -> 410439.79 | N50: =SUMIFS(INDIRECT($U50 & Z$8),INDIRECT($U50 & "B3:B200"),$V50,INDIRECT($U50 & "D3:D200"),$B50) -> 410439.79 | O50: =H50-K50-L50 -> 170737 | P50: =I50/H50 -> 1.5955656 | Q50: =L50/H50 -> 0.72757792 | R50: =M50/H50 -> 0.65488361 | S50: =N50/H50 -> 0.65488361 | U50: '2000 - SE'! | V50: =IF(A50="",LEFT(A49,4),LEFT(A50,4)) -> 000C
A51: 000F - Integração e Aquisição de Tecnologia da Informação | B51: Despesas correntes | C51: 1400000 | D51: 1308422 | E51: 1200471 | H51: =E51-G51-F51 -> 1200471 | I51: =SUMIFS(INDIRECT($U51 & W$8),INDIRECT($U51 & "B3:B200"),$V51,INDIRECT($U51 & "D3:D200"),$B51) -> 1400000 | J51: 1169337.2 | K51: =J51-L51 -> 718865.62 | L51: =SUMIFS(INDIRECT($U51 & X$8),INDIRECT($U51 & "B3:B200"),$V51,INDIRECT($U51 & "D3:D200"),$B51) -> 450471.58 | M51: =SUMIFS(INDIRECT($U51 & Y$8),INDIRECT($U51 & "B3:B200"),$V51,INDIRECT($U51 & "D3:D200"),$B51) -> 101171.82 | N51: =SUMIFS(INDIRECT($U51 & Z$8),INDIRECT($U51 & "B3:B200"),$V51,INDIRECT($U51 & "D3:D200"),$B51) -> 101171.82 | O51: =H51-K51-L51 -> 31133.8 | P51: =I51/H51 -> 1.1662089 | Q51: =L51/H51 -> 0.3752457 | R51: =M51/H51 -> 0.084276771 | S51: =N51/H51 -> 0.084276771 | U51: '2000 - SE'! | V51: =IF(A51="",LEFT(A50,4),LEFT(A51,4)) -> 000F
B52: Investimento | C52: 1000000 | D52: 926738 | E52: 147222 | H52: =E52-G52-F52 -> 147222 | I52: =SUMIFS(INDIRECT($U52 & W$8),INDIRECT($U52 & "B3:B200"),$V52,INDIRECT($U52 & "D3:D200"),$B52) -> 1000000 | J52: 147221.25 | K52: =J52-L52 -> 141673.7 | L52: =SUMIFS(INDIRECT($U52 & X$8),INDIRECT($U52 & "B3:B200"),$V52,INDIRECT($U52 & "D3:D200"),$B52) -> 5547.55 | M52: =SUMIFS(INDIRECT($U52 & Y$8),INDIRECT($U52 & "B3:B200"),$V52,INDIRECT($U52 & "D3:D200"),$B52) -> 0 | N52: =SUMIFS(INDIRECT($U52 & Z$8),INDIRECT($U52 & "B3:B200"),$V52,INDIRECT($U52 & "D3:D200"),$B52) -> 0 | O52: =H52-K52-L52 -> 0.75 | P52: =I52/H52 -> 6.7924631 | Q52: =L52/H52 -> 0.037681529 | R52: =M52/H52 -> 0 | S52: =N52/H52 -> 0 | U52: '2000 - SE'! | V52: =IF(A52="",LEFT(A51,4),LEFT(A52,4)) -> 000F
A53: 0010 - Conservação de ativos da União | B53: Despesas correntes | C53: 1000000 | D53: 926737 | E53: 926737 | H53: =E53-G53-F53 -> 926737 | I53: =SUMIFS(INDIRECT($U53 & W$8),INDIRECT($U53 & "B3:B200"),$V53,INDIRECT($U53 & "D3:D200"),$B53) -> 1000000 | J53: 811290.66 | K53: =J53-L53 -> 0 | L53: =SUMIFS(INDIRECT($U53 & X$8),INDIRECT($U53 & "B3:B200"),$V53,INDIRECT($U53 & "D3:D200"),$B53) -> 811290.66 | M53: =SUMIFS(INDIRECT($U53 & Y$8),INDIRECT($U53 & "B3:B200"),$V53,INDIRECT($U53 & "D3:D200"),$B53) -> 0 | N53: =SUMIFS(INDIRECT($U53 & Z$8),INDIRECT($U53 & "B3:B200"),$V53,INDIRECT($U53 & "D3:D200"),$B53) -> 0 | O53: =H53-K53-L53 -> 115446.34 | P53: =I53/H53 -> 1.0790548 | Q53: =L53/H53 -> 0.87542707 | R53: =M53/H53 -> 0 | S53: =N53/H53 -> 0 | U53: '2000 - SE'! | V53: =IF(A53="",LEFT(A52,4),LEFT(A53,4)) -> 0010
B54: Investimento | C54: 1000000 | D54: 926738 | E54: 24150 | H54: =E54-G54-F54 -> 24150 | I54: =SUMIFS(INDIRECT($U54 & W$8),INDIRECT($U54 & "B3:B200"),$V54,INDIRECT($U54 & "D3:D200"),$B54) -> 1000000 | J54: 24149.93 | K54: =J54-L54 -> 13799.96 | L54: =SUMIFS(INDIRECT($U54 & X$8),INDIRECT($U54 & "B3:B200"),$V54,INDIRECT($U54 & "D3:D200"),$B54) -> 10349.97 | M54: =SUMIFS(INDIRECT($U54 & Y$8),INDIRECT($U54 & "B3:B200"),$V54,INDIRECT($U54 & "D3:D200"),$B54) -> 4199.99 | N54: =SUMIFS(INDIRECT($U54 & Z$8),INDIRECT($U54 & "B3:B200"),$V54,INDIRECT($U54 & "D3:D200"),$B54) -> 4199.99 | O54: =H54-K54-L54 -> 0.07 | P54: =I54/H54 -> 41.407867 | Q54: =L54/H54 -> 0.42857019 | R54: =M54/H54 -> 0.17391263 | S54: =N54/H54 -> 0.17391263 | U54: '2000 - SE'! | V54: =IF(A54="",LEFT(A53,4),LEFT(A54,4)) -> 0010
A55: 216H - Ajuda de Custo para Moradia ou Auxílio-Moradia a Agentes Públicos | C55: =SUBTOTAL(109,C56:C56) -> 1500000 | D55: =SUBTOTAL(109,D56:D56) -> 1390108 | E55: =SUBTOTAL(109,E56:E56) -> 1390108 | F55: =SUBTOTAL(109,F56:F56) -> 0 | G55: =SUBTOTAL(109,G56:G56) -> 0 | H55: =SUBTOTAL(109,H56:H56) -> 1390108 | I55: =SUBTOTAL(109,I56:I56) -> 1500000 | J55: =SUBTOTAL(109,J56:J56) -> 1200000 | ... O55: =SUBTOTAL(109,O56:O56) -> 190108 | P55: =I55/H55 -> 1.0790529 | Q55: =L55/H55 -> 1 | R55: =M55/H55 -> 0.62938254 | S55: =N55/H55 -> 0.62938254
A56: 0000 - Ajuda de Custo para Moradia ou Auxílio-Moradia a Agentes Públicos | B56: Despesas correntes | C56: 1500000 | D56: 1390108 | E56: 1390108 | H56: =E56-G56-F56 -> 1390108 | I56: =SUMIFS(INDIRECT($U56 & W$8),INDIRECT($U56 & "B3:B200"),$V56,INDIRECT($U56 & "D3:D200"),$B56) -> 1500000 | J56: 1200000 | K56: =J56-L56 -> -190108 | L56: =SUMIFS(INDIRECT($U56 & X$8),INDIRECT($U56 & "B3:B200"),$V56,INDIRECT($U56 & "D3:D200"),$B56) -> 1390108 | M56: =SUMIFS(INDIRECT($U56 & Y$8),INDIRECT($U56 & "B3:B200"),$V56,INDIRECT($U56 & "D3:D200"),$B56) -> 874909.71 | N56: =SUMIFS(INDIRECT($U56 & Z$8),INDIRECT($U56 & "B3:B200"),$V56,INDIRECT($U56 & "D3:D200"),$B56) -> 874909.71 | O56: =H56-K56-L56 -> 190108 | P56: =I56/H56 -> 1.0790529 | Q56: =L56/H56 -> 1 | R56: =M56/H56 -> 0.62938254 | S56: =N56/H56 -> 0.62938254 | U56: '216H - SE'! | V56: =IF(A56="",LEFT(A55,4),LEFT(A56,4)) -> 0000 | AA56: =H56-I56 -> -109892
A57: 4641 - Publicidade de Utilidade Pública | C57: =SUBTOTAL(109,C58:C58) -> 1000000 | D57: =SUBTOTAL(109,D58:D58) -> 985707 | E57: =SUBTOTAL(109,E58:E58) -> 985707 | F57: =SUBTOTAL(109,F58:F58) -> 985707 | G57: =SUBTOTAL(109,G58:G58) -> 0 | H57: =SUBTOTAL(109,H58:H58) -> 0 | I57: =SUBTOTAL(109,I58:I58) -> 0 | J57: =SUBTOTAL(109,J58:J58) -> 0 | ... O57: =SUBTOTAL(109,O58:O58) -> 0 | P57: =I57/H57 -> #DIV/0! | Q57: =L57/H57 -> #DIV/0! | R57: =M57/H57 -> #DIV/0! | S57: =N57/H57 -> #DIV/0! | AA57: =H57-I57 -> 0
A58: 0000 - Publicidade de Utilidade Pública | B58: Despesas correntes | C58: 1000000 | D58: 985707 | E58: 985707 | F58: 985707 | H58: =E58-G58-F58 -> 0 | K58: =J58-L58 -> 0 | O58: =H58-K58 -> 0 | P58: =I58/H58 -> #DIV/0! | Q58: =L58/H58 -> #DIV/0! | R58: =M58/H58 -> #DIV/0! | S58: =N58/H58 -> #DIV/0! | U58: 4641 - SE'! | V58: 0000 | AA58: =H58-I58 -> 0

Sheet 2000 - SE
A1: ACOMPANHAMENTO EXECUÇÃO FINALÍSTICAS - 2025
A2: UNIDADE | B2: PO | C2: ANO DE FORMALIZAÇÃO | D2: GRUPO DE DESPESA | E2: INICIATIVAS | F2: SEI | G2: DIRETORIA | H2: RESPONSÁVEL PELA FORMALIZAÇÃO | I2: INSTRUMENTO | J2: SIAFI | K2: PARCEIRO | L2: PROGRAMADO 2026 | M2: EMPENHADO 2026 | N2: LIQUIDADO 2026 | O2: PAGO 2026 | P2: STATUS | Q2: OBSERVAÇÃO (PENDÊNCIAS)
A3: SECRETARIA EXECUTIVA | B3: 0000 | C3: 2025 | D3: Despesas Correntes | E3: Administração da Unidade - Despesas Diversas | F3: Vários | G3: DGA | H3: Jeremias | I3: Contrato | J3: não há | K3: Vários | L3: 30065065 | M3: 30695767 | N3: 19889117 | O3: 19481126
B4: 0000 | D4: Investimento | E4: Administração da Unidade - Despesas Diversas | F4: Vários | G4: DGA | H4: Jeremias | I4: Contrato | J4: não há | K4: Vários | L4: 1000000 | M4: 168239 | N4: 160319 | O4: 160319
B5: 0007 | D5: Despesas Correntes | E5: 0007 - Capacitação de Servidores Públicos Federais em Processo de Qualificação e Requalificação | F5: Vários | G5: DGA | H5: Jeremias | I5: Contrato | J5: não há | K5: Vários | L5: 526737 | M5: 466789.99 | N5: 338040.49 | O5: 338040.49
B6: 000B | D6: Despesas Correntes | E6: 000B - Ajuda de custo (mobilização e desmobilização) | F6: Vários | G6: DGA | H6: Jeremias | I6: Contrato | J6: não há | K6: Vários | L6: 1500000 | M6: 371386.4 | N6: 349478.89 | O6: 349478.89
B7: 000C | D7: Despesas Correntes | E7: 000C - Ajuda de custo para Estagiários | F7: Vários | G7: DGA | H7: Jeremias | I7: Contrato | J7: não há | K7: Vários | L7: 1000000 | M7: 456000 | N7: 410439.79 | O7: 410439.79
B8: 000F | D8: Despesas Correntes | E8: 000F - Integração e Aquisição de Tecnologia da Informação | F8: Vários | G8: DGA | H8: Jeremias | I8: Contrato | J8: não há | K8: Vários | L8: 1400000 | M8: 450471.58 | N8: 101171.82 | O8: 101171.82
B9: 000F | D9: Investimento | E9: 000F - Integração e Aquisição de Tecnologia da Informação | F9: Vários | G9: DGA | H9: Jeremias | I9: Contrato | J9: não há | K9: Vários | L9: 1000000 | M9: 5547.55
B10: 0010 | D10: Despesas Correntes | E10: 0010 - Conservação de ativos da União | F10: Vários | G10: DGA | H10: Jeremias | I10: Contrato | J10: não há | K10: Vários | L10: 1000000 | M10: 811290.66
B11: 0010 | D11: Investimento | E11: 0010 - Conservação de ativos da União | F11: Vários | G11: DGA | H11: Jeremias | I11: Contrato | J11: não há | K11: Vários | L11: 1000000 | M11: 10349.97 | N11: 4199.99 | O11: 4199.99
G13: TOTAL | L13: =SUM(L3:L12) -> 38491802 | M13: =SUM(M3:M12) -> 33435842 | N13: =SUM(N3:N12) -> 21252767 | O13: =SUM(O3:O12) -> 20844776
G14: Dotação livre para empenho | L14: ='Consolidado 2026'!H45 -> 36121393
G15: (%) PLE/PROGRAMADO | L15: =L13/L14 -> 1.0656234
P17: 267237.57

Sheet 216H - SE
A2: ACOMPANHAMENTO EXECUÇÃO GESTÃO - 2025
A3: UNIDADE | B3: PO | C3: ANO DE FORMALIZAÇÃO | D3: GRUPO DE DESPESA | E3: INICIATIVAS | F3: SEI | G3: DIRETORIA | H3: RESPONSÁVEL PELA FORMALIZAÇÃO | I3: INSTRUMENTO | J3: SIAFI | K3: PARCEIRO | L3: PROGRAMADO 2026 | M3: EMPENHADO 2026 | N3: LIQUIDADO 2026 | O3: PAGO 2026 | P3: STATUS
A4: SECRETARIA EXECUTIVA | B4: 0000 | C4: 2025 | D4: Despesas correntes | E4: não há | F4: Vários | G4: DGA | H4: Jerê / Nayara | I4: Pessoal | J4: não há | K4: não há | L4: 1500000 | M4: 1390108 | N4: 874909.71 | O4: 874909.71 | P4: Empenhado
G8: TOTAL | L8: =SUM(L4:L7) -> 1500000 | M8: =SUM(M4:M7) -> 1390108 | N8: =SUM(N4:N7) -> 874909.71 | O8: =SUM(O4:O7) -> 874909.71
G9: Dotação livre para empenho | L9: ='Consolidado 2026'!H55 -> 1390108
G10: (%) PLE/PROGRAMADO | L10: =L8/L9 -> 1.0790529

Sheet 21FC - SENAPIR
A1: ACOMPANHAMENTO EXECUÇÃO FINALÍSTICAS - 2025
A2: UNIDADE | B2: PO | C2: ANO DE FORMALIZAÇÃO | D2: GRUPO DE DESPESA | E2: INICIATIVAS | F2: SEI | G2: DIRETORIA | H2: RESPONSÁVEL PELA FORMALIZAÇÃO | I2: INSTRUMENTO | J2: SIAFI | K2: PARCEIRO | L2: PROGRAMADO 2026 | M2: EMPENHADO 2026 | N2: LIQUIDADO 2026 | O2: PAGO 2026 | P2: STATUS | Q2: PREVISÃO DE DESCENTRALIZAÇÃO | R2: OBSERVAÇÃO (PENDÊNCIAS) | S2: ENTREGA PPA
A3: SENAPIR | B3: 0000 | C3: 2026 | D3: Despesas correntes | E3: DIARIAS E PASSAGENS /DESPESAS ADMINISTRATIVAS | I3: CONTRATO | L3: 2473982 | M3: 2182615.8 | N3: 1397287.1 | O3: 1397287.1 | Q3: -
B4: 0001 | C4: 2023 | D4: Despesas correntes | E4: Cooperação para realização de pesquisas e desenvolvimento de indicadores e monitoramento de políticas públicas | F4: 21290.200603/2023-66 | G4: DAMGI | H4: Luciano Silva | I4: TED | J4: 945512 | K4: IPEA | L4: 117720 | P4: Empenhado | Q4: - | R4: 19/10/26: Despacho(65118481) Comunicação do fim de vigência; 13/10/26: Ofício(64906505) Prestação de Contas da Descentralização de Crédito - IPEA; 28/09/26: Despacho (64641576)envio do Ofício ao IPEA solcitando RCO; 21/09/26: Despacho (64409549) solicitação RCO; 14/09/26: Despacho(63724637) Comunicação fim da vigência 22/09/26; 17/08/26: Ofício DGA (63658861) Comunicação de fim de vigência do TED; 10/08/26: Nota Técnica(62835977) Análise do RCO. 20/07/26: TED em execução. Conforme cronograma plano de trabalho do TED, 2026NC000088 (57431120)e 2026PF000022 (57732657) emitidas em fevereiro/2026. | S4: 2071 - Observatório de monitoramento e avaliação do SINAPIR
B5: 0001 | C5: 2025 | D5: Despesas correntes | E5: ADITIVO - Plataforma ODS Racial - Monitoramento e inteligência de dados de indicadores da população negra no Brasil | F5: 21290.200789/2023-53 | G5: DAMGI | H5: Leandro/Luciano Silva | I5: TED | J5: 946960 | K5: UFPB | L5: 72000 | M5: 72000 | P5: Empenhado | Q5: junho | R5: 19/10/26: Anexo (65247630) Resposta a Nota Técnica nº 187/2026/MIR; 13/10/26: Despacho (64978265)repasse financeiro no valor de R$ 28.500,00; 05/10/26: Declaração(64901388); 28/09/26: Despacho(64553703)repasse financeiro no valor de R$ 9.000,00;14/09/26: Despacho (63981888) repasse financeiro no valor de R$ 20.000,00; 24/08/26: Despacho (63842878) repasse financeiro no valor de R$ 4.000,00 em 24/08/26; 17/08/26: Despacho (63293462) repasse financeiro no valor de R$ 2.000,00 em 02/08/26; 27/07/26: Ofício Gab (63126977)Celebração de Termo Aditivo de Suplementação, Vigência e Repasse financeiro; 20/07/26: Descentralização Orçamentária (62788574); 06/07/26: Termo Aditivo aguardando assinatura da Ministra(62321007). Autorização prévia celebração de termo aditivo de vigência com suplementação de recursos. 16/06/26: Aguardando a resposta da SE ao Ofício do Gabinete (60546011); 26/05/2026: O Aditivo correspondente a inclusão de uma nova meta objetivando: novas funcionalidades à Plataforma ODS Racial, o ajuste de prazos de entrega e a adequação do cronograma de desembolso. Ofício(60172451) de 10/04/2026 encaminhando a Minuta do Aditivo de Termo de Execução Descentralização - TED (56583856) e Minuta do Plano de Trabalho atualizado (56574438) | S5: 2071 - Observatório de monitoramento e avaliação do SINAPIR
B6: 0001 | C6: 2023 | D6: Despesas correntes | E6: Plataforma ODS Racial - Monitoramento e inteligência de dados de indicadores da população negra no Brasil | F6: 21290.200789/2023-53 | G6: DAMGI | H6: Leandro/Luciano Silva | I6: TED | J6: 946960 | K6: UFPB | L6: =45716.3 -> 45716.3 | M6: 42214.39 | N6: 20003.91 | O6: 16503.91 | P6: Empenhado | Q6: junho | R6: 19/10/26: Anexo (65247630) Resposta a Nota Técnica nº 187/2026/MIR; 13/10/26: Despacho (64978265)repasse financeiro no valor de R$ 28.500,00; 05/10/26: Declaração(64901388); 28/09/26: Despacho(64553703)repasse financeiro no valor de R$ 9.000,00; 14/09/26: Despacho (63981888) repasse financeiro no valor de R$ 20.000,00; 24/08/26: Despacho (63842878) repasse financeiro no valor de R$ 4.000,00 em 24/08/26; 17/08/26: Despacho (63293462) repasse financeiro no valor de R$ 2.000,00 em 02/08/26; 27/07/26: Ofício Gab (63126977)Celebração de Termo Aditivo de Suplementação e Vigência e Repasse financeiro; 20/07/26: Descentralização Orçamentária (62788574); 06/07/26: Termo Aditivo aguardando assinatura da Ministra(62321007). Autorização prévia celebração de termo aditivo de vigência com suplementação de recursos. 16/06/26: Aguardando a resposta da SE ao Ofício do Gabinete (60546011); 26/05/2026: corresponde a novo empenho tendo em vista anulação de empenho/devolução de crédito, conforme e-mail da Instituição à CGMO e à DGA em novembro/2025. Constitui parte do valor do aditivo, o qual totalizará R$ 117.716,30. | S6: 2071 - Observatório de monitoramento e avaliação do SINAPIR
B7: 0001 | C7: 2025 | D7: Despesas correntes | E7: ADITIVO - Apoio a pesquisa e eventos (CNPQ) | F7: 21290.200530/2024-93 | G7: DAMGI | H7: Ana Carolina | I7: TED | J7: 958214 | K7: CNPQ | P7: Instrução Processual | Q7: junho | R7: 19/10/26: Despacho (64864975)repasse financeiro no valor de R$ 98.760,00; 28/09/26: Despacho (63993205) repasse financeiro no valor de R$ 98.760,00; 24/08/26: Despacho(63713250) Reunião de Apresentação dos projetos selecionados pela Chamada CNPq/MIR nº 18/2025; 17/08/26: Despacho (63292965) repasse financeiro no valor de R$ 107.660,00; 27/07/26: Despacho (62715339)repasse financeiro no valor de R$ 109.310,00; 20/07/26: Aguardando a resposta da solicitação do RCO (61672471). Por sugestão do CNPQ, será desmembrado em a) 1 aditivo de 223 mil, para recurso de custeio e apoio a projetos remanescentes e 2) novo TED, com recurso contrapartida Edital Lelia Gonzalez. Reunião agendada para 08 de junho para revisão no Plano de trabalho. 26/05/2026: O TED está em execução. O recurso programado corresponde a um aditivo. Objetiva a realização de uma nova chamada pública de projetos de pesquisa voltados à temática racial, bem como a suplementação da chamada realizada em 2025. Manifestação de interesse enviada (SEI 56210415). Aguardando Plano de Trabalho. | S7: 2071 - Observatório de monitoramento e avaliação do SINAPIR
B8: 0001 | C8: 2025 | D8: Despesas correntes | E8: Apoio a pesquisas - Edital Lélia Gonzalez | F8: 21290.002101/2026-14 | G8: DAMGI | H8: Ana Carolina | I8: TED | K8: CNPQ | P8: Instrução Processual | Q8: junho | R8: 19/10/26: Ofício(64959423) Diligências; 05/10/26: TED 22(64490576) a ser assinado; 14/09/26: Nota Informativa (64101324) Ajuste no Cronograma de Desembolso; 31/08/26: Despacho DGA(63942470) autorização prévia; 24/08/26: Despacho DGA (63847784) com análise da documentação verificou-se que o processo encontra-se regularmente instruído;17/08/26: Nota Informativa DAMGI(63670143) a ser assinada; 05/08/26: Ofício(63315344)à SE e DGA. Encaminhamento de proposta de TED entre o MIR e CNPq; 03/08/26: Despacho DAMGI(62970623)para celebração do TED; 06/07/26: Resposta do CNPQ a manifestação de interesse, Ofício (62599686); 29/06/26: Redução do valor programado de R$ 2mi para R$ 1,5mi. 22/06/26: Despacho DAMGI(62204132) manifestação de interesse. Novo TED - Apoio a Pesquisas e Edital Lelia Gonzalez 1.500.000,00
B9: 0001 | C9: 2025 | D9: Despesas correntes | E9: INCLUA - Igualdade Racial | F9: 21290.001303/2025-68 | G9: DAMGI | H9: Ana Carolina | I9: TED | J9: 978843 | K9: IPEA | L9: 532400 | M9: 532400 | N9: 16080.49 | O9: 16080.49 | P9: Empenhado | Q9: - | R9: 19/10/26: Despacho(64953810) Encaminhamento da relação de municípios selecionados para participação no assessoramento relacionado à Plataforma Inclua Igualdade Racial; 05/10/26: Ofício SE(64846317) a ser assinado;28/09/26: Despacho(64680976) Encaminhamento da relação de municípios selecionados para participação no assessoramento Inclua; 21/09/26: Nota Técnica (63871862)Análise parcial RCO; 24/08/26: Despacho (62951307) encaminhando os ofícios ao IPEA; 17/08/26: Ofício 12502 (62948671) encaminhado ao IPEA em 17/07/26; 13/07/26: Despacho suspensão IA. Defeso Eleitoral(62825185);06/07/26: TED em execução. Conforme cronograma plano de trabalho do TED, Nota de Crédito - 2026NC000010 (57303054) emitida em janeiro/2026. 2026PF000023 (57737226) em fevereiro de 2026. | S9: 2071 - Observatório de monitoramento e avaliação do SINAPIR
B10: 0001 | C10: 2024 | D10: Despesas correntes | E10: UFSB - Observatório ODS 18 | F10: 21290.201857/2024-82 | G10: DAMGI | H10: Emanuel/Luciano Silva | I10: TED | J10: 966020 | K10: UFSB | L10: 536699.31 | M10: 536699.31 | N10: 536699.31 | O10: 536699.31 | P10: Pago/Liquidado | Q10: junho | R10: 19/10/26: Despacho (62690910) Repasse financeiro no valor de R$ 901.699,31 em 08/07/26; 13/07/26: Valor liquidado R$ 536.699,31; 06/07/26: valor empenhado R$ 536.699,31; 26/05/2026: Programado para abril/2026. Conforme cronograma plano de trabalho do TED, 2026NC0000075, SEI-57260689 emitida em janeiro/2026. Estorno da 2026NC0000075(SEI-57265246) em janeiro/2026. Parcel | S10: 2071 - Observatório de monitoramento e avaliação do SINAPIR
B11: 0001 | C11: 2025 | D11: Despesas correntes | E11: TED - UFSB - Estratrégias de Territorialização do ODS18 (continuidade das ações do Observatório do ODS 18), voltadas para entes subnacionais e OSC | F11: 21290.004241/2025-46 | G11: DAMGI | H11: Luciano Silva | I11: TED | K11: UFSB | L11: 223435 | P11: Instrução Processual | Q11: julho | R11: 19/10/26: Ofício Gab SENAPIR (64927041)a ser assinado; 05/10/26: Despacho (64600062)encaminhando TED; 21/09/26: Despacho SE(64129045) a ser assinado; 31/08/26: Despacho DGA(63792446)processo encontra-se regularmente instruído; 24/08/26: Despacho DGA (63769592)Resposta da solicitação de cumprimento da Portaria GAB/MIR nº 394; 17/08/26: Despacho DAMGI (63663029) Cumprimento da Portaria GAB/MIR nº 394, 15/07/26; 10/08/26: Portaria(63449564) fluxo de instrução, análise e tramitação dos processos administrativos;03/08/26: Ofício (62982241)à SE para celebração do TED; 20/07/26: Despacho DAMGI (62956804) ao Gabinete; 13/07/26:Aguardando assinatura do Secretário para SE(Ofício 62124772);11/06/26:Encaminhado Despacho 62036120 ao Gab SENAPIR com justes realizados em virtude das recomendações solicitadas pela Secretaria-Executiva; 28/05 - em ajuste, cf recomendações SE MIR. 26/05/2026 Aguardando apreciação SE/MIR - Ofício SENAPIR enviado em 20/5 SEI 57777491; 06/04/2026:(Despacho 59510990, de 28/01/26 - Instrução concluída na Diretoria). Instrução revisada na Diretoria, conforme NT 57611365, alterando o cronograma de desembolso para 2026 (R$ 1 milhão para 2026). Despacho 59510990, de 27/03/26, para Gabinete SENAPIR | S11: 2071 - Observatório de monitoramento e avaliação do SINAPIR
B12: 0001 | C12: 2026 | D12: Despesas correntes | E12: FIAR - ENAP Oferta de cursos síncronos e novo curso | F12: 21290.002743/2026-13 | G12: DAMGI | H12: Ana Carolina | I12: TEDinho | K12: ENAP | L12: 85000 | P12: Instrução Processual | Q12: - | R12: 19/10/26: Ofício(64959975) Proposta de parceria para curso sobre orçamento sensível a raça; 05/10/26: Despacho (64465148) Comunica o envio do Ofício Enap; 14/09/26: Ofício(64362344) Manifestação de Interesse; 08/09/26: Despacho DAMGI(62834700) encaminhando Minuta de Ofício (Manifestação de interesse) em 16/07/26; 20/07/26: CGAGC instrurá novo processo com Manifestação de interesse para Curso Síncrono - Orçamento sensivel a raça - verificar processo com Ana Carolina 13/07/26: Não ocorrerá em 2026; 22/12/2025: Ações do FIAR, para programação junto à ENAP Verificar com a Carol | S12: 0400 - Formação de gestores públicos para promoção da igualdade racial
B13: 0001 | C13: 2026 | D13: Despesas correntes | E13: FIAR - FIAR Novos cursos na EVG (Escola Virtual de Governo) - atendimento ao público | F13: 21290.001685/2026-19 | G13: DAMGI | H13: Ana Carolina | I13: TEDinho | K13: ENAP | P13: Planejamento | Q13: - | R13: 19/10/26: Checklist de Instrução Mínima Obrigatória (65171082); 13/10/26: Despacho (64245486) Manifestação de Interesse; 21/09/26: Despacho(64245486) envio do Ofício Manifestação de Interesse; 08/09/26: Ofício (64213089)Manifestação de Interesse para o devido acompanhamento; 31/08/26: Ofício Gab (63650358) a ser assinado; 10/08/26: Despacho DAMGI (63449289), a ser assinado, encaminhando Minuta de Ofício sobre descentralização de créditos entre MIR e Enap no âmbito do FIAR; 03/08/26:Novos cursos EVG: Parcerias com a Diretoria de Desenvolvimento Profissional DDPro-Enap. Ainda não enviado para ENAP. 13/07/26 Ações do FIAR, processo iniciado. Novos cursos EVG | S13: 0400 - Formação de gestores públicos para promoção da igualdade racial
B14: 0001 | C14: 2025 | D14: Despesas correntes | E14: FIAR ENAP - Vagas para servidores negros do Sinapir em MBA em gestão pública | F14: 21290.001553/2025-06 | G14: DAMGI | H14: Ana Carolina | I14: TEDinho | K14: ENAP | L14: 55566.42 | M14: 38945.56 | N14: 24278.39 | O14: 24278.39 | P14: Aguardando Empenho | Q14: - | R14: 19/10/26: Relatório parcial prestação de contas (63783310); 17/08/26: e-mail (61462875) sobre vagas remananescentes em 29/04/26; 27/07/26: repassado o financeiro em janeiro/2026 (SEI 57424120). 2026NC0000044 (57172406) emitida em janeiro/2026 corresponde à última parcela do TED. 22/12/2025: TED em execução. Conforme apostilamento (SEI 55813777), após a assinatura foi descentralizado o valor R$ 19.579,72 (SEI 55666534). | S14: 0400 - Formação de gestores públicos para promoção da igualdade racial
B15: 0001 | C15: 2025 | D15: Despesas correntes | E15: TED UNB - Casa da Igualdade Racial (disseminação do apoio aos Núcleos de prática jurídica e outros serviços voltados para a Casa) | F15: 21290.004151/2025-55 | G15: DAMGI | H15: Ana Carolina | I15: TED | K15: UNB | P15: Instrução Processual | Q15: - | R15: 19/10/26: Despacho(56580718)encaminhamento do Ofício 18096 (56518582) à UnB; 13/10/26: Redução do valor programado de R$ 2,9 mi para R$ 0,00. Aguardando resposta da UNB, desde dezembro/2025, ao OFÍCIO SEI Nº 18096/2025/MIR 56518582. Plano de trabalho, em análise na DAMGI/CGAGC. Realizadas reuniões com SEA e DAMGI/MIR, para fortalecimento da Casa da Igualdade Racial. Solicitação de Manifestação de interesse encaminhada ao Gabinete SENAPIR em 09/12/2025 - (SEI 56182188). O TED objetiva apoiar núcleos de pesquisa e extensão no desenvolvimento de ações nas Casas de Igualdade de Racial. A ação proposta tem foco no fortalecimento do atendimento multidisciplinar à vítima de racismo, abrangendo suporte jurídico, psicossocial e ações de promoção da igualdade racial, alinhadas às políticas públicas do Governo Federal e às atribuições desde Ministério. | S15: 2071 - Observatório de monitoramento e avaliação do SINAPIR
B16: 0001 | C16: 2026 | D16: Despesas correntes | E16: Projetos Redes – TEDs com IFES das cinco regiões, a partir de chamamento público; | F16: 21290.200112/2024-04 | G16: DAMGI | H16: Tatiana | I16: TED | K16: Diversos | P16: Instrução Processual | Q16: - | R16: 19/10/26: memória de reunião(50682620) em 13/05/2025; 17/08/26: encaminhado o Ofício 18096 (56518582) à Universidade de Brasília em 23/12/25; 27/07/26: Exclusão do valor programado. 22/06/2026: Edital em elaboração. Ver com a Tatiana | S16: 2071 - Observatório de monitoramento e avaliação do SINAPIR
B17: 0001 | C17: 2025 | D17: Despesas correntes | E17: TED - UFF sobre orçamento público de igualdade racial. | F17: 21290.000123/2026-40 | G17: DAMGI | H17: Luciano Silva | I17: TED | K17: UFF | P17: Instrução Processual | Q17: - | R17: 19/10/26: Ofício Gab SENAPIR(62878427) a ser assinado; 10/08/26: Despacho DAMGI (62721938)defeso eleitoral em 09/07/26; 06/07/26: Exclusão do valor programado na JEO. Está em análise, teve o valor global reduzido; 22/06/26: Despacho DAMGI 62147714 encaminhando ao Gabinete; 28/5 - Conclusão dos ajustes em PT para envio ao Gabinete SENAPIR. 06/04/2026: Processo em Instrução processual. enviado à UFF OFÍCIO SEI Nº 2677/2026/MIR em 03/03/2026 ainda sem resposta | S17: 2071 - Observatório de monitoramento e avaliação do SINAPIR
B18: 0001 | C18: 2025 | D18: Despesas correntes | E18: TED - UFF CERD | F18: 21290.000127/2026-28 | G18: DAMGI | H18: Luciano Silva | I18: TED | K18: UFF | L18: 204000 | M18: 204000 | N18: 179520 | O18: 179520 | P18: Empenhado | Q18: junho | R18: 19/10/26: e-mail (65170666) informando a liberação da programação financeira a UFF; 13/10/26:Despacho(64692938) Resposta sobre a indicação de Gestor de Parceria responsável pelo acompanhamento. Publicação; 21/09/26: Ofício (64547093) a ser assinado; 14/09/26: Despacho(63811282) Descentralização orçamentária R$ 204.000,00; 17/07/26: Despacho DAMGI(63659507) ao Gab indicação de gestores titular e suplente; 10/08/26: Extrato de publicação do tedinho(63489682); 07/08/26: e-mail (63276521) Extrato da Descentralização de crédito - MIR X UFF; 27/07/26: Despacho(62948635) Certificação de Disponibilidade; 20/07/26: Despacho DGA (62947323) autorização prévia; 13/07/26: Despacho (62817387)defeso eleitoral; 06/07/26: Ajustes realizados e reenvio para SE/MIR em 02/06 (61811202). Instrução completa enviada para SE/MIR em 22/05 - SEI 61467420 | S18: 2071 - Observatório de monitoramento e avaliação do SINAPIR
B19: 0001 | C19: 2025 | D19: Despesas correntes | E19: ADITIVO - GTMapir Desenvolvimento de avaliações e consultorias voltadas à políticas prioritárias do GTMAPIR | F19: 21290.001930/2025-07 | G19: DAMGI | H19: Tatiana | I19: TEDinho | K19: ENAP | P19: Planejamento | Q19: - | R19: 19/10/26: e-mail(64868367) Solicitação de Pretação de contas em 1/10/26; 28/09/26: Nota Técnica(62806366)Avaliação técnica dos produtos finais (Enap); 21/09/26: Despacho Gab SENAPIR(62882663) fim de vigência em 03/06/26; 13/07/26: Nota Técnica (62806366) Avaliação técnica dos produtos finais; 06/07/26:Despacho Gab. SENAPIR (60551170) Comunicação de fim de vigência; 26/05/2026: Em discussão com ENAP, objetivo é processo de Avaliação ex-post dos demais programas estratégicos do MIR. 235.000,00 | S19: 2071 - Observatório de monitoramento e avaliação do SINAPIR
B20: 0001 | C20: 2026 | D20: Despesas correntes | E20: Seminário - Apresentação de pesquisas e política públicas | G20: DAMGI | H20: Tatiana | I20: TEDinho | L20: 60000 | P20: Planejamento | Q20: - | R20: 22/12/2025: Objetiva-se a realização de Encontro com pesquisadores ligados às estratégias do MIR de apoio a NEABs e pesquisas para fortalecimento do SINAPIR. | S20: 2071 - Observatório de monitoramento e avaliação do SINAPIR
B21: 0001 | C21: 2026 | D21: Despesas correntes | E21: FIAR - FIAR ENAP aqui - 12 turmas (Incluindo Casa da Igualdade Racial) | F21: 21290.002084/2025-34 | G21: DAMGI | H21: Ana Carolina | I21: Tedinho | K21: ENAP | L21: 66809.2 | P21: Aguardando Empenho | Q21: - | R21: 19/10/26: Ofício Gab SENAPIR(65019655) a ser assinado; 05/10/26: Despacho DAMGI(64807894) a ser assinado; 28/09/26: Ofício(64464215) Resposta sobre o Programa “Enap Aqui Igualdade Racial: Estratégias de Implementação Local”; 14/09/26:Despacho(64258697)Indicação de localidades para realização das oficinas Enap Aqui08/09/26: Despacho(64145388)Indicação de localidades para realização das oficinas Enap Aqui – Igualdade Racial: Estratégias de Implementação Local; 31/08/26: Despacho(63912851) com a Nota Informativa SEI nº 461/2026/MIR (SEI nº 63903572), que trata do andamento do programa “Enap Aqui Igualdade Racial; 24/08/26: Despacho (63846784)indicação de estados e municípios para realização de novas edições da Oficina Enap Aqui; 17/08/26: Despacho Gab(63394096)Convite para participação na abertura das Oficinas "Enap Aqui" em 06/08/26; 03/08/26: E-mail (62315453) Divulgação e apoio à mobilização para participação na Oficina "Enap Aqui! Igualdade Racial: Estratégias de Implementação Local". Ofício (62306196) 29/06/26: Nota Jurídica 62195996. não se enquadram nas proibições legais, desde que as ações efetivamente desenvolvidas se mantenham dentro do espectro meramente técnico-acadêmico, congruentes com o Programa Enap Aqui; 26/05/2026: em abril/2026 Nota de Crédito 192 (SEI 60964125)15/04/2026: aguardando assinatura pelo MIR e pela instituição para posterior publicação. 07/04/2026: Manifestação de interesse enviada (SEI 52329757). Em 01 e 02 de dezembro/2025, foi realizado projeto piloto em parceria com a SEPROMI/BA. (59699323) Certificação de Disponibilidade Orçamentária. | S21: 0400 - Formação de gestores públicos para promoção da igualdade racial
B22: 0001 | C22: 2026 | D22: Despesas correntes | E22: FIAR - FIAR Cátedras Negras | F22: 21290.002144/2026-08 | G22: DAMGI | H22: Luciano Goes | I22: Tedinho | K22: ENAP | P22: Instrução Processual | Q22: julho | R22: 19/10/26: Despacho(62540214) encaminhamento de Manifestação de Interesse à ENAP no dia 30/06/26; 17/08/26: Manifestação de interesse Ofício (62495465) em 01/07/26; 29/06/26: Ofício 62051569 Plano de Trabalho Execução Descentralizada entre MIR e ENAP encaminhado a SE. Em diálogo com ENAP, para PT. Concluindo instrução para envio de Manifestação de Interesse
B23: 0001 | C23: 2026 | D23: Despesas correntes | E23: Apoio técnico aos entes SINAPIR | G23: DAMGI | H23: Ana Carolina | I23: TED | P23: Planejamento | Q23: - | R23: 22/12/2025: Tem como objetivo instituir coordenação de pesquisadores ligados às estratégias do MIR de apoio a NEABs e pesquisas para fortalecimento do SINAPIR. Ver com Ana Carolina | S23: 0400 - Formação de gestores públicos para promoção da igualdade racial
B24: 0001 | C24: 2026 | D24: Despesas correntes | E24: FIAR - Evidências express | G24: DAMGI | H24: Ana Carolina | I24: Tedinho | K24: ENAP | P24: Planejamento | Q24: - | S24: 0400 - Formação de gestores públicos para promoção da igualdade racial
B25: 0001 | C25: 2026 | D25: Despesas correntes | E25: TED UNB - COPENE | F25: 21290.001227/2026-71 | G25: Gabinete/DAMGI | H25: Luciano Silva | I25: TED | K25: UNB | L25: 240000 | M25: 240000 | N25: 240000 | O25: 240000 | P25: Pago/Liquidado | Q25: junho | R25: 19/10/26:Roteiro(65081105) PROGRAMAÇÃO COMPLETA; 05/10/26 Ofício(64473211) Publicação da designação de gestores do TED Nº 14/2026; 14/09/26: Despacho DGA(63355674) indicação de gestores; 03/08/26: Despacho (63247545) indicação de gestores; 27/07/26: Despacho(63130733) Termo de Execução Descentralizada nº 14/2026 - MIR X UnB; 20/07/26: NC e PF emitidas; 13/07/26: Aguardando a assinatura da Ministra. TED(62745335)
B26: 0001 | C26: 2026 | D26: Despesas correntes | E26: Material Gráfico | F26: 21290.000732/2025-18 | G26: DAMGI | K26: MGI | L26: 8557.77 | M26: 7251.06 | N26: 7251.06 | O26: 7251.06 | P26: Pago/Liquidado | Q26: - | R26: 19/10/26: Valores de despesas administrativas; 22/06/26. Verificar com a Luciana Rangel outros valores que foram empenhados no PO 0001 DAMGI: UFPR R$ 1.196,38; MGI R$ 4.154,96 | S26: 0400 - Formação de gestores públicos para promoção da igualdade racial
B27: 0002 | C27: 2026 | D27: Despesas correntes | E27: Casa da Igualdade Racial 2 + Inclusão Produtiva | F27: 21290.002082/2026-26 | G27: DAMGI | H27: Edvânio Macedo | R27: 19/10/26: Ofício (62031616)manifestou seu interesse em estabelecer parceria com esse Ministério
B28: 0002 | C28: 2026 | D28: Despesas correntes | E28: Casa da Igualdade Racial 2 + Inclusão Produtiva | F28: 21290.002082/2026-26 | G28: DAI | H28: Edvânio Macedo | I28: TED | K28: FIOCRUZ | L28: 5500000.5 | P28: Planejamento | Q28: - | R28: Sem decisão técnica e política sobre a tramitação processual do instrumento adequado. A IN está em discussão interna.
B29: 0002 | C29: 2026 | D29: Despesas correntes | E29: Agentes 2 e Xica 1 | F29: 21290.002528/2025-31 | G29: DAI | H29: Edvânio Macedo | I29: TED | K29: UFRB | L29: 1541605.9 | M29: 1541605.9 | N29: 1541605.9 | P29: Empenhado | Q29: junho
B30: 0002 | C30: 2026 | D30: Despesas correntes | E30: Incubadora do Afroturismo/Rotas Negras/Centro de Estudos Estratégicos | F30: 21290.000354/2026-53 | G30: DAI | H30: Edvânio Macedo | I30: TED | K30: UFSM | L30: 5710000 | M30: 5710000 | N30: 5710000 | O30: 5710000 | P30: Pago/Liquidado | Q30: junho
B31: 0002 | C31: 2026 | D31: Despesas correntes | E31: PAS Periferias Urbanas e Racismo Ambiental - SINAPIR pelo Clima | F31: 21290.004107/2025-45 | G31: DAI | H31: Edvânio Macedo | I31: TED | K31: UFMA | L31: 980332.52 | P31: Planejamento | Q31: - | R31: Retornou para Gabin da SENAPIR com ajustes, a UFMA está realizando os últimos ajustes do plano de trabalho.
B32: 0002 | C32: 2026 | D32: Despesas correntes | E32: Fortalecimento a Cadeia Produtiva do Carnaval/Trabalhadores | F32: 21290.001137/2026-81 | G32: DAI | H32: Edvânio Macedo | I32: TED | K32: UFF | L32: 3200000 | M32: 3200000 | N32: 2944000 | O32: 2944000 | P32: Pago/Liquidado | Q32: junho
B33: 0002 | C33: 2026 | D33: Despesas correntes | E33: Aditivo Fiocruz - Casas, Flilio | F33: 21290.002700/2025-57 | G33: DAI | H33: Edvânio Macedo | I33: TED | K33: FIOCRUZ | L33: 1216094.3 | P33: Planejamento | Q33: - | R33: Aguardando a Fiocruz enviar formalmente o PT e Ofício assinado
B34: 0002 | C34: 2026 | D34: Despesas correntes | E34: UFMA ADITIVO PLANAPIR ADPF | F34: 21290.002331/2025-01 | G34: DAI | H34: Edvânio Macedo | I34: TED | K34: UFMA | L34: 200000 | M34: 200000 | P34: Empenhado | Q34: julho
B35: 0002 | C35: 2026 | D35: Despesas correntes | E35: Cronograma de desembolso de 2025, passivo para 2026. TED FIOCRUZ | F35: 21290.002700/2025-57 | G35: DAI | H35: Edvânio Macedo | I35: TED | K35: FIOCRUZ | L35: 1215974.7 | M35: 1215974.7 | P35: Empenhado | Q35: junho
B36: 0002 | C36: 2026 | D36: Investimento | E36: Edital Equipagem (licitação e 07/2026) | F36: 21290.000520/2026-11 | G36: DAI | H36: Edvânio Macedo | I36: TED | K36: MIR | P36: Instrução Processual | Q36: - | R36: Decisão política sobre alocação de valor. Atenção à Janela do GND para reversão
B37: 0001 | C37: 2026 | D37: Despesas correntes | E37: APOIO A SQPT | F37: 21290.001965/2026-19 | I37: TED | K37: UFF | L37: 2000000 | M37: 1920000 | N37: 1000000 | O37: 1000000 | Q37: - | R37: 19/10/26: Despacho(64971458) solicita a indicação dos servidores designados como Fiscal Titular e Fiscal Suplente; 05/10/26: Despacho(64869229)Descentralização de crédito no valor de R$ 2.000.000,00; 28/09/26: Ofício(64705318) Indicação de gestor da parceria; 21/09/26: Despacho (64280473) Descentralização Orçamentária
Q38: -
G39: TOTAL | L39: =SUM(L3:L37) -> 26285894 | M39: =SUM(M3:M37) -> 17643707 | N39: =SUM(N3:N36) -> 12616726 | O39: =SUM(O3:O36) -> 11071620
G40: Dotação livre para empenho | L40: ='Consolidado 2026'!H25 -> 26234345
G41: (%) PLE/PROGRAMADO | L41: =L39/L40 -> 1.0019649

Sheet 21FE - SQPT
A1: ACOMPANHAMENTO EXECUÇÃO FINALÍSTICAS - 2026
A2: UNIDADE | B2: PO | C2: ANO DE FORMALIZAÇÃO | D2: GRUPO DE DESPESA | E2: INICIATIVAS | F2: SEI | G2: DIRETORIA | H2: RESPONSÁVEL PELA FORMALIZAÇÃO | I2: INSTRUMENTO | J2: SIAFI | K2: PARCEIRO | L2: PROGRAMADO 2026 | M2: EMPENHADO 2026 | N2: LIQUIDADO 2026 | O2: PAGO 2026 | P2: STATUS | Q2: PREVISÃO DE DESCENTRALIZAÇÃO | R2: OBSERVAÇÃO (PENDÊNCIAS) | S2: ENTREGA PPA
B3: 0000 | C3: 2026 | D3: Despesas correntes | E3: DIARIAS E PASSAGENS /DESPESAS ADMINISTRATIVAS | I3: CONTRATO | L3: 2499130 | M3: 1805034.4 | N3: 1327574.9 | O3: 1327574.9 | Q3: -
B4: 0002 | C4: 2023 | D4: Despesas correntes | E4: Promover atividades formativas para Povos e Comunidades Tradicionais orientadas pelas perspectivas da sustentabilidade dos territórios, da bioculturalidade e da interculturalidade. | F4: 21290.201747/2023-30 | G4: DPTMAT | H4: Regiane | I4: TED | K4: UnB | L4: 100800 | M4: 100800 | N4: 2100 | O4: 2100 | P4: Empenhado | Q4: - | S4: Objetivo Especifíco 0264 - Criar mecanismos de identificação e enfrentamento à violência e à discriminação contra quilombolas, povos e comunidades tradicionais de matriz africana, povos de terreiros e ciganos
B5: 0001 | C5: 2023 | D5: Despesas correntes | G5: CGPC | H5: Marciele | L5: 37800 | M5: 25200 | N5: 23100 | O5: 23100 | Q5: -
B6: 0003 | C6: 2023 | D6: Despesas correntes | G6: CGPQ | H6: Erlon | L6: 189000 | M6: 189000 | N6: 189000 | O6: 189000 | Q6: -
B7: 0003 | C7: 2025 | D7: Despesas correntes | E7: Apoiar a elaboração e implementação do Plano de Gestão Territorial e Ambiental do Quilombo Kalunga, em Cavalcante-GO | F7: 21290.001522/2025-47 | G7: DQC | H7: Erlon | I7: TED | K7: IFG | L7: 500000 | P7: Instrução Processual | Q7: setembro | R7: Reunião SE 06/10 - Verificar adequação do valor da parceria Processo enviado a DGA para tramitação quanto ao apostilamento | S7: 2228 - Planos locais de Gestão Territorial e Ambiental Quilombolas
B8: 0001 | C8: 2025 | D8: Despesas correntes | E8: Plano de Recontrução do Rio Grande do Sul /Realizar diagnóstico socioeconômico em todas as comunidades impactadas pela crise; Elaboração do Plano de Reconstrução e Elaboração de protocolo de atendimento para situação de desastres ambientais | F8: 21290.001171/2025-74 | G8: CGPC | H8: Marciele | I8: TED | K8: UFRGS | L8: 318084.92 | M8: 318084.92 | N8: 318084.92 | O8: 318084.92 | P8: Pago/Liquidado | Q8: - | S8: 2228 - Planos locais de Gestão Territorial e Ambiental Quilombolas Fomentar ações que fortaleçam as práticas agroecológicas, o fornecimento energético, o saneamento, a soberania alimentar, a valorização cultural, social, os saberes e fazeres dos quilombolas, povos e comunidades tradicionais de matriz africana, povos de terreiros e ciganos​
B9: 0002 | C9: 2025 | D9: Despesas correntes | G9: DPTMAT | H9: Regiane | L9: 566910.42 | M9: 566910.42 | N9: 566910.42 | O9: 566910.42 | Q9: -
B10: 0003 | C10: 2025 | D10: Despesas correntes | G10: CGPQ | H10: Erlon | L10: 1024746.7 | M10: 1024746.7 | N10: 1024746.7 | O10: 1024746.7 | Q10: -
B11: 0003 | C11: 2025 | D11: Despesas correntes | E11: Projeto de Pesquisa e Desenvolvimento de Relatórios sobre Identificação e Delimitação de Terras de Quilombos no Estado do Rio de Janeiro: reconhecimento territorial em situações de conflitos | F11: 21290.000071/2025-21 | G11: CGPQ | H11: Erlon | I11: TED | K11: UFF (Aditivo) | L11: 296765 | M11: 296764.87 | N11: 274507.5 | O11: 274507.5 | P11: Empenhado | Q11: -
B12: 0003 | C12: 2026 | D12: Despesas correntes | E12: Pesquisas para subsidiar o desenvolvimento de políticas territoriais e ambientais em terras e comunidades quilombolas. | F12: 21290.001092/2026-44 | G12: CGPQ | H12: Erlon | I12: TED | K12: UFF | L12: 1500000 | M12: 1425000 | N12: 1387500 | P12: Empenho Parcial | Q12: agosto | S12: 1 - Oficina de Disseminação da PNGTAQ, Elaboração e Execução da PGTAQ, Curso de Formação 2 - 2228. Planos Locais de Gestão Territorial e Ambiental Quilombola. 4 - Fomentar ações que fortaleçam as práticas agroecológicas, o fornecimento energético, o saneamento, a soberania alimentar, a valorização cultural, social, os saberes e fazeres dos quilombolas, povos e comunidades tradicionais de matriz africana, povos de terreiros e ciganos 5 - Oficinas de capacitação para desenvolvimento de ferramentas de aplicação de tratamento de água, esgoto e efluentes, gestão de energia descentralizada e práticas agroecológicas.
B13: 0003 | C13: 2026 | D13: Despesas correntes | E13: Fortalecimento da Política Nacional de Gestão Territorial e Ambiental Quilombola - Curso de Formação de profissionais para PGTAQ | F13: 21290.000112/2026-60 | G13: CGPQ | H13: Erlon | I13: TED | K13: UNIVASF | L13: 591641 | M13: 591641 | N13: 591641 | O13: 591641 | P13: Empenhado | Q13: junho | S13: 2228. Planos Locais de Gestão Territorial e Ambiental Quilombola. "Elaboração de ações e atividades que visam o fortalecimento das políticas para Povos Ciganos no país (PNPC). Formação para gestores servidores públicos acerca dos direitos dos quilombolas, povos e comunidades tradicionais de matriz africana, povos de terreiro e ciganos nas instituições públicas 323 Fomentar ações que fortaleçam as práticas agroecológicas, o fornecimento energético, o saneamento, a soberania alimentar, a valorização cultural, social, os saberes e fazeres dos quilombolas, povos e comunidades tradicionais de matriz africana, povos de terreiros e ciganos. "
B14: 0001 | D14: Despesas correntes | G14: CGPC | H14: Marciele | I14: TED | L14: 781831 | M14: 781831 | N14: 697495 | O14: 697495 | Q14: junho
B15: 0001 | C15: 2026 | D15: Despesas correntes | E15: Promoção de apoio e de valorização da diversidade étnico-racial das Comunidades Quilombolas e dos Povos Ciganos. | F15: 21290.000858/2026-73 | G15: CGPC | H15: Mar | I15: TED | K15: IFRN | L15: 1000000 | M15: 1000000 | N15: 1000000 | O15: 1000000 | P15: Pago/Liquidado | Q15: -
B16: 0003 | C16: 2026 | D16: Despesas correntes | G16: CGPQ | H16: Erlon | L16: 1890000 | M16: 1890000 | N16: 1890000 | O16: 1890000 | Q16: -
B17: 0001 | C17: 2025 | D17: Despesas correntes | E17: Fortalecimento da Diversidade, Cultura e Território para Quilombolas, Povos e Comunidades Tradicionais de Matriz Africana, Povos de Terreiros e Ciganos | F17: 21290.004335/2025-15 | G17: CGPC | H17: Marciele | I17: TED | K17: UFG | L17: 3195275 | M17: 3195275 | N17: 3195275 | O17: 3195275 | P17: Pago/Liquidado | Q17: - | S17: Entrega: 2076 - Oficinas de capacitação para desenvolvimento de ferramentas de aplicação de tratamento de água, esgoto e efluentes, gestão de energia descentralizada e práticas agroecológicas.
B18: 0002 | C18: 2025 | D18: Despesas correntes | G18: DPTMAT | H18: Regiane | L18: 1083600 | M18: 1083600 | N18: 1083600 | O18: 1083600 | Q18: -
B19: 0003 | C19: 2026 | D19: Despesas correntes | G19: CGPQ | H19: Erlon | L19: 732825 | M19: 732825 | N19: 732825 | O19: 732825 | Q19: -
B20: 0002 | C20: 2025 | D20: Despesas correntes | E20: Apoiar ações estruturantes voltadas à promoção de direitos, sustentabilidade, justiça social e enfrentamento ao racismo religioso, para os Povos e Comunidades Tradicionais de Terreiro e de Matriz Africana. | F20: 21290.000819/2025-95 | G20: DPTMAT | H20: Regiane | I20: TED | K20: FIOCRUZ (repasse + aditivo) | L20: 1981677 | M20: 1981676.8 | N20: 1504625 | O20: 1504625 | P20: Empenhado | Q20: outubro | R20: Processo enviado à DGA para formalização do aditivo | S20: Criar mecanismos de identificação e de enfrentamento à violência e à discriminação contra quilombolas, povos e comunidades tradicionais de matriz africana, povos de terreiros e ciganos
B21: 0002 | C21: 2026 | D21: Investimento | E21: Kit Costura para Povos de Terreiro e Matriz Africana | F21: 21290.000953/2026-77 | G21: DPTMAT | H21: Regiane | I21: TED | K21: IFBA | L21: 778587 | P21: Instrução Processual | Q21: outubro | R21: Tramitado para análise da DGA | S21: Entrega OE 0323- Fomentar ações que fortaleçam as práticas agroecológicas, o fornecimento energético, o saneamento, a soberania alimentar, a valorização cultural, social, os saberes e fazeres dos quilombolas, povos e comunidades tradicionais de matriz africana, povos de terreiros e ciganos.
B22: 0002 | D22: Despesas correntes | L22: 644086
B23: 0002 | C23: 2026 | D23: Despesas correntes | E23: Preservar e difundir o patrimônio material e imaterial e as expressões culturais dos povos e das comunidades tradicionais de terreiro e de matriz africana | F23: 21290.000181/2026-73 | G23: DPTMAT | H23: Regiane | I23: TED | K23: UFMA | L23: 586703 | M23: 586703 | P23: Empenhado | Q23: agosto | R23: A Universidade solicitou que o crédito fosse repassado integralmente na natureza de despesa 33.90.39, para que seja possível realizar o empenho
B24: 0002 | C24: 2026 | D24: Despesas correntes | E24: Impressões de relatórios Abre Caminhos, | F24: 21290.003736/2025-58 | G24: DPTMAT | H24: Regiane | I24: Serviços | K24: MGI | L24: 139331.79 | M24: 139331.79 | N24: 139331.79 | O24: 139331.79 | P24: Pago/Liquidado | Q24: -
B25: 0001 | C25: 2026 | D25: Despesas correntes | E25: Apoiar a execução de ações governamentais que consolidem as políticas públicas previstas, garantindo avanços concretos em direitos, inclusão e acesso a serviços essenciais para os povos ciganos. | F25: 21290.000773/2026-95 | G25: CGPC | H25: Marciele | I25: TED | K25: FIOCRUZ | L25: 1350000 | M25: 1350000 | N25: 810000 | P25: Empenhado | Q25: agosto | R25: aguardando empenho de 540 mil
B26: 0003 | C26: 2026 | D26: Despesas correntes | E26: Implementação do PGTAQ Boa Vista +30 | F26: 14021.020213/2026-61 | G26: CGPQ | H26: Erlon | I26: TED | K26: UFOPA | L26: 500000 | P26: Instrução Processual | Q26: outubro | R26: Processo enviado à DGA para formalização
B27: 0003 | C27: 2025 | D27: Despesas correntes | E27: Acompanhar, monitorar e qualificar as políticas públicas junto às Comunidades Quilombolas no âmbito do Programa Aquilomba Brasil. | F27: 21290.001443/2025-36 | G27: CGPQ | H27: Erlon | I27: TED | K27: FIOCRUZ | L27: 890600 | M27: 889612 | N27: 885012 | O27: 885012 | P27: Empenhado | Q27: -
B28: 0001 | C28: 2026 | D28: Despesas correntes | E28: Impressão Guia do Mapeamento | K28: MGI | L28: 10982.26 | M28: 20903.09 | N28: 20903.09 | O28: 20903.09 | P28: Pago/Liquidado | Q28: -
B29: 0001 | C29: 2026 | D29: Despesas correntes | E29: Implementação da Estratégia de Enfrentamento ao Racismo Ambiental | F29: 21290.001965/2026-19 | G29: CGPC | H29: Marciele | I29: TED | K29: UFF | L29: 200000 | M29: 200000 | N29: 200000 | O29: 200000 | P29: Empenhado | Q29: agosto | R29: Assinado, aguardando repasse de recurso
B30: 0002 | D30: Despesas correntes | G30: DPTMAT | H30: Regiane | L30: 800000 | M30: 800000 | N30: 800000 | O30: 796359.86 | Q30: agosto
B31: 0003 | D31: Despesas correntes | G31: CGPQ | H31: Erlon | L31: 1200000 | M31: 1000000 | N31: 1000000 | O31: 1000000 | Q31: agosto
B32: 0001 | C32: 2026 | D32: Despesas correntes | E32: Promoção de apoio e de valorização da diversidade étnico-racial das Comunidades Quilombolas e dos Povos Ciganos. | F32: 21290.000858/2026-73 | G32: CGPC | H32: Marciele | I32: TED | K32: IFRN (aditivo) | L32: 92568 | P32: Instrução Processual | Q32: outubro | R32: O processo necessitará de ajuste, tendo em vista que a parceria estabelecida entre o MIR e MDHC foi encerrada em 2 de agosto, não sendo possível, dessa forma, efetivar o repasse ao IFRN do valor de R$ 243.000,00, destinado ao apoio à realização do 4º EGBE – Encontro Nacional das Culturas dos Povos de Matriz Africana: O Poder Ancestral, realizado no período de 4 a 7 de junho. Ressalta-se que o valor total do aditivo corresponde a R$ 772.868,00. Desse montante, R$ 243.000,00 referem-se aos recursos originalmente recebidos do MDHC, destinados especificamente ao apoio à realização do 4º EGBE e 64.084, 00 é referente ao rateio de custos entre o MIR e o MMulheres para atendimento ao encontro de mulheres. "
B33: 0002 | C33: 2026 | D33: Despesas correntes | G33: DPTMAT | H33: Regiane | L33: 291000
B34: 0003 | C34: 2026 | D34: Despesas correntes | G34: CGPQ | H34: Erlon | L34: 78216
B35: 0003 | C35: 2026 | D35: Despesas correntes | E35: Copa Quilombola | F35: 21290.002505/2026-16 | G35: CGPQ | H35: Erlon | I35: TED | K35: IFRN | L35: 3893035 | P35: Instrução Processual | Q35: outubro | R35: Processo na DGA aguardando formalização
B36: 0002 | C36: 2026 | D36: Despesas correntes | E36: desenvolvimento de ações voltadas à mobilização e à organização de eventos relacionados à cultura alimentar dos povos de matriz africana e das comunidades tradicionais de Fundo de Pasto, bem como à promoção de ações de concertação para estruturação de rotas de comercialização baseadas na economia solidária da cadeia produtiva da caprinocultura, com ênfase no transporte da carga viva dos animais. | F36: 21290.001920/2026-44 | G36: DPTMAT | H36: Regiane | I36: TED | K36: EMBRAPA | L36: 87200 | P36: Instrução Processual | Q36: outubro | R36: Foi solicitado pela DGA ajustes no PT (previsão de retorno até próxima semana 13 a 16/10)
B37: 0002 | C37: 2026 | D37: Despesas correntes | E37: ADPF 973 | F37: 21290.002331/2025-01 | G37: DPTMAT | H37: Regiane | I37: TED | K37: UFMA | L37: 300000 | M37: 300000 | P37: Empenhado | Q37: outubro | R37: Parceria sendo tratado no âmbito da SENAPIR
B38: 0003 | C38: 2026 | D38: Despesas correntes | G38: CGPQ | H38: Erlon | L38: 300000 | M38: 300000 | Q38: outubro
B39: 0003 | C39: 2026 | D39: Despesas correntes | E39: Seminário quilombola | G39: CGPQ | H39: Erlon | I39: Evento | K39: Ata de eventos | L39: 400000 | P39: planejamento | Q39: outubro
G40: TOTAL | L40: =SUM(L3:L39) -> 30832395 | M40: =SUM(M3:M36) -> 21994940 | N40: =SUM(N3:N38) -> 19664232 | O40: =SUM(O3:O38) -> 17463092
G41: Dotação livre para empenho | L41: ='Consolidado 2026'!H32 -> 31127889
G42: (%) PLE/PROGRAMADO | L42: =L40/L41 -> 0.9905071

Sheet 21FF - SEPAR
A1: ACOMPANHAMENTO EXECUÇÃO FINALÍSTICAS - 2025
A2: UNIDADE | B2: PO | C2: ANO DE FORMALIZAÇÃO | D2: GRUPO DE DESPESA | E2: INICIATIVAS | F2: SEI | G2: DIRETORIA | H2: RESPONSÁVEL PELA FORMALIZAÇÃO | I2: INSTRUMENTO | J2: SIAFI | K2: PARCEIRO | L2: PROGRAMADO 2026 | M2: EMPENHADO 2026 | N2: LIQUIDADO 2026 | O2: PAGO 2026 | P2: STATUS | Q2: PREVISÃO DE DESCENTRALIZAÇÃO | R2: OBSERVAÇÃO (PENDÊNCIAS) | S2: ENTREGA PPA
A3: SEPAR | B3: 0000 | C3: 2026 | D3: Despesas correntes | E3: Diárias e Passagens | G3: SEPAR | I3: Contrato | L3: 480000 | M3: 480000 | N3: 250016.27 | O3: 250016.27 | P3: Empenhado
B4: 0001 | C4: 2026 | D4: Despesas correntes | E4: Promoção da igualdade racial e combate ao racismo por meio do desenvolvimento de iniciativas de saúde e educação. | F4: 21290.002730/2026-44 | G4: GAB.SEPAR | H4: Marcelo Raul | I4: TED | K4: UFF | L4: 3102827.5 | P4: Instrução Processual | Q4: -
B5: 0001 | C5: 2026 | D5: Despesas correntes | E5: Desenvolver e apoiar ações integradas de formação, articulação territorial, reconhecimento de iniciativas e produção de subsídios técnicos voltadas à promoção dos direitos humanos, do bem viver, do acesso ao mundo do trabalho, do direito à saúde e de agentes territoriais, com foco no fortalecimento das juventudes negras em seus território | F5: 21290.001624/2026-43 | G5: DCR | H5: Florence | I5: TED | K5: FIOCRUZ | L5: 1270000 | M5: 1270000 | P5: Empenhado | Q5: junho | R5: Apostilar alteração de cronograma de desembolso
B6: 0002 | C6: 2026 | D6: Despesas correntes | E6: Promoção de Justiça Racial e Garantia de Direitos às Pessoas Privadas de Liberdade - ADPF 347 | F6: 21290.001638/2026-67 | G6: DAG | H6: Lívia | L6: 1521150 | M6: 1521150 | N6: 1521150 | O6: 1521150 | P6: Pago/Liquidado | Q6: julho
G7: TOTAL | L7: =SUM(L3:L6) -> 6373977.5 | M7: =SUM(M3:M6) -> 3271150 | N7: =SUM(N3:N6) -> 1771166.3 | O7: =SUM(O3:O6) -> 1771166.3
G8: Dotação livre para empenho | L8: ='Consolidado 2026'!H17 -> 6383978
G9: (%) PLE/PROGRAMADO | L9: =L7/L8 -> 0.9984335

Sheet Planilha8

Sheet Restos a Pagar
A1: Secretaria de Orçamento Federal
A2: SIOP Gerencial - Execucao Orçamentária - Execução e RAP
A3: Data de geração deste relatório: 25/07/2024 14:46:22
A5: Unidade | B5: Ação | C5: PO | D5: GND | E5: RAP Pago | F5: RAP A Pagar | G5: Observação
A6: GAB/SE | B6: 2000 | C6: "0000" | D6: 3
C7: "000B" | D7: 3
C8: "000C" | D8: 3
B9: 210H | C9: "0000" | D9: 3
A10: TOTAL GAB/SE | E10: =SUM(E6:E9) -> 0 | F10: =SUM(F6:F9) -> 0
A11: SEPAR | B11: 21AR | C11: "0001" | D11: 3
A12: TOTAL SEPAR | E12: =E11 -> 0 | F12: =F11 -> 0
A13: SQPT | B13: 21AR | C13: "0002" | D13: 3
D14: 4
C15: "0003" | D15: 3
D16: 5
A17: TOTAL SQPT | E17: =SUM(E13:E16) -> 0 | F17: =SUM(F13:F16) -> 0
A18: SENAPIR | B18: 21AR | C18: "000J" | D18: 3
D19: 4
A20: TOTAL SENAPIR | E20: =SUM(E18:E19) -> 0 | F20: =SUM(F18:F19) -> 0
A21: CNPIR | B21: 21AT | C21: "0007" | D21: 3
A22: TOTAL CNPIR | E22: =E21 -> 0 | F22: =F21 -> 0
A24: TOTAL | E24: =E10+E12+E17+E20+E22 -> 0 | F24: =F10+F12+F17+F20+F22 -> 0
A27: Emendas | B27: 21AR | C27: "0000" | D27: 3
D28: 4
A29: TOTAL Emendas | E29: =SUM(E27:E28) -> 0 | F29: =SUM(F27:F28) -> 0

Sheet EMENDAS PARLAMENTARES
A1: EMENDAS PARLAMENTARES INDIVIDUAIS RP6 - 2024
A2: QTD | B2: Nome Parlamentar | C2: UF | D2: Município | E2: Emenda | F2: Ação | G2: Ptres | H2: Programa | I2: Processo | J2: Numero Interno | K2: Nº da Proposta | L2: Nº do Instumento | M2: Modalidade | N2: Beneficiário | O2: Objeto | P2: CNPJ | Q2: GND | S2: Total | T2: Área Técnica | U2: Técnico | V2: Parecer Técnico | W2: Formulário / Compromisso | X2: Empenho | Y2: Data da liberação do recurso | Z2: Gestor da Parceria | AA2: Contato | AB2: Situação
Q3: Custeio (3) | R3: Investimento (4)
A4: 1
A5: 2
A6: 3
A7: 4
A8: 5
A9: 6
A10: TOTAL | Q10: =SUM(Q4:Q9) -> 0 | R10: =SUM(R6:R9) -> 0 | S10: =SUM(S4:S9) -> 0

Sheet DIÁRIAS E PASSAGENS - SCDP
E2: Fonte: SCDP 03/10/ 2024
B3: AÇÃO (a) | C3: NOTA DE EMPENHO (b) | D3: VALOR EMPENHADO (c) | E3: VALOR EXECUTADO (d) | F3: DISPONÍVEL (e) = (c) - (d) | G3: (%) (f) = (d) / (c)
A5: TOTAL GERAL | D5: =SUBTOTAL(109,D6:D74) -> 8342952.2 | E5: =SUBTOTAL(109,E6:E74) -> 4912144.6 | F5: =SUBTOTAL(109,F6:F74) -> 3430807.5 | G5: =E5/D5 -> 0.58877776
A7: SECRETARIA EXECUTIVA | D7: =SUBTOTAL(109,D8:D23) -> 2420800 | E7: =SUBTOTAL(109,E8:E23) -> 1506109.2 | F7: =SUBTOTAL(109,F8:F23) -> 914690.79 | G7: =E7/D7 -> 0.62215351 | Z7: % Passages e diarias em relação à dotação RP2
A8: Subtotal - Dárias no país | D8: =SUBTOTAL(109,D9) -> 337000 | E8: =SUBTOTAL(109,E9) -> 165807.82 | F8: =SUBTOTAL(109,F9) -> 171192.18 | G8: =E8/D8 -> 0.49201134 | Z8: Passagens e Diarias | AA8: =E7 -> 1506109.2 | AB8: =AA8/AA9 -> 0.01132687
A9: 33901414 - Diárias no País | B9: 2000 | C9: 8100082024NE000001 | D9: 337000 | E9: =D9-F9 -> 165807.82 | F9: 171192.18 | G9: =E9/D9 -> 0.49201134 | Z9: Dotação | AA9: 132967819 | AB9: =100%-AB8 -> 0.98867313
A10: Subtotal - Diárias no Exterior | D10: =SUBTOTAL(109,D11) -> 363800 | E10: =SUBTOTAL(109,E11) -> 186391.54 | F10: =SUBTOTAL(109,F11) -> 177408.46 | G10: =E10/D10 -> 0.51234618
A11: 33901416 - Diárias no Exterior | B11: 2000 | C11: 8100082024NE000016 | D11: 363800 | E11: =D11-F11 -> 186391.54 | F11: 177408.46 | G11: =E11/D11 -> 0.51234618 | Z11: % Passages e diarias em relação à dotação RP2
A12: Subtotal - Passagens no país | D12: =SUBTOTAL(109,D13:D14) -> 890000 | E12: =SUBTOTAL(109,E13:E14) -> 519062.57 | F12: =SUBTOTAL(109,F13:F14) -> 370937.43 | G12: =E12/D12 -> 0.58321637 | Z12: Passagens e Diarias | AA12: =E7 -> 1506109.2 | AB12: =AA12/AA13 -> 0.62215351
A13: 33903301 - Passagens para o País | B13: 2000 | C13: 8100052024NE000019 | D13: 270000 | E13: =D13-F13 -> 171419.71 | F13: 98580.29 | G13: =E13/D13 -> 0.63488781 | Z13: Empenho | AA13: =D7 -> 2420800 | AB13: =100%-AB12 -> 0.37784649
B14: 2000 | C14: 2010572024NE000157 | D14: 620000 | E14: =D14-F14 -> 347642.86 | F14: 272357.14 | G14: =E14/D14 -> 0.56071429
A15: Subtotal - Passagens para o Exterior | D15: =SUBTOTAL(109,D16) -> 575000 | E15: =SUBTOTAL(109,E16) -> 569510.42 | F15: =SUBTOTAL(109,F16) -> 5489.58 | G15: =E15/D15 -> 0.9904529
A16: 33903302 - Passagens para o Exterior | B16: 2000 | C16: 8100052024NE000141 | D16: 575000 | E16: =D16-F16 -> 569510.42 | F16: 5489.58 | G16: =E16/D16 -> 0.9904529
A17: Subtotal - Diarias Colaboradores Eventuais | D17: =SUBTOTAL(109,D18) -> 130000 | E17: =SUBTOTAL(109,E18) -> 52970.81 | F17: =SUBTOTAL(109,F18:F19) -> 177029.19 | G17: =E17/D17 -> 0.40746777
A18: 33903601 - Diárias a Colaboradores Eventuais no pais | B18: 2000 | C18: 8100082024NE000002 | D18: 130000 | E18: =D18-F18 -> 52970.81 | F18: 77029.19 | G18: =E18/D18 -> 0.40746777
A19: 33903602 - Diárias a Colaboradores Eventuais no Exterior | B19: 2000 | C19: 8100082024NE000084 | D19: 100000 | E19: =D19-F19 -> 0 | F19: 100000 | G19: =E19/D19 -> 0
A20: Subtotal - Indenizações e restituições | D20: =SUBTOTAL(109,D21) -> 5000 | E20: =SUBTOTAL(109,E21) -> 1338.58 | F20: =SUBTOTAL(109,F21) -> 3661.42 | G20: =E20/D20 -> 0.267716
A21: 339093 - Indenizações e Restituições | B21: 2000 | C21: 8100082024NE000010 | D21: 5000 | E21: =D21-F21 -> 1338.58 | F21: 3661.42 | G21: =E21/D21 -> 0.267716
A22: Subtotal - Seguro Viagem | D22: =SUBTOTAL(109,D23) -> 20000 | E22: =SUBTOTAL(109,E23) -> 11027.47 | F22: =SUBTOTAL(109,F23) -> 8972.53 | G22: =E22/D22 -> 0.5513735
A23: 339039 - Seguro Viagem | B23: 2000 | C23: 8100052024NE000143 | D23: 20000 | E23: =D23-F23 -> 11027.47 | F23: 8972.53 | G23: =E23/D23 -> 0.5513735
A24: SENAPIR | D24: =SUBTOTAL(109,D25:D35) -> 1097065 | E24: =SUBTOTAL(109,E25:E35) -> 592725.56 | F24: =SUBTOTAL(109,F25:F35) -> 504339.44 | G24: =E24/D24 -> 0.54028299 | Z24: % Passages e diarias em relação à dotação RP2
A25: Subtotal - Dárias no país | D25: =SUBTOTAL(109,D26) -> 202065 | E25: =SUBTOTAL(109,E26) -> 96908.4 | F25: =SUBTOTAL(109,F26) -> 105156.6 | G25: =E25/D25 -> 0.47959023 | Z25: Passagens e Diarias | AA25: =E24 -> 592725.56 | AB25: =AA25/AA26 -> 0.0044576617
A26: 33901414 - Diárias no País | B26: 21FC | C26: 8100082024NE000007 | D26: 202065 | E26: =D26-F26 -> 96908.4 | F26: 105156.6 | G26: =E26/D26 -> 0.47959023 | Z26: Dotação | AA26: 132967819 | AB26: =100%-AB25 -> 0.99554234
A27: Subtotal - Diárias no Exterior | D27: =SUBTOTAL(109,D28) -> 165000 | E27: =SUBTOTAL(109,E28) -> 62091.29 | F27: =SUBTOTAL(109,F28) -> 102908.71 | G27: =E27/D27 -> 0.37631085
A28: 33901416 - Diárias no Exterior | B28: 21FC | C28: 8100082024NE000017 | D28: 165000 | E28: =D28-F28 -> 62091.29 | F28: 102908.71 | G28: =E28/D28 -> 0.37631085 | Z28: % Passages e diarias em relação à dotação RP2
A29: Subtotal - Passagens no país | D29: =SUBTOTAL(109,D30:D31) -> 420000 | E29: =SUBTOTAL(109,E30:E31) -> 317526.94 | F29: =SUBTOTAL(109,F30:F31) -> 102473.06 | G29: =E29/D29 -> 0.75601652 | Z29: Passagens e Diarias | AA29: =E24 -> 592725.56 | AB29: =AA29/AA30 -> 0.54028299
A30: 33903301 - Passagens para o País | B30: 21FC | C30: 8100052024NE000035 | D30: 158000 | E30: =D30-F30 -> 149248.88 | F30: 8751.12 | G30: =E30/D30 -> 0.94461316 | Z30: Empenho | AA30: =D24 -> 1097065 | AB30: =100%-AB29 -> 0.45971701
B31: 21FC | C31: 2010572024NE000156 | D31: 262000 | E31: =D31-F31 -> 168278.06 | F31: 93721.94 | G31: =E31/D31 -> 0.64228267
A32: Subtotal - Passagens para o Exterior | D32: =SUBTOTAL(109,D33) -> 195000 | E32: =SUBTOTAL(109,E33) -> 83888.93 | F32: =SUBTOTAL(109,F33) -> 111111.07 | G32: =E32/D32 -> 0.43019964
A33: 33903302 - Passagens para o Exterior | B33: 21FC | C33: 8100052024NE000140 | D33: 195000 | E33: =D33-F33 -> 83888.93 | F33: 111111.07 | G33: =E33/D33 -> 0.43019964
A34: Subtotal - Diarias Colaboradores Eventuais | D34: =SUBTOTAL(109,D35) -> 115000 | E34: =SUBTOTAL(109,E35) -> 32310 | F34: =SUBTOTAL(109,F35) -> 82690 | G34: =E34/D34 -> 0.28095652
A35: 33903602 - Diárias a Colaboradores Eventuais no pais | B35: 21FC | C35: 8100082024NE000008 | D35: 115000 | E35: =D35-F35 -> 32310 | F35: 82690 | G35: =E35/D35 -> 0.28095652
A36: SEPAR | D36: =SUBTOTAL(109,D37:D58) -> 2306737 | E36: =SUBTOTAL(109,E37:E58) -> 1408286.2 | F36: =SUBTOTAL(109,F37:F58) -> 898450.78 | G36: =E36/D36 -> 0.61051009 | Z36: % Passages e diarias em relação à dotação RP2
A37: Subtotal - Dárias no país | D37: =SUBTOTAL(109,D38:D40) -> 190000 | E37: =SUBTOTAL(109,E38:E40) -> 74206.02 | F37: =SUBTOTAL(109,F38:F40) -> 115793.98 | G37: =E37/D37 -> 0.390558 | Z37: Passagens e Diarias | AA37: =E36 -> 1408286.2 | AB37: =AA37/AA38 -> 0.010591181
A38: 33901414 - Diárias no País | B38: 21FF | C38: 8100082024NE000011 | D38: 70000 | E38: =D38-F38 -> 12424.33 | F38: 57575.67 | G38: =E38/D38 -> 0.17749043 | Z38: Dotação | AA38: 132967819 | AB38: =100%-AB37 -> 0.98940882
B39: 21FB | C39: 8100082024NE000012 | D39: 50000 | E39: =D39-F39 -> 28701.65 | F39: 21298.35 | G39: =E39/D39 -> 0.574033
B40: 21FD | C40: 8100082024NE000014 | D40: 70000 | E40: =D40-F40 -> 33080.04 | F40: 36919.96 | G40: =E40/D40 -> 0.472572 | Z40: % Passages e diarias em relação à dotação RP2
A41: Subtotal - Diárias no Exterior | D41: =SUBTOTAL(109,D42:D44) -> 436737 | E41: =SUBTOTAL(109,E42:E44) -> 291980.21 | F41: =SUBTOTAL(109,F42:F44) -> 144756.79 | G41: =E41/D41 -> 0.66854929 | Z41: Passagens e Diarias | AA41: =E36 -> 1408286.2 | AB41: =AA41/AA42 -> 0.61051009
A42: 33901416 - Diárias no Exterior | B42: 21FF | C42: 8100082024NE000020 | D42: 70000 | E42: =D42-F42 -> 43495.46 | F42: 26504.54 | G42: =E42/D42 -> 0.62136371 | Z42: Empenho | AA42: =D36 -> 2306737 | AB42: =100%-AB41 -> 0.38948991
B43: 21FB | C43: 8100082024NE000018 | D43: 50000 | E43: =D43-F43 -> 42325.95 | F43: 7674.05 | G43: =E43/D43 -> 0.846519
B44: 21FD | C44: 8100082024NE000019 | D44: 316737 | E44: =D44-F44 -> 206158.8 | F44: 110578.2 | G44: =E44/D44 -> 0.65088322
A45: Subtotal - Passagens no país | D45: =SUBTOTAL(109,D46:D50) -> 1030000 | E45: =SUBTOTAL(109,E46:E50) -> 529368.66 | F45: =SUBTOTAL(109,F46:F50) -> 500631.34 | G45: =E45/D45 -> 0.51395016
A46: 33903301 - Passagens para o País | B46: 21FF | C46: 8100052024NE000135 | D46: 100000 | E46: =D46-F46 -> 0 | F46: 100000 | G46: =E46/D46 -> 0
B47: 21FD | C47: 8100052024NE000033 | D47: 100000 | E47: =D47-F47 -> 24666.4 | F47: 75333.6 | G47: =E47/D47 -> 0.246664
B48: 21FF | C48: 2010572024NE000231 | D48: 440000 | E48: =D48-F48 -> 219260.43 | F48: 220739.57 | G48: =E48/D48 -> 0.49831916
B49: 21FB | C49: 2010572024NE000155 | D49: 130000 | E49: =D49-F49 -> 100225.48 | F49: 29774.52 | G49: =E49/D49 -> 0.77096523
B50: 21FD | C50: 2010572024NE000232 | D50: 260000 | E50: =D50-F50 -> 185216.35 | F50: 74783.65 | G50: =E50/D50 -> 0.71237058
A51: Subtotal - Passagens para o Exterior | D51: =SUBTOTAL(109,D52:D54) -> 390000 | E51: =SUBTOTAL(109,E52:E54) -> 340158.83 | F51: =SUBTOTAL(109,F52:F54) -> 49841.17 | G51: =E51/D51 -> 0.87220213
A52: 33903302 - Passagens para o Exterior | B52: 21FF | C52: 8100052024NE000138 | D52: 70000 | E52: =D52-F52 -> 58441.69 | F52: 11558.31 | G52: =E52/D52 -> 0.83488129
B53: 21FB | C53: 8100052024NE000137 | D53: 50000 | E53: =D53-F53 -> 22496.42 | F53: 27503.58 | G53: =E53/D53 -> 0.4499284
B54: 21FD | C54: 8100052024NE000136 | D54: 270000 | E54: =D54-F54 -> 259220.72 | F54: 10779.28 | G54: =E54/D54 -> 0.96007674
A55: Subtotal - Diarias Colaboradores Eventuais | D55: =SUBTOTAL(109,D56:D58) -> 260000 | E55: =SUBTOTAL(109,E56:E58) -> 172572.5 | F55: =SUBTOTAL(109,F56:F58) -> 87427.5 | G55: =E55/D55 -> 0.66374038
A56: 33903602 - Diárias a Colaboradores Eventuais no pais | B56: 21FB | C56: 8100082024NE000013 | D56: 30000 | E56: =D56-F56 -> 12290 | F56: 17710 | G56: =E56/D56 -> 0.40966667
B57: 21FF | C57: 8100082024NE000004 | D57: 180000 | E57: =D57-F57 -> 110690 | F57: 69310 | G57: =E57/D57 -> 0.61494444
B58: 21FD | C58: 8100082024NE000015 | D58: 50000 | E58: =D58-F58 -> 49592.5 | F58: 407.5 | G58: =E58/D58 -> 0.99185
A59: SQPT | D59: =SUBTOTAL(109,D60:D71) -> 1781350.1 | E59: =SUBTOTAL(109,E60:E71) -> 907148.57 | F59: =SUBTOTAL(109,F60:F71) -> 874201.58 | G59: =E59/D59 -> 0.50924776 | Z59: % Passages e diarias em relação à dotação RP2
A60: Subtotal - Dárias no país | D60: =SUBTOTAL(109,D61) -> 335382.5 | E60: =SUBTOTAL(109,E61) -> 172332.23 | F60: =SUBTOTAL(109,F61) -> 163050.27 | G60: =E60/D60 -> 0.51383787 | Z60: Passagens e Diarias | AA60: =E59 -> 907148.57 | AB60: =AA60/AA61 -> 0.0068223167
A61: 33901414 - Diárias no País | B61: 21FE | C61: 8100082024NE000005 | D61: 335382.5 | E61: =D61-F61 -> 172332.23 | F61: 163050.27 | G61: =E61/D61 -> 0.51383787 | Z61: Dotação | AA61: 132967819 | AB61: =100%-AB60 -> 0.99317768
A62: Subtotal - Diárias no Exterior | D62: =SUBTOTAL(109,D63:D64) -> 287891.65 | E62: =SUBTOTAL(109,E63:E64) -> 135901.46 | F62: =SUBTOTAL(109,F63:F64) -> 151990.19 | G62: =E62/D62 -> 0.47205766
A63: 33901416 - Diárias no Exterior | B63: 21FE | C63: 8100082024NE000049 | D63: 123681.15 | E63: =D63-F63 -> 59379.97 | F63: 64301.18 | G63: =E63/D63 -> 0.48010525 | Z63: % Passages e diarias em relação à dotação RP2
B64: 21FE | C64: 8100082024NE000050 | D64: 164210.5 | E64: =D64-F64 -> 76521.49 | F64: 87689.01 | G64: =E64/D64 -> 0.46599633 | Z64: Passagens e Diarias | AA64: =E59 -> 907148.57 | AB64: =AA64/AA65 -> 0.50924776
A65: Subtotal - Passagens no país | D65: =SUBTOTAL(109,D66:D67) -> 651000 | E65: =SUBTOTAL(109,E66:E67) -> 444610.5 | F65: =SUBTOTAL(109,F66:F67) -> 206389.5 | G65: =E65/D65 -> 0.68296544 | Z65: Empenho | AA65: =D59 -> 1781350.1 | AB65: =100%-AB64 -> 0.49075224
A66: 33903301 - Passagens para o País | B66: 21FE | C66: 8100052024NE000034 | D66: 224000 | E66: =D66-F66 -> 208271.97 | F66: 15728.03 | G66: =E66/D66 -> 0.92978558
B67: 21FE | C67: 2010572024NE000154 | D67: 427000 | E67: =D67-F67 -> 236338.53 | F67: 190661.47 | G67: =E67/D67 -> 0.55348602
A68: Subtotal - Passagens para o Exterior | D68: =SUBTOTAL(109,D69) -> 322426 | E68: =SUBTOTAL(109,E69) -> 89979.38 | F68: =SUBTOTAL(109,F69) -> 232446.62 | G68: =E68/D68 -> 0.27906986
A69: 33903302 - Passagens para o Exterior | B69: 21FE | C69: 8100052024NE000286 | D69: 322426 | E69: =D69-F69 -> 89979.38 | F69: 232446.62 | G69: =E69/D69 -> 0.27906986
A70: Subtotal - Diarias Colaboradores Eventuais | D70: =SUBTOTAL(109,D71) -> 184650 | E70: =SUBTOTAL(109,E71) -> 64325 | F70: =SUBTOTAL(109,F71) -> 120325 | G70: =E70/D70 -> 0.34836177
A71: 33903602 - Diárias a Colaboradores Eventuais no pais | B71: 21FE | C71: 8100082024NE000006 | D71: 184650 | E71: =D71-F71 -> 64325 | F71: 120325 | G71: =E71/D71 -> 0.34836177
A72: CNPIR | D72: =SUBTOTAL(109,D73:D74) -> 737000 | E72: =SUBTOTAL(109,E73:E74) -> 497875.08 | F72: =SUBTOTAL(109,F73:F74) -> 239124.92 | G72: =E72/D72 -> 0.67554285 | Z72: % Passages e diarias em relação à dotação RP2
A73: 33903301 - Passagens para o País | B73: 21FG | C73: 8100052024NE000036 | D73: 415000 | E73: =D73-F73 -> 319520.08 | F73: 95479.92 | G73: =E73/D73 -> 0.7699279 | Z73: Passagens e Diarias | AA73: =E72 -> 497875.08 | AB73: =AA73/AA74 -> 0.0037443276
A74: 33903602 - Diárias a Colaboradores Eventuais no pais | B74: 21FG | C74: 8100082024NE000009 | D74: 322000 | E74: =D74-F74 -> 178355 | F74: 143645 | G74: =E74/D74 -> 0.55389752 | Z74: Dotação | AA74: 132967819 | AB74: =100%-AB73 -> 0.99625567
Z76: % Passages e diarias em relação à dotação RP2
Z77: Passagens e Diarias | AA77: =E72 -> 497875.08 | AB77: =AA77/AA78 -> 0.67554285
Z78: Empenho | AA78: =D72 -> 737000 | AB78: =100%-AB77 -> 0.32445715

Sheet _56F9DC9755BA473782653E2940F9
A1: eLGl-_E6IESWa79RY-ax2iuoN7rWI-dLhfbHv3sOlYFUOTIzSkhYUlVZMjJTNTM3V1kyWjAxMFJPMCQlQCN0PWcu
A2: Form2
A3: {f62d1b90-5b8b-47b9-9246-cc08b8118503}

Sheet 21FG - CNPIR
A1: ACOMPANHAMENTO EXECUÇÃO FINALÍSTICAS - 2024
A2: UNIDADE | B2: PO | C2: ANO DE FORMALIZAÇÃO | D2: GRUPO DE DESPESA | E2: INICIATIVAS | F2: SEI | G2: DIRETORIA | H2: RESPONSÁVEL PELA FORMALIZAÇÃO | I2: INSTRUMENTO | J2: SIAFI | K2: PARCEIRO | L2: PROGRAMADO 2026 | M2: EMPENHADO 2026 | N2: LIQUIDADO 2026 | O2: PAGO 2026 | P2: STATUS | Q2: PREVISÃO DE DESCENTRALIZAÇÃO | R2: OBSERVAÇÃO (PENDÊNCIAS) | S2: ENTREGA PPA
A3: CNPIR | B3: 0000 | C3: 2026 | D3: Despesas correntes | E3: DIARIAS E PASSAGENS /DESPESAS ADMINISTRATIVAS | L3: 1853476 | M3: 1389048.9 | N3: 1173132.5 | O3: 1173132.5 | P3: Empenhado | Q3: -
Q4: -
Q5: -
Q6: -
Q7: -
Q8: -
Q9: -
Q10: -
Q11: -
Q12: -
Q13: -
Q14: -
Q15: -
Q16: -
G17: TOTAL | L17: =SUM(L3:L16) -> 1853476 | M17: =SUM(M3:M16) -> 1389048.9 | N17: =SUM(N3:N16) -> 1173132.5 | O17: =SUM(O3:O16) -> 1173132.5
G18: Dotação livre para empenho | L18: ='Consolidado 2026'!H41 -> 2253476
G19: (%) PLE/PROGRAMADO | L19: =L17/L18 -> 0.82249645

Sheet 21HN - SEPAR
A1: ACOMPANHAMENTO EXECUÇÃO FINALÍSTICAS - 2024
A2: UNIDADE | B2: PO | C2: ANO DE FORMALIZAÇÃO | D2: GRUPO DE DESPESA | E2: INICIATIVAS | F2: SEI | G2: DIRETORIA | H2: RESPONSÁVEL PELA FORMALIZAÇÃO | I2: INSTRUMENTO | J2: SIAFI | K2: PARCEIRO | L2: PROGRAMADO 2026 | M2: EMPENHADO 2026 | N2: LIQUIDADO 2026 | O2: PAGO 2026 | P2: STATUS | Q2: PREVISÃO DE DESCENTRALIZAÇÃO | R2: OBSERVAÇÃO (PENDÊNCIAS) | S2: ENTREGA PPA
A3: SEPAR | B3: 0000 | C3: 2026 | D3: Despesas correntes | E3: Diarias e Passagens | G3: SEPAR | I3: Contrato | L3: 560000 | M3: 560000 | N3: 304630.96 | O3: 304630.96 | Q3: -
B4: 0001 | C4: 2024 | D4: Despesas correntes | E4: Programa Institucional de Iniciação Científica nas Ações Afirmativas (PIBIC-Af) - CICLO 2024-2027 | F4: 21290.201128/2024-26 | G4: DPA | I4: TED | J4: 956865 | K4: CNPq | L4: 2520000 | P4: Instrução Processual | Q4: -
B5: 0002 | C5: 2023 | D5: Despesas correntes | E5: Implementação do “Observatório AmeÁfrica: diálogos de políticas e experiências Sul-Sul | F5: 21290.204058/2023-87 | G5: DCR | H5: Kátia Regis | I5: TED | J5: 949551 | K5: UFMA | L5: 490076.6 | M5: 490076.6 | N5: 490076.6 | O5: 490076.6 | P5: Pago/Liquidado | Q5: -
B6: 0001 | C6: 2025 | D6: Despesas correntes | E6: Programa Sankofa | F6: 21290.003287/2025-48 | G6: GAB/DPA | H6: Marcelo Raul | I6: TED | K6: UFRB | L6: 500000 | M6: 500000 | P6: Empenhado | Q6: - | S6: 087F – Implementação da Política Nacional de Combate ao Racismo Ambiental 0880 – Execução do TED do Fórum Nacional de Combate ao Racismo Ambiental
B7: 0002 | C7: 2025 | D7: Despesas correntes | E7: ADITIVO Promoção da Cidadania Antirracista, da Reparação Histórica e do Desenvolvimento Socioeconômico da população negra. | F7: 21290.003389/2025-63 | G7: GAB | H7: Marcelo Raul | I7: TED | K7: IFG (Aditivo) | L7: 7562874.6 | M7: 7562874.6 | N7: 7562874.6 | O7: 7562874.6 | P7: Pago/Liquidado | Q7: - | S7: 08C2 – Produção de dados e diagnósticos territoriais com recorte racial 087F – Subsídios técnicos para ações de enfrentamento ao racismo ambiental 0879 – Produção de evidências para enfrentamento ao racismo institucional
B8: 0001 | C8: 2025 | D8: Despesas correntes | E8: Projeto Comunica Jovem - Estratégia de Comunicação Voluntária no combate ao Racismo (Paracambi / Japeri) | F8: 21290.003046/2025-07 | G8: GAB | H8: Marcelo Raul | I8: TED | K8: IFRJ | L8: 350000 | M8: 348854.56 | N8: 339800 | O8: 144899.4 | P8: Empenho Parcial | Q8: - | S8: Ação de comunicação comunitária e educação antirracista, voltada ao enfrentamento do racismo em territórios vulnerabilizados, por meio da mobilização voluntária de jovens e da produção de conteúdos educativos, com impacto transversal nas políticas de promoção da igualdade racial.
B9: 0002 | C9: 2026 | D9: Despesas correntes | E9: HQ - hip-hop - distribuição no Caminhos Amefricanos | F9: 21290.003210/2025-78 | G9: DCR | H9: KÁTIA | I9: Contrato | L9: 70000 | P9: Empenhado | Q9: - | S9: Ação de educação antirracista e difusão cultural, com valorização das africanidades e fortalecimento da cooperação Sul-Sul, no âmbito do Programa 5804.
B10: 0001 | C10: 2026 | D10: Despesas correntes | E10: Masculinidades em Debate - Papo de Baile do Maisum | F10: 21290.001435/2026-71 | G10: DPA | H10: Vitor | I10: TED | L10: 170887.5 | P10: Instrução Processual
B11: 0001 | C11: 2026 | D11: Despesas correntes | E11: Avaliação e monitoramento dos impactos da lei nº 15.142/2025 (lei de cotas raciais nos concursos públicos) | F11: 21290.001483/2026-69 | G11: DPA | H11: Vitor | I11: TED | K11: Univasf | L11: 800320 | P11: Instrução Processual | Q11: -
B12: 0001 | C12: 2026 | D12: Despesas correntes | E12: Apoio à OBERERI - Olimpíadas Brasileiras de Relações Étnico-Raciai | F12: 21290.001071/2026-29 | G12: DPA | H12: Vitor | I12: TED | K12: CNPq | L12: 200000 | P12: Planejamento | Q12: -
B13: 0001 | C13: 2026 | D13: Despesas correntes | E13: Apoio ao XIV Congresso Nacional de Pesquisadores(as) Negros(as) | F13: 21290.001227/2026-71 | G13: DPA | H13: Vitor | I13: TED | K13: UnB | L13: 240000 | M13: 240000 | N13: 240000 | O13: 240000 | P13: Pago/Liquidado | Q13: -
B14: 0002 | C14: 2026 | D14: Despesas correntes | E14: 03 intercâmbios institucionais (Panamá, México e Angola) / Comissões de Heteroidentificação / Edição Moçambique sem custear intercambistas (CAPES) | F14: 21290.002404/2026-37 | G14: DCR | H14: Katia | I14: TED | K14: UNFPA | L14: 1736475.9 | M14: 1736475.9 | N14: 1736475.9 | O14: 1736475.9 | P14: Pago/Liquidado | Q14: -
B15: 0002 | C15: 2026 | D15: Despesas correntes | E15: Seminário Internacional de Justiça Racial e Cooperação Sul-Sul / Intercâmbio – Edição Brasil / Intercâmbio – Edição China (BRICS) | F15: 21290.000394/2026-03 | G15: DCR | H15: Katia | I15: TED | K15: IFG | L15: 4920792 | M15: 4920792 | N15: 4768939.4 | O15: 4768939.4 | P15: Pago/Liquidado | Q15: -
B16: 0002 | C16: 2026 | D16: Despesas correntes | E16: Vale do Jequitinhonha | F16: 21290.003548/2025-20 | G16: DCR | H16: Florence | I16: Convênio | K16: UNIMONTES | L16: 300000 | M16: 300000 | P16: Empenhado | Q16: -
B17: 0002 | C17: 2026 | D17: Despesas correntes | E17: PLANAPIR - ADPF 973 VIDAS NEGRAS | F17: 21290.002331/2025-01 | G17: DAI - SENAPIR | H17: ISADORA | K17: UFMA | L17: 600000 | M17: 600000 | P17: Empenhado
B18: 0002 | C18: 2026 | D18: Despesas correntes | E18: APOIO SENAPIR | F18: 21290.002528/2025-31 | I18: TED | K18: UFRB | L18: 1000000 | M18: 1000000 | N18: 1000000 | O18: 254939.28 | P18: Empenhado
B19: 0001 | C19: 2026 | D19: Despesas correntes | E19: Beatriz Nascimento - 2° Chamada Atlanticas. | F19: 21290.001921/2026-99 | G19: DPA | H19: Jean | I19: TED | K19: CNPq | L19: 500000 | M19: 450000 | P19: Empenhado
B20: 0001 | C20: 2026 | D20: Despesas correntes | K20: MGI | L20: 71216.41 | M20: 71216.41 | N20: 71216.41 | O20: 71216.41 | P20: Pago/Liquidado | Q20: -
B21: 0001 | C21: 2026 | D21: Despesas correntes | E21: Programa de Ações Afirmativas - IRBr (ADITIVO) | F21: 21290.001482/2025-33 - 21290.002314/2026-46 | G21: DPA | H21: Vitor | I21: TED | L21: 210000 | P21: Instrução Processual
B22: 0002 | C22: 2026 | D22: Despesas correntes | E22: SQPT - estruturação, implementação e operacionalização da Estratégia de Enfrentamento ao Racismo Ambiental, no âmbito do Ministério da Igualdade Racial. | F22: 21290.001965/2026-19 | G22: SQPT | I22: TED | K22: UFF | L22: 2000000 | M22: 1920000 | N22: 1000000 | O22: 1000000 | P22: Empenhado | Q22: -
Q23: -
Q24: -
G25: TOTAL | L25: =SUM(L3:L24) -> 24802643 | M25: =SUM(M3:M24) -> 20700290 | N25: =SUM(N3:N24) -> 17514014 | O25: =SUM(O3:O24) -> 16574053
G26: Dotação livre para empenho | L26: ='Consolidado 2026'!H13 -> 25131610
G27: (%) PLE/PROGRAMADO | L27: =L25/L26 -> 0.98691023

Sheet 21HN - OUV
A1: ACOMPANHAMENTO EXECUÇÃO FINALÍSTICAS - 2026
A2: UNIDADE | B2: PO | C2: ANO DE FORMALIZAÇÃO | D2: GRUPO DE DESPESA | E2: INICIATIVAS | F2: SEI | G2: DIRETORIA | H2: RESPONSÁVEL PELA FORMALIZAÇÃO | I2: INSTRUMENTO | J2: SIAFI | K2: PARCEIRO | L2: PROGRAMADO 2026 | M2: EMPENHADO 2026 | N2: LIQUIDADO 2026 | O2: PAGO 2026 | P2: STATUS | R2: OBSERVAÇÃO (PENDÊNCIAS)
A3: OUVIDORIA
G13: TOTAL | L13: =SUM(L3:L12) -> 0 | M13: =SUM(M3:M12) -> 0 | N13: =SUM(N3:N12) -> 0 | O13: =SUM(O3:O12) -> 0
G14: Dotação livre para empenho | L14: ='Consolidado 2026'!H21 -> 282800
G15: (%) PLE/PROGRAMADO | L15: =L13/L14 -> 0

Sheet 4641- SE
A1: ACOMPANHAMENTO EXECUÇÃO GESTÃO - 2025
A2: UNIDADE | B2: PO | C2: ANO DE FORMALIZAÇÃO | D2: GRUPO DE DESPESA | E2: INICIATIVAS | F2: SEI | G2: DIRETORIA | H2: RESPONSÁVEL PELA FORMALIZAÇÃO | I2: INSTRUMENTO | J2: SIAFI | K2: PARCEIRO | L2: PROGRAMADO 2026 | M2: EMPENHADO 2026 | N2: LIQUIDADO 2026 | O2: PAGO 2026 | P2: STATUS
A3: SECRETARIA EXECUTIVA | B3: 0000
G7: TOTAL | M7: =SUM(M3:M6) -> 0 | N7: =SUM(N3:N6) -> 0 | O7: =SUM(O3:O6) -> 0
G8: Dotação livre para empenho | L8: ='Consolidado 2026'!H57 -> 0
G9: (%) PLE/PROGRAMADO | L9: =L7/L8 -> #DIV/0!

Sheet Planilha1
B3: - | D3: -
B4: Planejamento | D4: junho
B5: Instrução Processual | D5: julho
B6: Aguardando Empenho | D6: agosto
B7: Empenho Parcial | D7: setembro
B8: Empenhado | D8: outubro
B9: Pago/Liquidado | D9: novembro
D10: dezembro

Sheet Consolidado - Emendas RP6
A2: PROGRAMAÇÃO | B2: DOTAÇÃO ATUALIZADA 2025 | C2: EMPENHADO 2025 | D2: LIQUIDADO 2025 | E2: PAGO 2025 | F2: (%) Execução
A4: TOTAL GERAL | B4: =SUBTOTAL(109,B6:B21) -> 16712992 | C4: =SUBTOTAL(109,C6:C18) -> 0 | D4: =SUBTOTAL(109,D6:D18) -> 0 | E4: =SUBTOTAL(109,E6:E18) -> 0 | F4: =C4/B4 -> 0
A6: SEPAR | B6: =SUBTOTAL(109,B7:B12) -> 3637992 | C6: =SUBTOTAL(109,C7:C12) -> 0 | D6: =SUBTOTAL(109,D7:D12) -> 0 | E6: =SUBTOTAL(109,E7:E12) -> 0 | F6: =C6/B6 -> 0
A7: 21FD - Fortalecimento e Desenvolvimento de Políticas para o Enfrentamento ao Racismo | B7: =SUBTOTAL(109,B8:B8) -> 0 | C7: =SUBTOTAL(109,C8:C8) -> 0 | D7: =SUBTOTAL(109,D8:D8) -> 0 | E7: =SUBTOTAL(109,E8:E8) -> 0 | F7: =C7/B7 -> #DIV/0!
A8: 0000 - Fortalecimento e Desenvolvimento de Políticas para o Enfrentamento ao Racismo - Despesas Diversas | F8: =C8/B8 -> #DIV/0!
A9: 21FB - Fomento das políticas de Ações Afirmativas | B9: =SUBTOTAL(109,B10:B10) -> 0 | C9: =SUBTOTAL(109,C10:C10) -> 0 | D9: =SUBTOTAL(109,D10:D10) -> 0 | E9: =SUBTOTAL(109,E10:E10) -> 0 | F9: =C9/B9 -> #DIV/0!
A10: 0000 - Fomento das políticas de Ações Afirmativas - Despesas Diversas | F10: =C10/B10 -> #DIV/0!
A11: 21FF - Fortalecimento de Políticas em prol da Vida e do Bem Viver da Juventude Negra | B11: =SUBTOTAL(109,B12:B12) -> 3637992 | C11: =SUBTOTAL(109,C12:C12) -> 0 | D11: =SUBTOTAL(109,D12:D12) -> 0 | E11: =SUBTOTAL(109,E12:E12) -> 0 | F11: =C11/B11 -> 0
A12: 0000 - Fortalecimento de Políticas em prol da Vida e do Bem Viver da Juventude Negra - Despesas Diversas | B12: 3637992 | F12: =C12/B12 -> 0
A13: SENAPIR | B13: =SUBTOTAL(109,B14:B15) -> 3925000 | C13: =SUBTOTAL(109,C14:C15) -> 0 | D13: =SUBTOTAL(109,D14:D15) -> 0 | E13: =SUBTOTAL(109,E14:E15) -> 0 | F13: =C13/B13 -> 0
A14: 21FC - Monitoramento, aperfeiçoamento, articulação e estruturação de políticas de promoção da igualdade racial no âmbito do SINAPIR | B14: =SUBTOTAL(109,B15:B15) -> 3925000 | C14: =SUBTOTAL(109,C15:C15) -> 0 | D14: =SUBTOTAL(109,D15:D15) -> 0 | E14: =SUBTOTAL(109,E15:E15) -> 0 | F14: =C14/B14 -> 0 | G14: R$2.375.000(Empenhados)
A15: 0000 - Monitoramento, aperfeiçoamento, articulação e estruturação de políticas de promoção da igualdade racial no âmbito do SINAPIR - Despesas Diversas | B15: 3925000 | F15: =C15/B15 -> 0
A16: SQPT | B16: =SUBTOTAL(109,B17:B18) -> 4250000 | C16: =SUBTOTAL(109,C17:C18) -> 0 | D16: =SUBTOTAL(109,D17:D18) -> 0 | E16: =SUBTOTAL(109,E17:E18) -> 0 | F16: =C16/B16 -> 0
A17: 21FE - Apoio à Implementação de Políticas para Quilombolas, Comunidades Tradicionais de Matriz Africana, Povos de Terreiro e Ciganos | B17: =SUBTOTAL(109,B18:B18) -> 4250000 | C17: =SUBTOTAL(109,C18:C18) -> 0 | D17: =SUBTOTAL(109,D18:D18) -> 0 | E17: =SUBTOTAL(109,E18:E18) -> 0 | F17: =C17/B17 -> 0
A18: 0000 - Apoio à Implementação de Políticas para Quilombolas, Comunidades Tradicionais de Matriz Africana, Povos de Terreiro e Ciganos - Despesas Diversas | B18: 4250000 | F18: =C18/B18 -> 0
A19: SQPT | B19: =SUBTOTAL(109,B20:B21) -> 4900000 | C19: =SUBTOTAL(109,C20:C21) -> 0 | D19: =SUBTOTAL(109,D20:D21) -> 0 | E19: =SUBTOTAL(109,E20:E21) -> 0 | F19: =C19/B19 -> 0
A20: 21HN - GESTAO DE POLITICAS DE ACOES AFIRMATIVAS E DE COMBATE | B20: =SUBTOTAL(109,B21:B21) -> 4900000 | C20: =SUBTOTAL(109,C21:C21) -> 0 | D20: =SUBTOTAL(109,D21:D21) -> 0 | E20: =SUBTOTAL(109,E21:E21) -> 0 | F20: =C20/B20 -> 0
A21: 0000 - GESTAO DE POLITICAS DE ACOES AFIRMATIVAS E DE COMBATE E SUPERACAO DO RACISMO - DESPESAS DIVERSAS | B21: 4900000 | F21: =C21/B21 -> 0

Sheet Diárias e Passagens
B1: AÇÃO (a) | C1: NOTA DE EMPENHO (b) | D1: VALOR EMPENHADO (c) | E1: VALOR EXECUTADO (d) | F1: DISPONÍVEL (e) = (c) - (d) | G1: (%) (f) = (d) / (c)
G2: Atualizado: 14/10/2026
A3: TOTAL GERAL | D3: =SUBTOTAL(109,D4:D94) -> 10023306 | E3: =SUBTOTAL(109,E4:E94) -> 8054722.4 | F3: =SUBTOTAL(109,F4:F94) -> 1968583.7 | G3: =E3/D3 -> 0.80359937 | K3: Número | L3: Valor Empenhado (R$) | M3: Valor Executado (R$) | N3: Disponível no Empenho (R$)
K4: 1706052026NE000019 | L4: 300000 | M4: 239426.4 | N4: 60573.6 | O4: =IF(ISERROR(VLOOKUP(K4,C:C,1,0)),"NÃO ENCONTRADO","OK") -> OK
A5: SECRETARIA EXECUTIVA | D5: =SUBTOTAL(109,D6:D16) -> 1365000 | E5: =SUBTOTAL(109,E6:E16) -> 1071110.4 | F5: =SUBTOTAL(109,F6:F16) -> 293889.6 | G5: =E5/D5 -> 0.78469626 | K5: 1706052026NE000020 | L5: 350000 | M5: 260611.05 | N5: 89388.95 | O5: =IF(ISERROR(VLOOKUP(K5,C:C,1,0)),"NÃO ENCONTRADO","OK") -> OK
A6: Subtotal - Dárias no país | D6: =SUBTOTAL(109,D7) -> 180000 | E6: =SUBTOTAL(109,E7) -> 142105.05 | F6: =SUBTOTAL(109,F7) -> 37894.95 | G6: =E6/D6 -> 0.7894725 | K6: 1706052026NE000021 | L6: 145000 | M6: 73832.5 | N6: 71167.5 | O6: =IF(ISERROR(VLOOKUP(K6,C:C,1,0)),"NÃO ENCONTRADO","OK") -> OK
A7: 33901414 - Diárias no País | B7: 2000 | C7: 1706052026NE000022 | D7: =IF(ISERROR(VLOOKUP(C7,K:L,2,0)),"",VLOOKUP(C7,K:L,2,0)) -> 180000 | E7: =IF(ISERROR(VLOOKUP(C7,K:M,3,0)),"",VLOOKUP(C7,K:M,3,0)) -> 142105.05 | F7: =IF(ISERROR(VLOOKUP(C7,K:N,3,0)),"",VLOOKUP(C7,K:N,4,0)) -> 37894.95 | G7: =E7/D7 -> 0.7894725 | K7: 1706052026NE000022 | L7: 180000 | M7: 142105.05 | N7: 37894.95 | O7: =IF(ISERROR(VLOOKUP(K7,C:C,1,0)),"NÃO ENCONTRADO","OK") -> OK
A8: Subtotal - Diárias no Exterior | D8: =SUBTOTAL(109,D9) -> 160000 | E8: =SUBTOTAL(109,E9) -> 76443.69 | F8: =SUBTOTAL(109,F9) -> 83556.31 | G8: =E8/D8 -> 0.47777306 | K8: 1706052026NE000023 | L8: 125000 | M8: 78172.5 | N8: 46827.5 | O8: =IF(ISERROR(VLOOKUP(K8,C:C,1,0)),"NÃO ENCONTRADO","OK") -> OK
A9: 33901416 - Diárias no Exterior | B9: 2000 | C9: 1706052026NE000173 | D9: =IF(ISERROR(VLOOKUP(C9,K:L,2,0)),"",VLOOKUP(C9,K:L,2,0)) -> 160000 | E9: =IF(ISERROR(VLOOKUP(C9,K:M,3,0)),"",VLOOKUP(C9,K:M,3,0)) -> 76443.69 | F9: =IF(ISERROR(VLOOKUP(C9,K:N,3,0)),"",VLOOKUP(C9,K:N,4,0)) -> 83556.31 | G9: =E9/D9 -> 0.47777306 | K9: 1706052026NE000024 | L9: 245000 | M9: 219695 | N9: 25305 | O9: =IF(ISERROR(VLOOKUP(K9,C:C,1,0)),"NÃO ENCONTRADO","OK") -> OK
A10: Subtotal - Passagens no país | D10: =SUBTOTAL(109,D11:D12) -> 630000 | E10: =SUBTOTAL(109,E11:E12) -> 564595.11 | F10: =SUBTOTAL(109,F11:F12) -> 65404.89 | G10: =E10/D10 -> 0.89618271 | K10: 1706052026NE000025 | L10: 270000 | M10: 247800 | N10: 22200 | O10: =IF(ISERROR(VLOOKUP(K10,C:C,1,0)),"NÃO ENCONTRADO","OK") -> OK
A11: 33903301 - Passagens para o País | B11: 2000 | C11: 1706052026NE000159 | D11: =IF(ISERROR(VLOOKUP(C11,K:L,2,0)),"",VLOOKUP(C11,K:L,2,0)) -> 150000 | E11: =IF(ISERROR(VLOOKUP(C11,K:M,3,0)),"",VLOOKUP(C11,K:M,3,0)) -> 104895.83 | F11: =IF(ISERROR(VLOOKUP(C11,K:N,3,0)),"",VLOOKUP(C11,K:N,4,0)) -> 45104.17 | G11: =E11/D11 -> 0.69930553 | K11: 1706052026NE000026 | L11: 25000 | M11: 16449.27 | N11: 8550.73 | O11: =IF(ISERROR(VLOOKUP(K11,C:C,1,0)),"NÃO ENCONTRADO","OK") -> OK
A12: 33903301 - Passagens para o País | B12: 2000 | C12: 2010572026NE000046 | D12: =IF(ISERROR(VLOOKUP(C12,K:L,2,0)),"",VLOOKUP(C12,K:L,2,0)) -> 480000 | E12: =IF(ISERROR(VLOOKUP(C12,K:M,3,0)),"",VLOOKUP(C12,K:M,3,0)) -> 459699.28 | F12: =IF(ISERROR(VLOOKUP(C12,K:N,3,0)),"",VLOOKUP(C12,K:N,4,0)) -> 20300.72 | G12: =E12/D12 -> 0.95770683 | K12: 1706052026NE000027 | L12: 270000 | M12: 212337.65 | N12: 57662.35 | O12: =IF(ISERROR(VLOOKUP(K12,C:C,1,0)),"NÃO ENCONTRADO","OK") -> OK
A13: Subtotal - Passagens para o Exterior | D13: =SUBTOTAL(109,D14) -> 270000 | E13: =SUBTOTAL(109,E14) -> 209794.05 | F13: =SUBTOTAL(109,F14) -> 60205.95 | G13: =E13/D13 -> 0.777015 | K13: 1706052026NE000028 | L13: 110000 | M13: 54637.5 | N13: 55362.5 | O13: =IF(ISERROR(VLOOKUP(K13,C:C,1,0)),"NÃO ENCONTRADO","OK") -> OK
A14: 33903302 - Passagens para o Exterior | B14: 2000 | C14: 1706052026NE000160 | D14: =IF(ISERROR(VLOOKUP(C14,K:L,2,0)),"",VLOOKUP(C14,K:L,2,0)) -> 270000 | E14: =IF(ISERROR(VLOOKUP(C14,K:M,3,0)),"",VLOOKUP(C14,K:M,3,0)) -> 209794.05 | F14: =IF(ISERROR(VLOOKUP(C14,K:N,3,0)),"",VLOOKUP(C14,K:N,4,0)) -> 60205.95 | G14: =E14/D14 -> 0.777015 | K14: 1706052026NE000029 | L14: 110000 | M14: 21267.4 | N14: 88732.6 | O14: =IF(ISERROR(VLOOKUP(K14,C:C,1,0)),"NÃO ENCONTRADO","OK") -> OK
A15: Subtotal - Diarias Colaboradores Eventuais | D15: =SUBTOTAL(109,D16) -> 125000 | E15: =SUBTOTAL(109,E16) -> 78172.5 | F15: =SUBTOTAL(109,F16:F16) -> 46827.5 | G15: =E15/D15 -> 0.62538 | K15: 1706052026NE000030 | L15: 60000 | M15: 59500 | N15: 500 | O15: =IF(ISERROR(VLOOKUP(K15,C:C,1,0)),"NÃO ENCONTRADO","OK") -> OK
A16: 33903601 - Diárias a Colaboradores Eventuais no pais | B16: 2000 | C16: 1706052026NE000023 | D16: =IF(ISERROR(VLOOKUP(C16,K:L,2,0)),"",VLOOKUP(C16,K:L,2,0)) -> 125000 | E16: =IF(ISERROR(VLOOKUP(C16,K:M,3,0)),"",VLOOKUP(C16,K:M,3,0)) -> 78172.5 | F16: =IF(ISERROR(VLOOKUP(C16,K:N,3,0)),"",VLOOKUP(C16,K:N,4,0)) -> 46827.5 | G16: =E16/D16 -> 0.62538 | K16: 1706052026NE000031 | L16: 110000 | M16: 51137.1 | N16: 58862.9 | O16: =IF(ISERROR(VLOOKUP(K16,C:C,1,0)),"NÃO ENCONTRADO","OK") -> OK
A17: GABINETE | D17: =SUBTOTAL(109,D18:D36) -> 2699000 | E17: =SUBTOTAL(109,E18:E36) -> 2247510.3 | F17: =SUBTOTAL(109,F18:F36) -> 451489.73 | G17: =E17/D17 -> 0.83271963 | K17: 1706052026NE000032 | L17: 60000 | M17: 25410 | N17: 34590 | O17: =IF(ISERROR(VLOOKUP(K17,C:C,1,0)),"NÃO ENCONTRADO","OK") -> OK
A18: Subtotal - Seguro Viagem | D18: =SUBTOTAL(109,D19:D20) -> 20000 | E18: =SUBTOTAL(109,E19:E20) -> 16803.05 | F18: =SUBTOTAL(109,F19:F20) -> 3196.95 | G18: =E18/D18 -> 0.8401525 | K18: 1706052026NE000033 | L18: 295000 | M18: 227526.16 | N18: 67473.84 | O18: =IF(ISERROR(VLOOKUP(K18,C:C,1,0)),"NÃO ENCONTRADO","OK") -> OK
A19: 339039 - Seguro Viagem | B19: 2000 | C19: 1706052026NE000157 | D19: =IF(ISERROR(VLOOKUP(C19,K:L,2,0)),"",VLOOKUP(C19,K:L,2,0)) -> 20000 | E19: =IF(ISERROR(VLOOKUP(C19,K:M,3,0)),"",VLOOKUP(C19,K:M,3,0)) -> 16803.05 | F19: =IF(ISERROR(VLOOKUP(C19,K:N,3,0)),"",VLOOKUP(C19,K:N,4,0)) -> 3196.95 | G19: =E19/D19 -> 0.8401525 | K19: 1706052026NE000034 | L19: 215000 | M19: 155870 | N19: 59130 | O19: =IF(ISERROR(VLOOKUP(K19,C:C,1,0)),"NÃO ENCONTRADO","OK") -> OK
B20: 2000 | D20: =IF(ISERROR(VLOOKUP(C20,K:L,2,0)),"",VLOOKUP(C20,K:L,2,0)) | E20: =IF(ISERROR(VLOOKUP(C20,K:M,3,0)),"",VLOOKUP(C20,K:M,3,0)) | F20: =IF(ISERROR(VLOOKUP(C20,K:N,3,0)),"",VLOOKUP(C20,K:N,4,0)) | K20: 1706052026NE000157 | L20: 20000 | M20: 16803.05 | N20: 3196.95 | O20: =IF(ISERROR(VLOOKUP(K20,C:C,1,0)),"NÃO ENCONTRADO","OK") -> OK
A21: Subtotal - Indenizações e restituições | D21: =SUBTOTAL(109,D22) -> 4000 | E21: =SUBTOTAL(109,E22) -> 1980.1 | F21: =SUBTOTAL(109,F22) -> 2019.9 | G21: =E21/D21 -> 0.495025 | K21: 1706052026NE000158 | L21: 600000 | M21: 518495.86 | N21: 81504.14 | O21: =IF(ISERROR(VLOOKUP(K21,C:C,1,0)),"NÃO ENCONTRADO","OK") -> OK
A22: 339093 - Indenizações e Restituições | B22: 2000 | C22: 1706052026NE000213 | D22: =IF(ISERROR(VLOOKUP(C22,K:L,2,0)),"",VLOOKUP(C22,K:L,2,0)) -> 4000 | E22: =IF(ISERROR(VLOOKUP(C22,K:M,3,0)),"",VLOOKUP(C22,K:M,3,0)) -> 1980.1 | F22: =IF(ISERROR(VLOOKUP(C22,K:N,3,0)),"",VLOOKUP(C22,K:N,4,0)) -> 2019.9 | G22: =E22/D22 -> 0.495025 | K22: 1706052026NE000159 | L22: 150000 | M22: 104895.83 | N22: 45104.17 | O22: =IF(ISERROR(VLOOKUP(K22,C:C,1,0)),"NÃO ENCONTRADO","OK") -> OK
A23: Subtotal - Passagens no país | D23: =SUBTOTAL(109,D24:D25) -> 1220000 | E23: =SUBTOTAL(109,E24:E25) -> 1156783.3 | F23: =SUBTOTAL(109,F24:F25) -> 63216.66 | G23: =E23/D23 -> 0.94818307 | K23: 1706052026NE000160 | L23: 270000 | M23: 209794.05 | N23: 60205.95 | O23: =IF(ISERROR(VLOOKUP(K23,C:C,1,0)),"NÃO ENCONTRADO","OK") -> OK
A24: 33903301 - Passagens para o País | B24: 2000 | C24: 1706052026NE000019 | D24: =IF(ISERROR(VLOOKUP(C24,K:L,2,0)),"",VLOOKUP(C24,K:L,2,0)) -> 300000 | E24: =IF(ISERROR(VLOOKUP(C24,K:M,3,0)),"",VLOOKUP(C24,K:M,3,0)) -> 239426.4 | F24: =IF(ISERROR(VLOOKUP(C24,K:N,3,0)),"",VLOOKUP(C24,K:N,4,0)) -> 60573.6 | G24: =E24/D24 -> 0.798088 | K24: 1706052026NE000161 | L24: 160000 | M24: 117337.09 | N24: 42662.91 | O24: =IF(ISERROR(VLOOKUP(K24,C:C,1,0)),"NÃO ENCONTRADO","OK") -> OK
B25: 2000 | C25: 2010572026NE000045 | D25: =IF(ISERROR(VLOOKUP(C25,K:L,2,0)),"",VLOOKUP(C25,K:L,2,0)) -> 920000 | E25: =IF(ISERROR(VLOOKUP(C25,K:M,3,0)),"",VLOOKUP(C25,K:M,3,0)) -> 917356.94 | F25: =IF(ISERROR(VLOOKUP(C25,K:N,3,0)),"",VLOOKUP(C25,K:N,4,0)) -> 2643.06 | G25: =E25/D25 -> 0.99712711 | K25: 1706052026NE000162 | L25: 300000 | M25: 134543.72 | N25: 165456.28 | O25: =IF(ISERROR(VLOOKUP(K25,C:C,1,0)),"NÃO ENCONTRADO","OK") -> OK
A26: Subtotal - Passagens para o Exterior | D26: =SUBTOTAL(109,D27:D27) -> 600000 | E26: =SUBTOTAL(109,E27:E27) -> 518495.86 | F26: =SUBTOTAL(109,F27:F27) -> 81504.14 | G26: =E26/D26 -> 0.86415977 | K26: 1706052026NE000163 | L26: 0 | M26: 0 | N26: 0 | O26: =IF(ISERROR(VLOOKUP(K26,C:C,1,0)),"NÃO ENCONTRADO","OK") -> OK
A27: 33903302 - Passagens para o Exterior | B27: 2000 | C27: 1706052026NE000158 | D27: =IF(ISERROR(VLOOKUP(C27,K:L,2,0)),"",VLOOKUP(C27,K:L,2,0)) -> 600000 | E27: =IF(ISERROR(VLOOKUP(C27,K:M,3,0)),"",VLOOKUP(C27,K:M,3,0)) -> 518495.86 | F27: =IF(ISERROR(VLOOKUP(C27,K:N,3,0)),"",VLOOKUP(C27,K:N,4,0)) -> 81504.14 | G27: =E27/D27 -> 0.86415977 | K27: 1706052026NE000164 | L27: 80000 | M27: 73634.46 | N27: 6365.54 | O27: =IF(ISERROR(VLOOKUP(K27,C:C,1,0)),"NÃO ENCONTRADO","OK") -> OK
A28: Subtotal - Dárias no país | D28: =SUBTOTAL(109,D29:D30) -> 350000 | E28: =SUBTOTAL(109,E29:E30) -> 260611.05 | F28: =SUBTOTAL(109,F29:F30) -> 89388.95 | G28: =E28/D28 -> 0.744603 | K28: 1706052026NE000165 | L28: 50000 | M28: 0 | N28: 50000 | O28: =IF(ISERROR(VLOOKUP(K28,C:C,1,0)),"NÃO ENCONTRADO","OK") -> OK
A29: 33901414 - Diárias no País | B29: 2000 | C29: 1706052026NE000020 | D29: =IF(ISERROR(VLOOKUP(C29,K:L,2,0)),"",VLOOKUP(C29,K:L,2,0)) -> 350000 | E29: =IF(ISERROR(VLOOKUP(C29,K:M,3,0)),"",VLOOKUP(C29,K:M,3,0)) -> 260611.05 | F29: =IF(ISERROR(VLOOKUP(C29,K:N,3,0)),"",VLOOKUP(C29,K:N,4,0)) -> 89388.95 | G29: =E29/D29 -> 0.744603 | K29: 1706052026NE000166 | L29: 80000 | M29: 37236.91 | N29: 42763.09 | O29: =IF(ISERROR(VLOOKUP(K29,C:C,1,0)),"NÃO ENCONTRADO","OK") -> OK
B30: 2000 | D30: =IF(ISERROR(VLOOKUP(C30,K:L,2,0)),"",VLOOKUP(C30,K:L,2,0)) | E30: =IF(ISERROR(VLOOKUP(C30,K:M,3,0)),"",VLOOKUP(C30,K:M,3,0)) | F30: =IF(ISERROR(VLOOKUP(C30,K:N,3,0)),"",VLOOKUP(C30,K:N,4,0)) | K30: 1706052026NE000167 | L30: 100000 | M30: 80152.01 | N30: 19847.99 | O30: =IF(ISERROR(VLOOKUP(K30,C:C,1,0)),"NÃO ENCONTRADO","OK") -> OK
A31: Subtotal - Dárias no Exterior | D31: =SUBTOTAL(109,D32:D33) -> 310000 | E31: =SUBTOTAL(109,E32:E33) -> 208456.28 | F31: =SUBTOTAL(109,F32:F33) -> 101543.72 | G31: =E31/D31 -> 0.67243961 | K31: 1706052026NE000168 | L31: 250000 | M31: 133499.69 | N31: 116500.31 | O31: =IF(ISERROR(VLOOKUP(K31,C:C,1,0)),"NÃO ENCONTRADO","OK") -> OK
A32: 33901416 - Diárias no Exterior | B32: 2000 | C32: 1706052026NE000171 | D32: =IF(ISERROR(VLOOKUP(C32,K:L,2,0)),"",VLOOKUP(C32,K:L,2,0)) -> 310000 | E32: =IF(ISERROR(VLOOKUP(C32,K:M,3,0)),"",VLOOKUP(C32,K:M,3,0)) -> 208456.28 | F32: =IF(ISERROR(VLOOKUP(C32,K:N,3,0)),"",VLOOKUP(C32,K:N,4,0)) -> 101543.72 | G32: =E32/D32 -> 0.67243961 | K32: 1706052026NE000169 | L32: 200000 | M32: 130366 | N32: 69634 | O32: =IF(ISERROR(VLOOKUP(K32,C:C,1,0)),"NÃO ENCONTRADO","OK") -> OK
B33: 2000 | D33: =IF(ISERROR(VLOOKUP(C33,K:L,2,0)),"",VLOOKUP(C33,K:L,2,0)) | E33: =IF(ISERROR(VLOOKUP(C33,K:M,3,0)),"",VLOOKUP(C33,K:M,3,0)) | F33: =IF(ISERROR(VLOOKUP(C33,K:N,3,0)),"",VLOOKUP(C33,K:N,4,0)) | K33: 1706052026NE000170 | L33: 40000 | M33: 18889.4 | N33: 21110.6 | O33: =IF(ISERROR(VLOOKUP(K33,C:C,1,0)),"NÃO ENCONTRADO","OK") -> OK
A34: Subtotal - Diarias Colaboradores Eventuais | D34: =SUBTOTAL(109,D35:D36) -> 195000 | E34: =SUBTOTAL(109,E35:E36) -> 84380.59 | F34: =SUBTOTAL(109,F35:F36) -> 110619.41 | G34: =E34/D34 -> 0.43272097 | K34: 1706052026NE000171 | L34: 310000 | M34: 208456.28 | N34: 101543.72 | O34: =IF(ISERROR(VLOOKUP(K34,C:C,1,0)),"NÃO ENCONTRADO","OK") -> OK
A35: 33903601 - Diárias a Colaboradores Eventuais no pais | B35: 2000 | C35: 1706052026NE000021 | D35: =IF(ISERROR(VLOOKUP(C35,K:L,2,0)),"",VLOOKUP(C35,K:L,2,0)) -> 145000 | E35: =IF(ISERROR(VLOOKUP(C35,K:M,3,0)),"",VLOOKUP(C35,K:M,3,0)) -> 73832.5 | F35: =IF(ISERROR(VLOOKUP(C35,K:N,3,0)),"",VLOOKUP(C35,K:N,4,0)) -> 71167.5 | G35: =E35/D35 -> 0.50918966 | K35: 1706052026NE000172 | L35: 50000 | M35: 10548.09 | N35: 39451.91 | O35: =IF(ISERROR(VLOOKUP(K35,C:C,1,0)),"NÃO ENCONTRADO","OK") -> OK
A36: 339036033 - Diárias a Colaboradores Eventuais no Exterior | B36: 200 | C36: 1706052026NE000172 | D36: =IF(ISERROR(VLOOKUP(C36,K:L,2,0)),"",VLOOKUP(C36,K:L,2,0)) -> 50000 | E36: =IF(ISERROR(VLOOKUP(C36,K:M,3,0)),"",VLOOKUP(C36,K:M,3,0)) -> 10548.09 | F36: =IF(ISERROR(VLOOKUP(C36,K:N,3,0)),"",VLOOKUP(C36,K:N,4,0)) -> 39451.91 | G36: =E36/D36 -> 0.2109618 | K36: 1706052026NE000173 | L36: 160000 | M36: 76443.69 | N36: 83556.31 | O36: =IF(ISERROR(VLOOKUP(K36,C:C,1,0)),"NÃO ENCONTRADO","OK") -> OK
A37: SENAPIR | D37: =SUBTOTAL(109,D38:D49) -> 1830000 | E37: =SUBTOTAL(109,E38:E49) -> 1412955.7 | F37: =SUBTOTAL(109,F38:F49) -> 417044.27 | G37: =E37/D37 -> 0.77210696 | K37: 1706052026NE000174 | L37: 220000 | M37: 126024.69 | N37: 93975.31 | O37: =IF(ISERROR(VLOOKUP(K37,C:C,1,0)),"NÃO ENCONTRADO","OK") -> OK
A38: Subtotal - Dárias no país | D38: =SUBTOTAL(109,D39:D40) -> 270000 | E38: =SUBTOTAL(109,E39:E40) -> 212337.65 | F38: =SUBTOTAL(109,F39:F40) -> 57662.35 | G38: =E38/D38 -> 0.78643574 | K38: 1706052026NE000175 | L38: 50000 | M38: 38272.68 | N38: 11727.32 | O38: =IF(ISERROR(VLOOKUP(K38,C:C,1,0)),"NÃO ENCONTRADO","OK") -> OK
A39: 33901414 - Diárias no País | B39: 21FC | C39: 1706052026NE000027 | D39: =IF(ISERROR(VLOOKUP(C39,K:L,2,0)),"",VLOOKUP(C39,K:L,2,0)) -> 270000 | E39: =IF(ISERROR(VLOOKUP(C39,K:M,3,0)),"",VLOOKUP(C39,K:M,3,0)) -> 212337.65 | F39: =IF(ISERROR(VLOOKUP(C39,K:N,3,0)),"",VLOOKUP(C39,K:N,4,0)) -> 57662.35 | G39: =E39/D39 -> 0.78643574 | K39: 1706052026NE000213 | L39: 4000 | M39: 1980.1 | N39: 2019.9 | O39: =IF(ISERROR(VLOOKUP(K39,C:C,1,0)),"NÃO ENCONTRADO","OK") -> OK
B40: 21FC | D40: =IF(ISERROR(VLOOKUP(C40,K:L,2,0)),"",VLOOKUP(C40,K:L,2,0)) | E40: =IF(ISERROR(VLOOKUP(C40,K:M,3,0)),"",VLOOKUP(C40,K:M,3,0)) | F40: =IF(ISERROR(VLOOKUP(C40,K:N,3,0)),"",VLOOKUP(C40,K:N,4,0)) | K40: 1706052026NE000224 | L40: 0 | M40: 0 | N40: 0 | O40: =IF(ISERROR(VLOOKUP(K40,C:C,1,0)),"NÃO ENCONTRADO","OK") -> NÃO ENCONTRADO
A41: Subtotal - Diárias no Exterior | D41: =SUBTOTAL(109,D42) -> 220000 | E41: =SUBTOTAL(109,E42) -> 126024.69 | F41: =SUBTOTAL(109,F42) -> 93975.31 | G41: =E41/D41 -> 0.5728395 | K41: 1706052026NE000225 | L41: 19306.1 | M41: 17529.7 | N41: 1776.4 | O41: =IF(ISERROR(VLOOKUP(K41,C:C,1,0)),"NÃO ENCONTRADO","OK") -> OK
A42: 33901416 - Diárias no Exterior | B42: 21FC | C42: 1706052026NE000174 | D42: =IF(ISERROR(VLOOKUP(C42,K:L,2,0)),"",VLOOKUP(C42,K:L,2,0)) -> 220000 | E42: =IF(ISERROR(VLOOKUP(C42,K:M,3,0)),"",VLOOKUP(C42,K:M,3,0)) -> 126024.69 | F42: =IF(ISERROR(VLOOKUP(C42,K:N,3,0)),"",VLOOKUP(C42,K:N,4,0)) -> 93975.31 | G42: =E42/D42 -> 0.5728395 | K42: 1706052026NE000226 | L42: 40000 | M42: 30018.86 | N42: 9981.14 | O42: =IF(ISERROR(VLOOKUP(K42,C:C,1,0)),"NÃO ENCONTRADO","OK") -> OK
A43: Subtotal - Passagens no país | D43: =SUBTOTAL(109,D44:D44) -> 160000 | E43: =SUBTOTAL(109,E44:E44) -> 117337.09 | F43: =SUBTOTAL(109,F44:F44) -> 42662.91 | G43: =E43/D43 -> 0.73335681 | K43: 1706052026NE000228 | L43: 5034.35 | M43: 5034.35 | N43: 0 | O43: =IF(ISERROR(VLOOKUP(K43,C:C,1,0)),"NÃO ENCONTRADO","OK") -> NÃO ENCONTRADO
A44: 33903301 - Passagens para o País | B44: 21FC | C44: 1706052026NE000161 | D44: =IF(ISERROR(VLOOKUP(C44,K:L,2,0)),"",VLOOKUP(C44,K:L,2,0)) -> 160000 | E44: =IF(ISERROR(VLOOKUP(C44,K:M,3,0)),"",VLOOKUP(C44,K:M,3,0)) -> 117337.09 | F44: =IF(ISERROR(VLOOKUP(C44,K:N,3,0)),"",VLOOKUP(C44,K:N,4,0)) -> 42662.91 | G44: =E44/D44 -> 0.73335681 | K44: 1706052026NE000239 | L44: 2970.66 | M44: 1630.23 | N44: 1340.43 | O44: =IF(ISERROR(VLOOKUP(K44,C:C,1,0)),"NÃO ENCONTRADO","OK") -> NÃO ENCONTRADO
A45: 33903301 - Passagens para o País | B45: 21FC | C45: 2010572026NE000047 | D45: =IF(ISERROR(VLOOKUP(C45,K:L,2,0)),"",VLOOKUP(C45,K:L,2,0)) -> 770000 | E45: =IF(ISERROR(VLOOKUP(C45,K:M,3,0)),"",VLOOKUP(C45,K:M,3,0)) -> 768075.08 | F45: =IF(ISERROR(VLOOKUP(C45,K:N,3,0)),"",VLOOKUP(C45,K:N,4,0)) -> 1924.92 | G45: =E45/D45 -> 0.9975001 | K45: 2010572026NE000045 | L45: 920000 | M45: 917356.94 | N45: 2643.06 | O45: =IF(ISERROR(VLOOKUP(K45,C:C,1,0)),"NÃO ENCONTRADO","OK") -> OK
A46: Subtotal - Passagens para o Exterior | D46: =SUBTOTAL(109,D47) -> 300000 | E46: =SUBTOTAL(109,E47) -> 134543.72 | F46: =SUBTOTAL(109,F47) -> 165456.28 | G46: =E46/D46 -> 0.44847907 | K46: 2010572026NE000046 | L46: 480000 | M46: 459699.28 | N46: 20300.72 | O46: =IF(ISERROR(VLOOKUP(K46,C:C,1,0)),"NÃO ENCONTRADO","OK") -> OK
A47: 33903302 - Passagens para o Exterior | B47: 21FC | C47: 1706052026NE000162 | D47: =IF(ISERROR(VLOOKUP(C47,K:L,2,0)),"",VLOOKUP(C47,K:L,2,0)) -> 300000 | E47: =IF(ISERROR(VLOOKUP(C47,K:M,3,0)),"",VLOOKUP(C47,K:M,3,0)) -> 134543.72 | F47: =IF(ISERROR(VLOOKUP(C47,K:N,3,0)),"",VLOOKUP(C47,K:N,4,0)) -> 165456.28 | G47: =E47/D47 -> 0.44847907 | K47: 2010572026NE000047 | L47: 770000 | M47: 768075.08 | N47: 1924.92 | O47: =IF(ISERROR(VLOOKUP(K47,C:C,1,0)),"NÃO ENCONTRADO","OK") -> OK
A48: Subtotal - Diarias Colaboradores Eventuais | D48: =SUBTOTAL(109,D49) -> 110000 | E48: =SUBTOTAL(109,E49) -> 54637.5 | F48: =SUBTOTAL(109,F49) -> 55362.5 | G48: =E48/D48 -> 0.49670455 | K48: 2010572026NE000048 | L48: 720000 | M48: 719184.47 | N48: 815.53 | O48: =IF(ISERROR(VLOOKUP(K48,C:C,1,0)),"NÃO ENCONTRADO","OK") -> OK
A49: 33903602 - Diárias a Colaboradores Eventuais no pais | B49: 21FC | C49: 1706052026NE000028 | D49: =IF(ISERROR(VLOOKUP(C49,K:L,2,0)),"",VLOOKUP(C49,K:L,2,0)) -> 110000 | E49: =IF(ISERROR(VLOOKUP(C49,K:M,3,0)),"",VLOOKUP(C49,K:M,3,0)) -> 54637.5 | F49: =IF(ISERROR(VLOOKUP(C49,K:N,3,0)),"",VLOOKUP(C49,K:N,4,0)) -> 55362.5 | G49: =E49/D49 -> 0.49670455 | K49: 2010572026NE000049 | L49: 130000 | M49: 116778.59 | N49: 13221.41 | O49: =IF(ISERROR(VLOOKUP(K49,C:C,1,0)),"NÃO ENCONTRADO","OK") -> OK
A50: SEPAR | D50: =SUBTOTAL(109,D51:D67) -> 970000 | E50: =SUBTOTAL(109,E51:E67) -> 581099.2 | F50: =SUBTOTAL(109,F51:F67) -> 388900.8 | G50: =E50/D50 -> 0.59907134 | K50: 2010572026NE000050 | L50: 780000 | M50: 763955.66 | N50: 16044.34 | O50: =IF(ISERROR(VLOOKUP(K50,C:C,1,0)),"NÃO ENCONTRADO","OK") -> OK
A51: Subtotal - Dárias no país | D51: =SUBTOTAL(109,D52:D53) -> 220000 | E51: =SUBTOTAL(109,E52:E53) -> 72404.5 | F51: =SUBTOTAL(109,F52:F53) -> 147595.5 | G51: =E51/D51 -> 0.32911136 | K51: 2010572026NE000051 | L51: 200000 | M51: 138972.66 | N51: 61027.34 | O51: =IF(ISERROR(VLOOKUP(K51,C:C,1,0)),"NÃO ENCONTRADO","OK") -> OK
A52: 33901414 - Diárias no País | B52: 21FF | C52: 1706052026NE000029 | D52: =IF(ISERROR(VLOOKUP(C52,K:L,2,0)),"",VLOOKUP(C52,K:L,2,0)) -> 110000 | E52: =IF(ISERROR(VLOOKUP(C52,K:M,3,0)),"",VLOOKUP(C52,K:M,3,0)) -> 21267.4 | F52: =IF(ISERROR(VLOOKUP(C52,K:N,3,0)),"",VLOOKUP(C52,K:N,4,0)) -> 88732.6 | G52: =E52/D52 -> 0.19334 | O52: =IF(ISERROR(VLOOKUP(K52,C:C,1,0)),"NÃO ENCONTRADO","OK") -> NÃO ENCONTRADO
B53: 21HN | C53: 1706052026NE000031 | D53: =IF(ISERROR(VLOOKUP(C53,K:L,2,0)),"",VLOOKUP(C53,K:L,2,0)) -> 110000 | E53: =IF(ISERROR(VLOOKUP(C53,K:M,3,0)),"",VLOOKUP(C53,K:M,3,0)) -> 51137.1 | F53: =IF(ISERROR(VLOOKUP(C53,K:N,3,0)),"",VLOOKUP(C53,K:N,4,0)) -> 58862.9 | G53: =E53/D53 -> 0.46488273 | O53: =IF(ISERROR(VLOOKUP(K53,C:C,1,0)),"NÃO ENCONTRADO","OK") -> NÃO ENCONTRADO
A54: Subtotal - Diárias no Exterior | D54: =SUBTOTAL(109,D55:D56) -> 90000 | E54: =SUBTOTAL(109,E55:E56) -> 57162.08 | F54: =SUBTOTAL(109,F55:F56) -> 32837.92 | G54: =E54/D54 -> 0.63513422 | O54: =IF(ISERROR(VLOOKUP(K54,C:C,1,0)),"NÃO ENCONTRADO","OK") -> NÃO ENCONTRADO
A55: 33901416 - Diárias no Exterior | B55: 21FF | C55: 1706052026NE000175 | D55: =IF(ISERROR(VLOOKUP(C55,K:L,2,0)),"",VLOOKUP(C55,K:L,2,0)) -> 50000 | E55: =IF(ISERROR(VLOOKUP(C55,K:M,3,0)),"",VLOOKUP(C55,K:M,3,0)) -> 38272.68 | F55: =IF(ISERROR(VLOOKUP(C55,K:N,3,0)),"",VLOOKUP(C55,K:N,4,0)) -> 11727.32 | G55: =E55/D55 -> 0.7654536 | O55: =IF(ISERROR(VLOOKUP(K55,C:C,1,0)),"NÃO ENCONTRADO","OK") -> NÃO ENCONTRADO
B56: 21HN | C56: 1706052026NE000170 | D56: =IF(ISERROR(VLOOKUP(C56,K:L,2,0)),"",VLOOKUP(C56,K:L,2,0)) -> 40000 | E56: =IF(ISERROR(VLOOKUP(C56,K:M,3,0)),"",VLOOKUP(C56,K:M,3,0)) -> 18889.4 | F56: =IF(ISERROR(VLOOKUP(C56,K:N,3,0)),"",VLOOKUP(C56,K:N,4,0)) -> 21110.6 | G56: =E56/D56 -> 0.472235 | O56: =IF(ISERROR(VLOOKUP(K56,C:C,1,0)),"NÃO ENCONTRADO","OK") -> NÃO ENCONTRADO
A57: Subtotal - Passagens no país | D57: =SUBTOTAL(109,D58:D61) -> 380000 | E57: =SUBTOTAL(109,E58:E61) -> 255751.25 | F57: =SUBTOTAL(109,F58:F61) -> 124248.75 | G57: =E57/D57 -> 0.67302961 | O57: =IF(ISERROR(VLOOKUP(K57,C:C,1,0)),"NÃO ENCONTRADO","OK") -> NÃO ENCONTRADO
A58: 33903301 - Passagens para o País | B58: 21FF | C58: 1706052026NE000165 | D58: =IF(ISERROR(VLOOKUP(C58,K:L,2,0)),"",VLOOKUP(C58,K:L,2,0)) -> 50000 | E58: =IF(ISERROR(VLOOKUP(C58,K:M,3,0)),"",VLOOKUP(C58,K:M,3,0)) -> 0 | F58: =IF(ISERROR(VLOOKUP(C58,K:N,3,0)),"",VLOOKUP(C58,K:N,4,0)) -> 50000 | G58: =E58/D58 -> 0 | O58: =IF(ISERROR(VLOOKUP(K58,C:C,1,0)),"NÃO ENCONTRADO","OK") -> NÃO ENCONTRADO
B59: 21HN | C59: 1706052026NE000163 | D59: =IF(ISERROR(VLOOKUP(C59,K:L,2,0)),"",VLOOKUP(C59,K:L,2,0)) -> 0 | E59: =IF(ISERROR(VLOOKUP(C59,K:M,3,0)),"",VLOOKUP(C59,K:M,3,0)) -> 0 | F59: =IF(ISERROR(VLOOKUP(C59,K:N,3,0)),"",VLOOKUP(C59,K:N,4,0)) -> 0 | O59: =IF(ISERROR(VLOOKUP(K59,C:C,1,0)),"NÃO ENCONTRADO","OK") -> NÃO ENCONTRADO
B60: 21FF | C60: 2010572026NE000049 | D60: =IF(ISERROR(VLOOKUP(C60,K:L,2,0)),"",VLOOKUP(C60,K:L,2,0)) -> 130000 | E60: =IF(ISERROR(VLOOKUP(C60,K:M,3,0)),"",VLOOKUP(C60,K:M,3,0)) -> 116778.59 | F60: =IF(ISERROR(VLOOKUP(C60,K:N,3,0)),"",VLOOKUP(C60,K:N,4,0)) -> 13221.41 | G60: =E60/D60 -> 0.89829685 | O60: =IF(ISERROR(VLOOKUP(K60,C:C,1,0)),"NÃO ENCONTRADO","OK") -> NÃO ENCONTRADO
B61: 21HN | C61: 2010572026NE000051 | D61: =IF(ISERROR(VLOOKUP(C61,K:L,2,0)),"",VLOOKUP(C61,K:L,2,0)) -> 200000 | E61: =IF(ISERROR(VLOOKUP(C61,K:M,3,0)),"",VLOOKUP(C61,K:M,3,0)) -> 138972.66 | F61: =IF(ISERROR(VLOOKUP(C61,K:N,3,0)),"",VLOOKUP(C61,K:N,4,0)) -> 61027.34 | G61: =E61/D61 -> 0.6948633 | O61: =IF(ISERROR(VLOOKUP(K61,C:C,1,0)),"NÃO ENCONTRADO","OK") -> NÃO ENCONTRADO
A62: Subtotal - Passagens para o Exterior | D62: =SUBTOTAL(109,D63:D64) -> 160000 | E62: =SUBTOTAL(109,E63:E64) -> 110871.37 | F62: =SUBTOTAL(109,F63:F64) -> 49128.63 | G62: =E62/D62 -> 0.69294606 | O62: =IF(ISERROR(VLOOKUP(K62,C:C,1,0)),"NÃO ENCONTRADO","OK") -> NÃO ENCONTRADO
A63: 33903302 - Passagens para o Exterior | B63: 21FF | C63: 1706052026NE000166 | D63: =IF(ISERROR(VLOOKUP(C63,K:L,2,0)),"",VLOOKUP(C63,K:L,2,0)) -> 80000 | E63: =IF(ISERROR(VLOOKUP(C63,K:M,3,0)),"",VLOOKUP(C63,K:M,3,0)) -> 37236.91 | F63: =IF(ISERROR(VLOOKUP(C63,K:N,3,0)),"",VLOOKUP(C63,K:N,4,0)) -> 42763.09 | G63: =E63/D63 -> 0.46546138 | O63: =IF(ISERROR(VLOOKUP(K63,C:C,1,0)),"NÃO ENCONTRADO","OK") -> NÃO ENCONTRADO
B64: 21HN | C64: 1706052026NE000164 | D64: =IF(ISERROR(VLOOKUP(C64,K:L,2,0)),"",VLOOKUP(C64,K:L,2,0)) -> 80000 | E64: =IF(ISERROR(VLOOKUP(C64,K:M,3,0)),"",VLOOKUP(C64,K:M,3,0)) -> 73634.46 | F64: =IF(ISERROR(VLOOKUP(C64,K:N,3,0)),"",VLOOKUP(C64,K:N,4,0)) -> 6365.54 | G64: =E64/D64 -> 0.92043075 | O64: =IF(ISERROR(VLOOKUP(K64,C:C,1,0)),"NÃO ENCONTRADO","OK") -> NÃO ENCONTRADO
A65: Subtotal - Diarias Colaboradores Eventuais | D65: =SUBTOTAL(109,D66:D67) -> 120000 | E65: =SUBTOTAL(109,E66:E67) -> 84910 | F65: =SUBTOTAL(109,F66:F67) -> 35090 | G65: =E65/D65 -> 0.70758333 | O65: =IF(ISERROR(VLOOKUP(K65,C:C,1,0)),"NÃO ENCONTRADO","OK") -> NÃO ENCONTRADO
A66: 33903602 - Diárias a Colaboradores Eventuais no pais | B66: 21FF | C66: 1706052026NE000030 | D66: =IF(ISERROR(VLOOKUP(C66,K:L,2,0)),"",VLOOKUP(C66,K:L,2,0)) -> 60000 | E66: =IF(ISERROR(VLOOKUP(C66,K:M,3,0)),"",VLOOKUP(C66,K:M,3,0)) -> 59500 | F66: =IF(ISERROR(VLOOKUP(C66,K:N,3,0)),"",VLOOKUP(C66,K:N,4,0)) -> 500 | G66: =E66/D66 -> 0.99166667
B67: 21HN | C67: 1706052026NE000032 | D67: =IF(ISERROR(VLOOKUP(C67,K:L,2,0)),"",VLOOKUP(C67,K:L,2,0)) -> 60000 | E67: =IF(ISERROR(VLOOKUP(C67,K:M,3,0)),"",VLOOKUP(C67,K:M,3,0)) -> 25410 | F67: =IF(ISERROR(VLOOKUP(C67,K:N,3,0)),"",VLOOKUP(C67,K:N,4,0)) -> 34590 | G67: =E67/D67 -> 0.4235
A68: SQPT | D68: =SUBTOTAL(109,D69:D80) -> 1780000 | E68: =SUBTOTAL(109,E69:E80) -> 1446598.3 | F68: =SUBTOTAL(109,F69:F80) -> 333401.67 | G68: =E68/D68 -> 0.81269569
A69: Subtotal - Dárias no país | D69: =SUBTOTAL(109,D70) -> 295000 | E69: =SUBTOTAL(109,E70) -> 227526.16 | F69: =SUBTOTAL(109,F70) -> 67473.84 | G69: =E69/D69 -> 0.77127512
A70: 33901414 - Diárias no País | B70: 21FE | C70: 1706052026NE000033 | D70: =IF(ISERROR(VLOOKUP(C70,K:L,2,0)),"",VLOOKUP(C70,K:L,2,0)) -> 295000 | E70: =IF(ISERROR(VLOOKUP(C70,K:M,3,0)),"",VLOOKUP(C70,K:M,3,0)) -> 227526.16 | F70: =IF(ISERROR(VLOOKUP(C70,K:N,3,0)),"",VLOOKUP(C70,K:N,4,0)) -> 67473.84 | G70: =E70/D70 -> 0.77127512
A71: Subtotal - Diárias no Exterior | D71: =SUBTOTAL(109,D72:D72) -> 200000 | E71: =SUBTOTAL(109,E72:E72) -> 130366 | F71: =SUBTOTAL(109,F72:F72) -> 69634 | G71: =E71/D71 -> 0.65183
A72: 33901416 - Diárias no Exterior | B72: 21FE | C72: 1706052026NE000169 | D72: =IF(ISERROR(VLOOKUP(C72,K:L,2,0)),"",VLOOKUP(C72,K:L,2,0)) -> 200000 | E72: =IF(ISERROR(VLOOKUP(C72,K:M,3,0)),"",VLOOKUP(C72,K:M,3,0)) -> 130366 | F72: =IF(ISERROR(VLOOKUP(C72,K:N,3,0)),"",VLOOKUP(C72,K:N,4,0)) -> 69634 | G72: =E72/D72 -> 0.65183
A73: Subtotal - Passagens no país | D73: =SUBTOTAL(109,D74:D75) -> 820000 | E73: =SUBTOTAL(109,E74:E75) -> 799336.48 | F73: =SUBTOTAL(109,F74:F75) -> 20663.52 | G73: =E73/D73 -> 0.97480059
A74: 33903301 - Passagens para o País | B74: 21FE | C74: 1706052026NE000167 | D74: =IF(ISERROR(VLOOKUP(C74,K:L,2,0)),"",VLOOKUP(C74,K:L,2,0)) -> 100000 | E74: =IF(ISERROR(VLOOKUP(C74,K:M,3,0)),"",VLOOKUP(C74,K:M,3,0)) -> 80152.01 | F74: =IF(ISERROR(VLOOKUP(C74,K:N,3,0)),"",VLOOKUP(C74,K:N,4,0)) -> 19847.99 | G74: =E74/D74 -> 0.8015201
B75: 21FE | C75: 2010572026NE000048 | D75: =IF(ISERROR(VLOOKUP(C75,K:L,2,0)),"",VLOOKUP(C75,K:L,2,0)) -> 720000 | E75: =IF(ISERROR(VLOOKUP(C75,K:M,3,0)),"",VLOOKUP(C75,K:M,3,0)) -> 719184.47 | F75: =IF(ISERROR(VLOOKUP(C75,K:N,3,0)),"",VLOOKUP(C75,K:N,4,0)) -> 815.53 | G75: =E75/D75 -> 0.99886732
A76: Subtotal - Passagens para o Exterior | D76: =SUBTOTAL(109,D77) -> 250000 | E76: =SUBTOTAL(109,E77) -> 133499.69 | F76: =SUBTOTAL(109,F77) -> 116500.31 | G76: =E76/D76 -> 0.53399876
A77: 33903302 - Passagens para o Exterior | B77: 21FE | C77: 1706052026NE000168 | D77: =IF(ISERROR(VLOOKUP(C77,K:L,2,0)),"",VLOOKUP(C77,K:L,2,0)) -> 250000 | E77: =IF(ISERROR(VLOOKUP(C77,K:M,3,0)),"",VLOOKUP(C77,K:M,3,0)) -> 133499.69 | F77: =IF(ISERROR(VLOOKUP(C77,K:N,3,0)),"",VLOOKUP(C77,K:N,4,0)) -> 116500.31 | G77: =E77/D77 -> 0.53399876
A78: Subtotal - Diarias Colaboradores Eventuais | D78: =SUBTOTAL(109,D79:D80) -> 215000 | E78: =SUBTOTAL(109,E79:E80) -> 155870 | F78: =SUBTOTAL(109,F79:F80) -> 59130 | G78: =E78/D78 -> 0.72497674
A79: 33903602 - Diárias a Colaboradores Eventuais no pais | B79: 21FE | C79: 1706052026NE000034 | D79: =IF(ISERROR(VLOOKUP(C79,K:L,2,0)),"",VLOOKUP(C79,K:L,2,0)) -> 215000 | E79: =IF(ISERROR(VLOOKUP(C79,K:M,3,0)),"",VLOOKUP(C79,K:M,3,0)) -> 155870 | F79: =IF(ISERROR(VLOOKUP(C79,K:N,3,0)),"",VLOOKUP(C79,K:N,4,0)) -> 59130 | G79: =E79/D79 -> 0.72497674
A80: 33903603 - Diárias a Colaboradores Eventuais no Exterior | B80: 21FE | D80: =IF(ISERROR(VLOOKUP(C80,K:L,2,0)),"",VLOOKUP(C80,K:L,2,0)) | E80: =IF(ISERROR(VLOOKUP(C80,K:M,3,0)),"",VLOOKUP(C80,K:M,3,0)) | F80: =IF(ISERROR(VLOOKUP(C80,K:N,3,0)),"",VLOOKUP(C80,K:N,4,0))
A81: CNPIR | D81: =SUBTOTAL(109,D82:D94) -> 1379306.1 | E81: =SUBTOTAL(109,E82:E94) -> 1295448.5 | F81: =SUBTOTAL(109,F82:F94) -> 83857.61 | G81: =E81/D81 -> 0.93920305
A82: Subtotal - Dárias no país | D82: =SUBTOTAL(109,D83:D84) -> 25000 | E82: =SUBTOTAL(109,E83:E84) -> 16449.27 | F82: =SUBTOTAL(109,F83:F84) -> 8550.73 | G82: =E82/D82 -> 0.6579708
A83: 33901414 - Diárias no País | B83: 21FG | C83: 1706052026NE000026 | D83: =IF(ISERROR(VLOOKUP(C83,K:L,2,0)),"",VLOOKUP(C83,K:L,2,0)) -> 25000 | E83: =IF(ISERROR(VLOOKUP(C83,K:M,3,0)),"",VLOOKUP(C83,K:M,3,0)) -> 16449.27 | F83: =IF(ISERROR(VLOOKUP(C83,K:N,3,0)),"",VLOOKUP(C83,K:N,4,0)) -> 8550.73 | G83: =E83/D83 -> 0.6579708
A84: 33901414 - Diárias no País | B84: 21FG | D84: =IF(ISERROR(VLOOKUP(C84,K:L,2,0)),"",VLOOKUP(C84,K:L,2,0)) | E84: =IF(ISERROR(VLOOKUP(C84,K:M,3,0)),"",VLOOKUP(C84,K:M,3,0)) | F84: =IF(ISERROR(VLOOKUP(C84,K:N,3,0)),"",VLOOKUP(C84,K:N,4,0))
A85: Subtotal - Passagens no país | D85: =SUBTOTAL(109,D86:D89) -> 820000 | E85: =SUBTOTAL(109,E86:E89) -> 793974.52 | F85: =SUBTOTAL(109,F86:F89) -> 26025.48 | G85: =E85/D85 -> 0.96826161
A86: 33903301 - Passagens para o País | B86: 21FG | C86: 2010572026NE000050 | D86: =IF(ISERROR(VLOOKUP(C86,K:L,2,0)),"",VLOOKUP(C86,K:L,2,0)) -> 780000 | E86: =IF(ISERROR(VLOOKUP(C86,K:M,3,0)),"",VLOOKUP(C86,K:M,3,0)) -> 763955.66 | F86: =IF(ISERROR(VLOOKUP(C86,K:N,3,0)),"",VLOOKUP(C86,K:N,4,0)) -> 16044.34 | G86: =E86/D86 -> 0.97943033
A87: 33903302 - Passagens para o Exterior | B87: 21FG | C87: 1706052026NE000226 | D87: =IF(ISERROR(VLOOKUP(C87,K:L,2,0)),"",VLOOKUP(C87,K:L,2,0)) -> 40000 | E87: =IF(ISERROR(VLOOKUP(C87,K:M,3,0)),"",VLOOKUP(C87,K:M,3,0)) -> 30018.86 | F87: =IF(ISERROR(VLOOKUP(C87,K:N,3,0)),"",VLOOKUP(C87,K:N,4,0)) -> 9981.14 | G87: =E87/D87 -> 0.7504715
A88: 33903301 - Passagens para o País | B88: 21FG | D88: =IF(ISERROR(VLOOKUP(C88,K:L,2,0)),"",VLOOKUP(C88,K:L,2,0)) | E88: =IF(ISERROR(VLOOKUP(C88,K:M,3,0)),"",VLOOKUP(C88,K:M,3,0)) | F88: =IF(ISERROR(VLOOKUP(C88,K:N,3,0)),"",VLOOKUP(C88,K:N,4,0))
A89: Subtotal - Diarias Colaboradores Eventuais | D89: =SUBTOTAL(109,D90:D94) -> 534306.1 | E89: =SUBTOTAL(109,E90:E94) -> 485024.7 | F89: =SUBTOTAL(109,F90:F94) -> 49281.4 | G89: =E89/D89 -> 0.9077656
A90: 33903602 - Diárias a Colaboradores Eventuais no pais | B90: 21FG | C90: 1706052026NE000025 | D90: =IF(ISERROR(VLOOKUP(C90,K:L,2,0)),"",VLOOKUP(C90,K:L,2,0)) -> 270000 | E90: =IF(ISERROR(VLOOKUP(C90,K:M,3,0)),"",VLOOKUP(C90,K:M,3,0)) -> 247800 | F90: =IF(ISERROR(VLOOKUP(C90,K:N,3,0)),"",VLOOKUP(C90,K:N,4,0)) -> 22200 | G90: =E90/D90 -> 0.91777778
A91: 33903602 - Diárias a Colaboradores Eventuais no pais | B91: 21FG | D91: =IF(ISERROR(VLOOKUP(C91,K:L,2,0)),"",VLOOKUP(C91,K:L,2,0)) | E91: =IF(ISERROR(VLOOKUP(C91,K:M,3,0)),"",VLOOKUP(C91,K:M,3,0)) | F91: =IF(ISERROR(VLOOKUP(C91,K:N,3,0)),"",VLOOKUP(C91,K:N,4,0))
A92: 33903646 - Diárias a Conselheiros no pais | B92: 21FG | C92: 1706052026NE000024 | D92: =IF(ISERROR(VLOOKUP(C92,K:L,2,0)),"",VLOOKUP(C92,K:L,2,0)) -> 245000 | E92: =IF(ISERROR(VLOOKUP(C92,K:M,3,0)),"",VLOOKUP(C92,K:M,3,0)) -> 219695 | F92: =IF(ISERROR(VLOOKUP(C92,K:N,3,0)),"",VLOOKUP(C92,K:N,4,0)) -> 25305 | G92: =E92/D92 -> 0.89671429
A93: 33903646 - Diárias a Conselheiros no pais | B93: 21FG | D93: =IF(ISERROR(VLOOKUP(C93,K:L,2,0)),"",VLOOKUP(C93,K:L,2,0)) | E93: =IF(ISERROR(VLOOKUP(C93,K:M,3,0)),"",VLOOKUP(C93,K:M,3,0)) | F93: =IF(ISERROR(VLOOKUP(C93,K:N,3,0)),"",VLOOKUP(C93,K:N,4,0))
A94: 33903603 - Diárias a Colaboradores Eventuais no Exterior | B94: 21FG | C94: 1706052026NE000225 | D94: =IF(ISERROR(VLOOKUP(C94,K:L,2,0)),"",VLOOKUP(C94,K:L,2,0)) -> 19306.1 | E94: =IF(ISERROR(VLOOKUP(C94,K:M,3,0)),"",VLOOKUP(C94,K:M,3,0)) -> 17529.7 | F94: =IF(ISERROR(VLOOKUP(C94,K:N,3,0)),"",VLOOKUP(C94,K:N,4,0)) -> 1776.4 | G94: =E94/D94 -> 0.90798763
